Workbook
Name Catergory: 'Accident & Incident Detail'!$I$2
Name Investigationtype: 'Lookup Sheets'!$X$2:$X$8
Name Investigationtype: 'Lookup Sheets'!$X$2:$X$8

Sheet Data
B1: 1 | C1: 1 | D1: 1 | E1: 1 | F1: 1 | G1: 1 | H1: 1 | I1: 1 | J1: 1 | K1: 1 | L1: 1 | M1: 1 | N1: 1 | O1: 1 | P1: 1 | Q1: 1 | R1: 1 | S1: 1 | T1: 1 | U1: 1 | V1: 1 | W1: 1 | X1: 1 | Y1: 1 | Z1: 1 | AA1: 1 | AB1: 1 | AC1: 1 | AD1: 1 | AE1: 1 | AF1: 1 | AG1: 1 | AH1: 1 | AI1: 1 | AJ1: 1 | AK1: 1
A3: Actuals | N3: WK 1
B4: 2301 | C4: 2302 | D4: 2303 | E4: 2304 | F4: 2305 | G4: 2306 | H4: 2307 | I4: 2308 | J4: 2309 | K4: 2310 | L4: 2311 | M4: 2312 | N4: 2313 | O4: 2401 | P4: 2402 | Q4: 2403 | R4: 2404 | S4: 2405 | T4: 2406 | U4: 2407 | V4: 2408 | W4: 2409 | X4: 2410 | Y4: 2411 | Z4: 2412 | AA4: 2413 | AB4: 2501 | AC4: 2502 | AD4: 2503 | AE4: 2504 | AF4: 2505 | AG4: 2506 | AH4: 2507 | AI4: 2508 | AJ4: 2509 | AK4: 2510 | AL4: 2511 | AM4: 2512 | AN4: 2513
B5: {=SUM(($A$6='Accident & Incident Detail'!$I$3:$I$3433)*(Data!B4='Accident & Incident Detail'!$C$3:$C$3433))} -> 0 | C5: {=SUM(($A$6='Accident & Incident Detail'!$I$3:$I$3433)*(Data!C4='Accident & Incident Detail'!$C$3:$C$3433))} -> 0 | D5: {=SUM(($A$6='Accident & Incident Detail'!$I$3:$I$3433)*(Data!D4='Accident & Incident Detail'!$C$3:$C$3433))} -> 0 | E5: {=SUM(($A$6='Accident & Incident Detail'!$I$3:$I$3433)*(Data!E4='Accident & Incident Detail'!$C$3:$C$3433))} -> 0 | F5: {=SUM(($A$6='Accident & Incident Detail'!$I$3:$I$3433)*(Data!F4='Accident & Incident Detail'!$C$3:$C$3433))} -> 0 | G5: {=SUM(($A$6='Accident & Incident Detail'!$I$3:$I$3433)*(Data!G4='Accident & Incident Detail'!$C$3:$C$3433))} -> 0 | H5: {=SUM(($A$6='Accident & Incident Detail'!$I$3:$I$3433)*(Data!H4='Accident & Incident Detail'!$C$3:$C$3433))} -> 0 | I5: {=SUM(($A$6='Accident & Incident Detail'!$I$3:$I$3433)*(Data!I4='Accident & Incident Detail'!$C$3:$C$3433))} -> 0 | ... AA5: {=SUM(($A$6='Accident & Incident Detail'!$I$3:$I$3433)*(Data!AA4='Accident & Incident Detail'!$C$3:$C$3433))} -> 4 | AB5: {=SUM(($A$6='Accident & Incident Detail'!$I$3:$I$3434)*(Data!AB4='Accident & Incident Detail'!$C$3:$C$3434))} -> 4 | AC5: {=SUM(($A$6='Accident & Incident Detail'!$I$3:$I$3433)*(Data!AC4='Accident & Incident Detail'!$C$3:$C$3433))} -> 1 | AD5: {=SUM(($A$6='Accident & Incident Detail'!$I$3:$I$3433)*(Data!AD4='Accident & Incident Detail'!$C$3:$C$3433))} -> 3 | AE5: {=SUM(($A$6='Accident & Incident Detail'!$I$3:$I$3433)*(Data!AE4='Accident & Incident Detail'!$C$3:$C$3433))} -> 2 | AF5: {=SUM(($A$6='Accident & Incident Detail'!$I$3:$I$3433)*(Data!AF4='Accident & Incident Detail'!$C$3:$C$3433))} -> 0 | AG5: {=SUM(($A$6='Accident & Incident Detail'!$I$3:$I$3433)*(Data!AG4='Accident & Incident Detail'!$C$3:$C$3433))} -> 1 | AH5: {=SUM(($A$6='Accident & Incident Detail'!$I$3:$I$3433)*(Data!AH4='Accident & Incident Detail'!$C$3:$C$3433))} -> 4 | AI5: {=SUM(($A$6='Accident & Incident Detail'!$I$3:$I$3433)*(Data!AI4='Accident & Incident Detail'!$C$3:$C$3433))} -> 0 | AJ5: {=SUM(($A$6='Accident & Incident Detail'!$I$3:$I$3433)*(Data!AJ4='Accident & Incident Detail'!$C$3:$C$3433))} -> 4 | ... AN5: {=SUM(($A$6='Accident & Incident Detail'!$I$3:$I$3433)*(Data!AN4='Accident & Incident Detail'!$C$3:$C$3433))} -> 0 | AO5: =SUM(AB5:AN5) -> 24
A6: Staff Accident | B6: =B5-B7 -> 0 | C6: =C5-C7 -> 0 | D6: =D5-D7 -> 0 | E6: =E5-E7 -> -1 | F6: =F5-F7 -> 0 | G6: =G5-G7 -> -1 | H6: =H5-H7 -> 0 | I6: =I5-I7 -> 0 | ... Y6: =Y5-Y7 -> 5 | Z6: {=SUM(($A$6='Accident & Incident Detail'!$I$3:$I$3433)*(Data!Z5='Accident & Incident Detail'!$C$3:$C$3433))} -> 0 | AA6: {=SUM(($A$6='Accident & Incident Detail'!$I$3:$I$3433)*(Data!AA5='Accident & Incident Detail'!$C$3:$C$3433))} -> 0 | AB6: =AB5-AB7 -> 3 | AC6: =AC5-AC7 -> 1 | AD6: =AD5-AD7 -> 3 | AE6: =AE5-AE7 -> 2 | AF6: =AF5-AF7 -> 0 | AG6: =AG5-AG7 -> 1 | AH6: =AH5-AH7 -> 4 | AI6: =AI5-AI7 -> 0 | ... AN6: =AN5-AN7 -> 0 | AO6: =SUM(AB6:AN6) -> 22
A7: Staff LTA | E7: 1 | G7: 1 | P7: 1 | Z7: {=SUM(($A$6='Accident & Incident Detail'!$I$3:$I$3433)*(Data!Z6='Accident & Incident Detail'!$C$3:$C$3433))} -> 0 | AA7: {=SUM(($A$6='Accident & Incident Detail'!$I$3:$I$3433)*(Data!AA6='Accident & Incident Detail'!$C$3:$C$3433))} -> 0 | AB7: 1 | AJ7: 1 | AO7: =SUM(AB7:AN7) -> 2
A8: Assaults | B8: {=SUM(($A$8='Accident & Incident Detail'!$I$3:$I$3433)*(Data!B4='Accident & Incident Detail'!$C$3:$C$3433))} -> 0 | C8: {=SUM(($A$8='Accident & Incident Detail'!$I$3:$I$3433)*(Data!C4='Accident & Incident Detail'!$C$3:$C$3433))} -> 0 | D8: {=SUM(($A$8='Accident & Incident Detail'!$I$3:$I$3433)*(Data!D4='Accident & Incident Detail'!$C$3:$C$3433))} -> 0 | E8: {=SUM(($A$8='Accident & Incident Detail'!$I$3:$I$3433)*(Data!E4='Accident & Incident Detail'!$C$3:$C$3433))} -> 0 | F8: {=SUM(($A$8='Accident & Incident Detail'!$I$3:$I$3433)*(Data!F4='Accident & Incident Detail'!$C$3:$C$3433))} -> 0 | G8: {=SUM(($A$8='Accident & Incident Detail'!$I$3:$I$3433)*(Data!G4='Accident & Incident Detail'!$C$3:$C$3433))} -> 0 | H8: {=SUM(($A$8='Accident & Incident Detail'!$I$3:$I$3433)*(Data!H4='Accident & Incident Detail'!$C$3:$C$3433))} -> 0 | I8: {=SUM(($A$8='Accident & Incident Detail'!$I$3:$I$3433)*(Data!I4='Accident & Incident Detail'!$C$3:$C$3433))} -> 0 | ... Y8: {=SUM(($A$8='Accident & Incident Detail'!$I$3:$I$3433)*(Data!Y4='Accident & Incident Detail'!$C$3:$C$3433))} -> 1 | Z8: {=SUM(($A$6='Accident & Incident Detail'!$I$3:$I$3433)*(Data!Z7='Accident & Incident Detail'!$C$3:$C$3433))} -> 0 | AA8: {=SUM(($A$6='Accident & Incident Detail'!$I$3:$I$3433)*(Data!AA7='Accident & Incident Detail'!$C$3:$C$3433))} -> 0 | AB8: {=SUM(($A$8='Accident & Incident Detail'!$I$3:$I$3433)*(Data!AB7='Accident & Incident Detail'!$C$3:$C$3433))} -> 0 | AC8: {=SUM(($A$8='Accident & Incident Detail'!$I$3:$I$3433)*(Data!AC4='Accident & Incident Detail'!$C$3:$C$3433))} -> 4 | AD8: {=SUM(($A$8='Accident & Incident Detail'!$I$3:$I$3433)*(Data!AD4='Accident & Incident Detail'!$C$3:$C$3433))} -> 6 | AE8: {=SUM(($A$8='Accident & Incident Detail'!$I$3:$I$3433)*(Data!AE4='Accident & Incident Detail'!$C$3:$C$3433))} -> 2 | AF8: {=SUM(($A$8='Accident & Incident Detail'!$I$3:$I$3433)*(Data!AF4='Accident & Incident Detail'!$C$3:$C$3433))} -> 1 | AG8: {=SUM(($A$8='Accident & Incident Detail'!$I$3:$I$3433)*(Data!AG4='Accident & Incident Detail'!$C$3:$C$3433))} -> 1 | AH8: {=SUM(($A$8='Accident & Incident Detail'!$I$3:$I$3433)*(Data!AH4='Accident & Incident Detail'!$C$3:$C$3433))} -> 3 | AI8: {=SUM(($A$8='Accident & Incident Detail'!$I$3:$I$3433)*(Data!AI4='Accident & Incident Detail'!$C$3:$C$3433))} -> 1 | AJ8: {=SUM(($A$8='Accident & Incident Detail'!$I$3:$I$3433)*(Data!AJ4='Accident & Incident Detail'!$C$3:$C$3433))} -> 0 | ... AN8: {=SUM(($A$8='Accident & Incident Detail'!$I$3:$I$3433)*(Data!AN4='Accident & Incident Detail'!$C$3:$C$3433))} -> 0 | AO8: =SUM(AB8:AN8) -> 22
A9: Movement | B9: {=SUM(($A$9='Accident & Incident Detail'!$I$3:$I$3433)*(Data!B4='Accident & Incident Detail'!$C$3:$C$3433))} -> 0 | C9: {=SUM(($A$9='Accident & Incident Detail'!$I$3:$I$3433)*(Data!C4='Accident & Incident Detail'!$C$3:$C$3433))} -> 0 | D9: {=SUM(($A$9='Accident & Incident Detail'!$I$3:$I$3433)*(Data!D4='Accident & Incident Detail'!$C$3:$C$3433))} -> 0 | E9: {=SUM(($A$9='Accident & Incident Detail'!$I$3:$I$3433)*(Data!E4='Accident & Incident Detail'!$C$3:$C$3433))} -> 0 | F9: {=SUM(($A$9='Accident & Incident Detail'!$I$3:$I$3433)*(Data!F4='Accident & Incident Detail'!$C$3:$C$3433))} -> 0 | G9: {=SUM(($A$9='Accident & Incident Detail'!$I$3:$I$3433)*(Data!G4='Accident & Incident Detail'!$C$3:$C$3433))} -> 0 | H9: {=SUM(($A$9='Accident & Incident Detail'!$I$3:$I$3433)*(Data!H4='Accident & Incident Detail'!$C$3:$C$3433))} -> 0 | I9: {=SUM(($A$9='Accident & Incident Detail'!$I$3:$I$3433)*(Data!I4='Accident & Incident Detail'!$C$3:$C$3433))} -> 0 | ... Y9: {=SUM(($A$9='Accident & Incident Detail'!$I$3:$I$3433)*(Data!Y4='Accident & Incident Detail'!$C$3:$C$3433))} -> 4 | Z9: {=SUM(($A$9='Accident & Incident Detail'!$I$3:$I$3433)*(Data!Z8='Accident & Incident Detail'!$C$3:$C$3433))} -> 0 | AA9: {=SUM(($A$9='Accident & Incident Detail'!$I$3:$I$3433)*(Data!AA8='Accident & Incident Detail'!$C$3:$C$3433))} -> 0 | AB9: {=SUM(($A$9='Accident & Incident Detail'!$I$3:$I$3433)*(Data!AB8='Accident & Incident Detail'!$C$3:$C$3433))} -> 0 | AC9: {=SUM(($A$9='Accident & Incident Detail'!$I$3:$I$3433)*(Data!AC4='Accident & Incident Detail'!$C$3:$C$3433))} -> 1 | AD9: {=SUM(($A$9='Accident & Incident Detail'!$I$3:$I$3433)*(Data!AD4='Accident & Incident Detail'!$C$3:$C$3433))} -> 4 | AE9: {=SUM(($A$9='Accident & Incident Detail'!$I$3:$I$3433)*(Data!AE4='Accident & Incident Detail'!$C$3:$C$3433))} -> 6 | AF9: {=SUM(($A$9='Accident & Incident Detail'!$I$3:$I$3433)*(Data!AF4='Accident & Incident Detail'!$C$3:$C$3433))} -> 1 | AG9: {=SUM(($A$9='Accident & Incident Detail'!$I$3:$I$3433)*(Data!AG4='Accident & Incident Detail'!$C$3:$C$3433))} -> 6 | AH9: {=SUM(($A$9='Accident & Incident Detail'!$I$3:$I$3433)*(Data!AH4='Accident & Incident Detail'!$C$3:$C$3433))} -> 5 | AI9: {=SUM(($A$9='Accident & Incident Detail'!$I$3:$I$3433)*(Data!AI4='Accident & Incident Detail'!$C$3:$C$3433))} -> 8 | AJ9: {=SUM(($A$9='Accident & Incident Detail'!$I$3:$I$3433)*(Data!AJ4='Accident & Incident Detail'!$C$3:$C$3433))} -> 9 | ... AN9: {=SUM(($A$9='Accident & Incident Detail'!$I$3:$I$3433)*(Data!AN4='Accident & Incident Detail'!$C$3:$C$3433))} -> 0 | AO9: =SUM(AB9:AN9) -> 46
A10: Non-Movement | B10: {=SUM(($A$10='Accident & Incident Detail'!$I$3:$I$3433)*(Data!B4='Accident & Incident Detail'!$C$3:$C$3433))} -> 0 | C10: {=SUM(($A$10='Accident & Incident Detail'!$I$3:$I$3433)*(Data!C4='Accident & Incident Detail'!$C$3:$C$3433))} -> 0 | D10: {=SUM(($A$10='Accident & Incident Detail'!$I$3:$I$3433)*(Data!D4='Accident & Incident Detail'!$C$3:$C$3433))} -> 0 | E10: {=SUM(($A$10='Accident & Incident Detail'!$I$3:$I$3433)*(Data!E4='Accident & Incident Detail'!$C$3:$C$3433))} -> 0 | F10: {=SUM(($A$10='Accident & Incident Detail'!$I$3:$I$3433)*(Data!F4='Accident & Incident Detail'!$C$3:$C$3433))} -> 0 | G10: {=SUM(($A$10='Accident & Incident Detail'!$I$3:$I$3433)*(Data!G4='Accident & Incident Detail'!$C$3:$C$3433))} -> 0 | H10: {=SUM(($A$10='Accident & Incident Detail'!$I$3:$I$3433)*(Data!H4='Accident & Incident Detail'!$C$3:$C$3433))} -> 0 | I10: {=SUM(($A$10='Accident & Incident Detail'!$I$3:$I$3433)*(Data!I4='Accident & Incident Detail'!$C$3:$C$3433))} -> 0 | ... Y10: {=SUM(($A$10='Accident & Incident Detail'!$I$3:$I$3433)*(Data!Y4='Accident & Incident Detail'!$C$3:$C$3433))} -> 0 | Z10: {=SUM(($A$6='Accident & Incident Detail'!$I$3:$I$3433)*(Data!Z9='Accident & Incident Detail'!$C$3:$C$3433))} -> 0 | AA10: {=SUM(($A$6='Accident & Incident Detail'!$I$3:$I$3433)*(Data!AA9='Accident & Incident Detail'!$C$3:$C$3433))} -> 0 | AB10: {=SUM(($A$10='Accident & Incident Detail'!$I$3:$I$3434)*(Data!AB9='Accident & Incident Detail'!$C$3:$C$3434))} -> 0 | AC10: {=SUM(($A$10='Accident & Incident Detail'!$I$3:$I$3434)*(Data!AC9='Accident & Incident Detail'!$C$3:$C$3434))} -> 0 | AD10: {=SUM(($A$10='Accident & Incident Detail'!$I$3:$I$3434)*(Data!AD9='Accident & Incident Detail'!$C$3:$C$3434))} -> 0 | AE10: {=SUM(($A$10='Accident & Incident Detail'!$I$3:$I$3434)*(Data!AE9='Accident & Incident Detail'!$C$3:$C$3434))} -> 0 | AF10: {=SUM(($A$10='Accident & Incident Detail'!$I$3:$I$3434)*(Data!AF9='Accident & Incident Detail'!$C$3:$C$3434))} -> 0 | AG10: {=SUM(($A$10='Accident & Incident Detail'!$I$3:$I$3434)*(Data!AG9='Accident & Incident Detail'!$C$3:$C$3434))} -> 0 | AH10: {=SUM(($A$10='Accident & Incident Detail'!$I$3:$I$3433)*(Data!AH4='Accident & Incident Detail'!$C$3:$C$3433))} -> 1 | AI10: {=SUM(($A$10='Accident & Incident Detail'!$I$3:$I$3433)*(Data!AI4='Accident & Incident Detail'!$C$3:$C$3433))} -> 0 | AJ10: {=SUM(($A$10='Accident & Incident Detail'!$I$3:$I$3433)*(Data!AJ4='Accident & Incident Detail'!$C$3:$C$3433))} -> 0 | AK10: {=SUM(($A$10='Accident & Incident Detail'!$I$3:$I$3433)*(Data!AK4='Accident & Incident Detail'!$C$3:$C$3433))} -> 0 | AL10: {=SUM(($A$10='Accident & Incident Detail'!$I$3:$I$3433)*(Data!AL4='Accident & Incident Detail'!$C$3:$C$3433))} -> 0 | AM10: {=SUM(($A$10='Accident & Incident Detail'!$I$3:$I$3433)*(Data!AM4='Accident & Incident Detail'!$C$3:$C$3433))} -> 0 | AN10: {=SUM(($A$10='Accident & Incident Detail'!$I$3:$I$3433)*(Data!AN4='Accident & Incident Detail'!$C$3:$C$3433))} -> 0 | AO10: =SUM(AB10:AN10) -> 1
A11: Accidents Total | B11: =SUM(B6:B10) -> 0 | C11: =SUM(C6:C10) -> 0 | D11: =SUM(D6:D10) -> 0 | E11: =SUM(E6:E10) -> 0 | F11: =SUM(F6:F10) -> 0 | G11: =SUM(G6:G10) -> 0 | H11: =SUM(H6:H10) -> 0 | I11: =SUM(I6:I10) -> 0 | ... Y11: =SUM(Y6:Y10) -> 10 | Z11: {=SUM(($A$6='Accident & Incident Detail'!$I$3:$I$3433)*(Data!Z10='Accident & Incident Detail'!$C$3:$C$3433))} -> 0 | AA11: {=SUM(($A$6='Accident & Incident Detail'!$I$3:$I$3433)*(Data!AA10='Accident & Incident Detail'!$C$3:$C$3433))} -> 0 | AB11: =SUM(AB6:AB10) -> 4 | AC11: =SUM(AC6:AC10) -> 6 | AD11: =SUM(AD6:AD10) -> 13 | AE11: =SUM(AE6:AE10) -> 10 | AF11: =SUM(AF6:AF10) -> 2 | AG11: =SUM(AG6:AG10) -> 8 | AH11: =SUM(AH6:AH10) -> 13 | AI11: =SUM(AI6:AI10) -> 9 | ... AN11: =SUM(AN6:AN10) -> 0 | AO11: =SUM(AB11:AN11) -> 93
A12: Vandalism | B12: {=SUM(($A$12='Accident & Incident Detail'!$E$3:$E$3434)*(Data!B4='Accident & Incident Detail'!$C$3:$C$3434))} -> 0 | C12: {=SUM(($A$12='Accident & Incident Detail'!$E$3:$E$3434)*(Data!C4='Accident & Incident Detail'!$C$3:$C$3434))} -> 0 | D12: {=SUM(($A$12='Accident & Incident Detail'!$E$3:$E$3434)*(Data!D4='Accident & Incident Detail'!$C$3:$C$3434))} -> 0 | E12: {=SUM(($A$12='Accident & Incident Detail'!$E$3:$E$3434)*(Data!E4='Accident & Incident Detail'!$C$3:$C$3434))} -> 0 | F12: {=SUM(($A$12='Accident & Incident Detail'!$E$3:$E$3434)*(Data!F4='Accident & Incident Detail'!$C$3:$C$3434))} -> 0 | G12: {=SUM(($A$12='Accident & Incident Detail'!$E$3:$E$3434)*(Data!G4='Accident & Incident Detail'!$C$3:$C$3434))} -> 0 | H12: {=SUM(($A$12='Accident & Incident Detail'!$E$3:$E$3434)*(Data!H4='Accident & Incident Detail'!$C$3:$C$3434))} -> 0 | I12: {=SUM(($A$12='Accident & Incident Detail'!$E$3:$E$3434)*(Data!I4='Accident & Incident Detail'!$C$3:$C$3434))} -> 0 | ... Y12: {=SUM(($A$12='Accident & Incident Detail'!$E$3:$E$3434)*(Data!Y4='Accident & Incident Detail'!$C$3:$C$3434))} -> 3 | Z12: {=SUM(($A$12='Accident & Incident Detail'!$E$3:$E$3433)*(Data!Z4='Accident & Incident Detail'!$C$3:$C$3433))} -> 7 | AA12: {=SUM(($A$12='Accident & Incident Detail'!$E$3:$E$3433)*(Data!AA4='Accident & Incident Detail'!$C$3:$C$3433))} -> 12 | AB12: {=SUM(($A$12='Accident & Incident Detail'!$E$3:$E$3435)*(Data!AB4='Accident & Incident Detail'!$C$3:$C$3435))} -> 11 | AC12: {=SUM(($A$12='Accident & Incident Detail'!$E$3:$E$3435)*(Data!AC4='Accident & Incident Detail'!$C$3:$C$3435))} -> 10 | AD12: {=SUM(($A$12='Accident & Incident Detail'!$E$3:$E$3435)*(Data!AD4='Accident & Incident Detail'!$C$3:$C$3435))} -> 14 | AE12: {=SUM(($A$12='Accident & Incident Detail'!$E$3:$E$3435)*(Data!AE4='Accident & Incident Detail'!$C$3:$C$3435))} -> 5 | AF12: {=SUM(($A$12='Accident & Incident Detail'!$E$3:$E$3435)*(Data!AF4='Accident & Incident Detail'!$C$3:$C$3435))} -> 11 | AG12: {=SUM(($A$12='Accident & Incident Detail'!$E$3:$E$3435)*(Data!AG4='Accident & Incident Detail'!$C$3:$C$3435))} -> 20 | AH12: {=SUM(($A$12='Accident & Incident Detail'!$E$3:$E$3435)*(Data!AH4='Accident & Incident Detail'!$C$3:$C$3435))} -> 16 | AI12: {=SUM(($A$12='Accident & Incident Detail'!$E$3:$E$3435)*(Data!AI4='Accident & Incident Detail'!$C$3:$C$3435))} -> 4 | ... AN12: {=SUM(($A$12='Accident & Incident Detail'!$E$3:$E$3435)*(Data!AN4='Accident & Incident Detail'!$C$3:$C$3435))} -> 0 | AO12: =SUM(AB12:AN12) -> 113
A13: Low Risk Operational | B13: =IF(B1=1,B236,0) -> 0 | C13: =IF(C1=1,C236,0) -> 0 | D13: =IF(D1=1,D236,0) -> 0 | E13: =IF(E1=1,E236,0) -> 0 | F13: =IF(F1=1,F236,0) -> 0 | G13: =IF(G1=1,G236,0) -> 1 | H13: =IF(H1=1,H236,0) -> 1 | I13: =IF(I1=1,I236,0) -> 1 | ... AN13: =IF(AN1=1,AN236,0) -> 0 | AO13: =SUM(AB13:AN13) -> 66
A14: High Risk Operation | B14: =IF(B1=1,B253,0) -> 0 | C14: =IF(C1=1,C253,0) -> 0 | D14: =IF(D1=1,D253,0) -> 0 | E14: =IF(E1=1,E253,0) -> 0 | F14: =IF(F1=1,F253,0) -> 0 | G14: =IF(G1=1,G253,0) -> 0 | H14: =IF(H1=1,H253,0) -> 0 | I14: =IF(I1=1,I253,0) -> 0 | ... AN14: =IF(AN1=1,AN253,0) -> 0 | AO14: =SUM(AB14:AN14) -> 4
A15: Siemens SRD | B15: {=SUM(($A$15='Accident & Incident Detail'!$I$3:$I$3433)*(Data!B4='Accident & Incident Detail'!$C$3:$C$3433))} -> 0 | C15: {=SUM(($A$15='Accident & Incident Detail'!$I$3:$I$3433)*(Data!C4='Accident & Incident Detail'!$C$3:$C$3433))} -> 0 | D15: {=SUM(($A$15='Accident & Incident Detail'!$I$3:$I$3433)*(Data!D4='Accident & Incident Detail'!$C$3:$C$3433))} -> 0 | E15: {=SUM(($A$15='Accident & Incident Detail'!$I$3:$I$3433)*(Data!E4='Accident & Incident Detail'!$C$3:$C$3433))} -> 0 | F15: {=SUM(($A$15='Accident & Incident Detail'!$I$3:$I$3433)*(Data!F4='Accident & Incident Detail'!$C$3:$C$3433))} -> 0 | G15: {=SUM(($A$15='Accident & Incident Detail'!$I$3:$I$3433)*(Data!G4='Accident & Incident Detail'!$C$3:$C$3433))} -> 0 | H15: {=SUM(($A$15='Accident & Incident Detail'!$I$3:$I$3433)*(Data!H4='Accident & Incident Detail'!$C$3:$C$3433))} -> 0 | I15: {=SUM(($A$15='Accident & Incident Detail'!$I$3:$I$3433)*(Data!I4='Accident & Incident Detail'!$C$3:$C$3433))} -> 0 | ... Y15: {=SUM(($A$15='Accident & Incident Detail'!$I$3:$I$3433)*(Data!Y4='Accident & Incident Detail'!$C$3:$C$3433))} -> 0 | Z15: {=SUM(($A$6='Accident & Incident Detail'!$I$3:$I$3433)*(Data!Z14='Accident & Incident Detail'!$C$3:$C$3433))} -> 0 | AA15: {=SUM(($A$6='Accident & Incident Detail'!$I$3:$I$3433)*(Data!AA14='Accident & Incident Detail'!$C$3:$C$3433))} -> 0 | AB15: {=SUM(($A$15='Accident & Incident Detail'!$I$3:$I$3434)*(Data!AB14='Accident & Incident Detail'!$C$3:$C$3434))} -> 0 | AC15: {=SUM(($A$15='Accident & Incident Detail'!$I$3:$I$3434)*(Data!AC4='Accident & Incident Detail'!$C$3:$C$3434))} -> 0 | AD15: {=SUM(($A$15='Accident & Incident Detail'!$I$3:$I$3434)*(Data!AD4='Accident & Incident Detail'!$C$3:$C$3434))} -> 0 | AE15: {=SUM(($A$15='Accident & Incident Detail'!$I$3:$I$3434)*(Data!AE4='Accident & Incident Detail'!$C$3:$C$3434))} -> 1 | AF15: {=SUM(($A$15='Accident & Incident Detail'!$I$3:$I$3434)*(Data!AF4='Accident & Incident Detail'!$C$3:$C$3434))} -> 0 | AG15: {=SUM(($A$15='Accident & Incident Detail'!$I$3:$I$3434)*(Data!AG4='Accident & Incident Detail'!$C$3:$C$3434))} -> 0 | AH15: {=SUM(($A$15='Accident & Incident Detail'!$I$3:$I$3434)*(Data!AH4='Accident & Incident Detail'!$C$3:$C$3434))} -> 0 | AI15: {=SUM(($A$15='Accident & Incident Detail'!$I$3:$I$3434)*(Data!AI4='Accident & Incident Detail'!$C$3:$C$3434))} -> 0 | AJ15: {=SUM(($A$15='Accident & Incident Detail'!$I$3:$I$3434)*(Data!AJ4='Accident & Incident Detail'!$C$3:$C$3434))} -> 0 | ... AN15: {=SUM(($A$15='Accident & Incident Detail'!$I$3:$I$3434)*(Data!AN4='Accident & Incident Detail'!$C$3:$C$3434))} -> 0 | AO15: =SUM(AB15:AN15) -> 1
A16: Citylink SRD | B16: {=SUM(($A$16='Accident & Incident Detail'!$I$3:$I$3433)*(Data!B4='Accident & Incident Detail'!$C$3:$C$3433))} -> 0 | C16: {=SUM(($A$16='Accident & Incident Detail'!$I$3:$I$3433)*(Data!C4='Accident & Incident Detail'!$C$3:$C$3433))} -> 0 | D16: {=SUM(($A$16='Accident & Incident Detail'!$I$3:$I$3433)*(Data!D4='Accident & Incident Detail'!$C$3:$C$3433))} -> 0 | E16: {=SUM(($A$16='Accident & Incident Detail'!$I$3:$I$3433)*(Data!E4='Accident & Incident Detail'!$C$3:$C$3433))} -> 0 | F16: {=SUM(($A$16='Accident & Incident Detail'!$I$3:$I$3433)*(Data!F4='Accident & Incident Detail'!$C$3:$C$3433))} -> 0 | G16: {=SUM(($A$16='Accident & Incident Detail'!$I$3:$I$3433)*(Data!G4='Accident & Incident Detail'!$C$3:$C$3433))} -> 0 | H16: {=SUM(($A$16='Accident & Incident Detail'!$I$3:$I$3433)*(Data!H4='Accident & Incident Detail'!$C$3:$C$3433))} -> 0 | I16: {=SUM(($A$16='Accident & Incident Detail'!$I$3:$I$3433)*(Data!I4='Accident & Incident Detail'!$C$3:$C$3433))} -> 0 | ... Y16: {=SUM(($A$16='Accident & Incident Detail'!$I$3:$I$3433)*(Data!Y4='Accident & Incident Detail'!$C$3:$C$3433))} -> 0 | Z16: {=SUM(($A$6='Accident & Incident Detail'!$I$3:$I$3433)*(Data!Z15='Accident & Incident Detail'!$C$3:$C$3433))} -> 0 | AA16: {=SUM(($A$6='Accident & Incident Detail'!$I$3:$I$3433)*(Data!AA15='Accident & Incident Detail'!$C$3:$C$3433))} -> 0 | AB16: {=SUM(($A$16='Accident & Incident Detail'!$I$3:$I$3434)*(Data!AB15='Accident & Incident Detail'!$C$3:$C$3434))} -> 0 | AC16: {=SUM(($A$16='Accident & Incident Detail'!$I$3:$I$3434)*(Data!AC15='Accident & Incident Detail'!$C$3:$C$3434))} -> 0 | AD16: {=SUM(($A$16='Accident & Incident Detail'!$I$3:$I$3434)*(Data!AD4='Accident & Incident Detail'!$C$3:$C$3434))} -> 0 | AE16: {=SUM(($A$16='Accident & Incident Detail'!$I$3:$I$3434)*(Data!AE15='Accident & Incident Detail'!$C$3:$C$3434))} -> 0 | AF16: {=SUM(($A$16='Accident & Incident Detail'!$I$3:$I$3434)*(Data!AF4='Accident & Incident Detail'!$C$3:$C$3434))} -> 0 | AG16: {=SUM(($A$16='Accident & Incident Detail'!$I$3:$I$3434)*(Data!AG4='Accident & Incident Detail'!$C$3:$C$3434))} -> 0 | AH16: {=SUM(($A$16='Accident & Incident Detail'!$I$3:$I$3434)*(Data!AH4='Accident & Incident Detail'!$C$3:$C$3434))} -> 0 | AI16: {=SUM(($A$16='Accident & Incident Detail'!$I$3:$I$3434)*(Data!AI4='Accident & Incident Detail'!$C$3:$C$3434))} -> 0 | AJ16: {=SUM(($A$16='Accident & Incident Detail'!$I$3:$I$3434)*(Data!AJ4='Accident & Incident Detail'!$C$3:$C$3434))} -> 0 | AK16: {=SUM(($A$16='Accident & Incident Detail'!$I$3:$I$3434)*(Data!AK4='Accident & Incident Detail'!$C$3:$C$3434))} -> 0 | AL16: {=SUM(($A$16='Accident & Incident Detail'!$I$3:$I$3434)*(Data!AL4='Accident & Incident Detail'!$C$3:$C$3434))} -> 0 | AM16: {=SUM(($A$16='Accident & Incident Detail'!$I$3:$I$3434)*(Data!AM4='Accident & Incident Detail'!$C$3:$C$3434))} -> 0 | AN16: {=SUM(($A$16='Accident & Incident Detail'!$I$3:$I$3434)*(Data!AN4='Accident & Incident Detail'!$C$3:$C$3434))} -> 0 | AO16: =SUM(AB16:AN16) -> 0
A17: Incidents Total | B17: =SUM(B12:B15) -> 0 | C17: =SUM(C12:C15) -> 0 | D17: =SUM(D12:D15) -> 0 | E17: =SUM(E12:E15) -> 0 | F17: =SUM(F12:F15) -> 0 | G17: =SUM(G12:G15) -> 1 | H17: =SUM(H12:H15) -> 1 | I17: =SUM(I12:I15) -> 1 | ... AN17: =SUM(AN12:AN15) -> 0 | AO17: =SUM(AB17:AN17) -> 184
A18: Total | B18: =B17+B11 -> 0 | C18: =C17+C11 -> 0 | D18: =D17+D11 -> 0 | E18: =E17+E11 -> 0 | F18: =F17+F11 -> 0 | G18: =G17+G11 -> 1 | H18: =H17+H11 -> 1 | I18: =I17+I11 -> 1 | ... Y18: =Y17+Y11 -> 22 | Z18: {=SUM(($A$6='Accident & Incident Detail'!$I$3:$I$3433)*(Data!Z17='Accident & Incident Detail'!$C$3:$C$3433))} -> 0 | AA18: {=SUM(($A$6='Accident & Incident Detail'!$I$3:$I$3433)*(Data!AA17='Accident & Incident Detail'!$C$3:$C$3433))} -> 0 | AB18: =AB17+AB11 -> 22 | AC18: =AC17+AC11 -> 22 | AD18: =AD17+AD11 -> 33 | AE18: =AE17+AE11 -> 23 | AF18: =AF17+AF11 -> 22 | AG18: =AG17+AG11 -> 32 | AH18: =AH17+AH11 -> 35 | AI18: =AI17+AI11 -> 26 | ... AN18: =AN17+AN11 -> 0 | AO18: =SUM(AB18:AN18) -> 277
A20: MAA
B21: 2301 | C21: 2302 | D21: 2303 | E21: 2304 | F21: 2305 | G21: 2306 | H21: 2307 | I21: 2308 | J21: 2309 | K21: 2310 | L21: 2311 | M21: 2312 | N21: 2313 | O21: 2401 | P21: 2402 | Q21: 2403 | R21: 2404 | S21: 2405 | T21: 2406 | U21: 2407 | V21: 2408 | W21: 2409 | X21: 2410 | Y21: 2411 | Z21: 2412 | AA21: 2413 | AB21: 2501 | AC21: 2502 | AD21: 2503 | AE21: 2504 | AF21: 2505 | AG21: 2506 | AH21: 2507 | AI21: 2508 | AJ21: 2509 | AK21: 2510 | AL21: 2511 | AM21: 2512 | AN21: 2513
A22: Staff Accident | B22: =IF(B$1=1,SUM(SUM(B6:B6)/13),NA()) -> 0 | C22: =IF(C$1=1,SUM(SUM(B6:C6)/13),NA()) -> 0 | D22: =IF(D$1=1,SUM(SUM(B6:D6)/13),NA()) -> 0 | E22: =IF(E$1=1,SUM(SUM(B6:E6)/13),NA()) -> -0.076923077 | F22: =IF(F$1=1,SUM(SUM(B6:F6)/13),NA()) -> -0.076923077 | G22: =IF(G$1=1,SUM(SUM(B6:G6)/13),NA()) -> -0.15384615 | H22: =IF(H$1=1,SUM(SUM(B6:H6)/13),NA()) -> -0.15384615 | I22: =IF(I$1=1,SUM(SUM(B6:I6)/13),NA()) -> -0.15384615 | J22: =IF(J$1=1,SUM(SUM(B6:J6)/13),NA()) -> -0.076923077 | K22: =IF(K$1=1,SUM(SUM(B6:K6)/13),NA()) -> 0.076923077 | L22: =IF(L$1=1,SUM(SUM(B6:L6)/13),NA()) -> 0.30769231 | M22: =IF(M$1=1,SUM(SUM(B6:M6)/13),NA()) -> 0.38461538 | N22: =IF(N$1=1,SUM(SUM(B6:N6)/13),NA()) -> 0.38461538 | O22: =IF(O$1=1,SUM(SUM(C6:O6)/13),NA()) -> 0.46153846 | P22: =IF(P$1=1,SUM(SUM(D6:P6)/13),NA()) -> 0.69230769 | Q22: =IF(Q$1=1,SUM(SUM(E6:Q6)/13),NA()) -> 0.69230769 | R22: =IF(R$1=1,SUM(SUM(F6:R6)/13),NA()) -> 0.92307692 | S22: =IF(S$1=1,SUM(SUM(G6:S6)/13),NA()) -> 1.0769231 | T22: =IF(T$1=1,SUM(SUM(H6:T6)/13),NA()) -> 1.2307692 | U22: =IF(U$1=1,SUM(SUM(I6:U6)/13),NA()) -> 1.4615385 | ... AN22: =IF(AN$1=1,SUM(SUM(AB6:AN6)/13),NA()) -> #N/A | AO22: =SUM(AC22:AN22) -> #N/A
A23: Staff LTA | B23: =IF(B$1=1,SUM(SUM(B7:B7)/13),NA()) -> 0 | C23: =IF(C$1=1,SUM(SUM(B7:C7)/13),NA()) -> 0 | D23: =IF(D$1=1,SUM(SUM(B7:D7)/13),NA()) -> 0 | E23: =IF(E$1=1,SUM(SUM(B7:E7)/13),NA()) -> 0.076923077 | F23: =IF(F$1=1,SUM(SUM(B7:F7)/13),NA()) -> 0.076923077 | G23: =IF(G$1=1,SUM(SUM(B7:G7)/13),NA()) -> 0.15384615 | H23: =IF(H$1=1,SUM(SUM(B7:H7)/13),NA()) -> 0.15384615 | I23: =IF(I$1=1,SUM(SUM(B7:I7)/13),NA()) -> 0.15384615 | J23: =IF(J$1=1,SUM(SUM(B7:J7)/13),NA()) -> 0.15384615 | K23: =IF(K$1=1,SUM(SUM(B7:K7)/13),NA()) -> 0.15384615 | L23: =IF(L$1=1,SUM(SUM(B7:L7)/13),NA()) -> 0.15384615 | M23: =IF(M$1=1,SUM(SUM(B7:M7)/13),NA()) -> 0.15384615 | N23: =IF(N$1=1,SUM(SUM(B7:N7)/13),NA()) -> 0.15384615 | O23: =IF(O$1=1,SUM(SUM(C7:O7)/13),NA()) -> 0.15384615 | P23: =IF(P$1=1,SUM(SUM(D7:P7)/13),NA()) -> 0.23076923 | Q23: =IF(Q$1=1,SUM(SUM(E7:Q7)/13),NA()) -> 0.23076923 | R23: =IF(R$1=1,SUM(SUM(F7:R7)/13),NA()) -> 0.15384615 | S23: =IF(S$1=1,SUM(SUM(G7:S7)/13),NA()) -> 0.15384615 | T23: =IF(T$1=1,SUM(SUM(H7:T7)/13),NA()) -> 0.076923077 | U23: =IF(U$1=1,SUM(SUM(I7:U7)/13),NA()) -> 0.076923077 | ... AN23: =IF(AN$1=1,SUM(SUM(AB7:AN7)/13),NA()) -> #N/A | AO23: =SUM(AC23:AN23) -> #N/A
A24: Assaults | B24: =IF(B$1=1,SUM(SUM(B8:B8)/13),NA()) -> 0 | C24: =IF(C$1=1,SUM(SUM(B8:C8)/13),NA()) -> 0 | D24: =IF(D$1=1,SUM(SUM(B8:D8)/13),NA()) -> 0 | E24: =IF(E$1=1,SUM(SUM(B8:E8)/13),NA()) -> 0 | F24: =IF(F$1=1,SUM(SUM(B8:F8)/13),NA()) -> 0 | G24: =IF(G$1=1,SUM(SUM(B8:G8)/13),NA()) -> 0 | H24: =IF(H$1=1,SUM(SUM(B8:H8)/13),NA()) -> 0 | I24: =IF(I$1=1,SUM(SUM(B8:I8)/13),NA()) -> 0 | J24: =IF(J$1=1,SUM(SUM(B8:J8)/13),NA()) -> 0.15384615 | K24: =IF(K$1=1,SUM(SUM(B8:K8)/13),NA()) -> 0.53846154 | L24: =IF(L$1=1,SUM(SUM(B8:L8)/13),NA()) -> 0.76923077 | M24: =IF(M$1=1,SUM(SUM(B8:M8)/13),NA()) -> 1.2307692 | N24: =IF(N$1=1,SUM(SUM(B8:N8)/13),NA()) -> 1.2307692 | O24: =IF(O$1=1,SUM(SUM(C8:O8)/13),NA()) -> 1.9230769 | P24: =IF(P$1=1,SUM(SUM(D8:P8)/13),NA()) -> 2.2307692 | Q24: =IF(Q$1=1,SUM(SUM(E8:Q8)/13),NA()) -> 2.5384615 | R24: =IF(R$1=1,SUM(SUM(F8:R8)/13),NA()) -> 2.8461538 | S24: =IF(S$1=1,SUM(SUM(G8:S8)/13),NA()) -> 3.0769231 | T24: =IF(T$1=1,SUM(SUM(H8:T8)/13),NA()) -> 3.3846154 | U24: =IF(U$1=1,SUM(SUM(I8:U8)/13),NA()) -> 3.8461538 | ... AN24: =IF(AN$1=1,SUM(SUM(AB8:AN8)/13),NA()) -> #N/A | AO24: =SUM(AC24:AN24) -> #N/A
A25: Movement | B25: =IF(B$1=1,(SUM(SUM(B9:B9))/13),NA()) -> 0 | C25: =IF(C$1=1,(SUM(SUM(B9:C9))/13),NA()) -> 0 | D25: =IF(D$1=1,(SUM(SUM(B9:D9))/13),NA()) -> 0 | E25: =IF(E$1=1,(SUM(SUM(B9:E9))/13),NA()) -> 0 | F25: =IF(F$1=1,(SUM(SUM(B9:F9))/13),NA()) -> 0 | G25: =IF(G$1=1,(SUM(SUM(B9:G9))/13),NA()) -> 0 | H25: =IF(H$1=1,(SUM(SUM(B9:H9))/13),NA()) -> 0 | I25: =IF(I$1=1,(SUM(SUM(B9:I9))/13),NA()) -> 0 | J25: =IF(J$1=1,(SUM(SUM(B9:J9))/13),NA()) -> 0.076923077 | K25: =IF(K$1=1,(SUM(SUM(B9:K9))/13),NA()) -> 0.30769231 | L25: =IF(L$1=1,(SUM(SUM(B9:L9))/13),NA()) -> 0.84615385 | M25: =IF(M$1=1,(SUM(SUM(B9:M9))/13),NA()) -> 1.3846154 | N25: =IF(N$1=1,(SUM(SUM(B9:N9))/13),NA()) -> 1.3846154 | O25: =IF(O$1=1,(SUM(SUM(C9:O9))/13),NA()) -> 2.0769231 | P25: =IF(P$1=1,(SUM(SUM(D9:P9))/13),NA()) -> 2.5384615 | Q25: =IF(Q$1=1,(SUM(SUM(E9:Q9))/13),NA()) -> 3.2307692 | R25: =IF(R$1=1,(SUM(SUM(F9:R9))/13),NA()) -> 3.6923077 | S25: =IF(S$1=1,(SUM(SUM(G9:S9))/13),NA()) -> 3.9230769 | T25: =IF(T$1=1,(SUM(SUM(H9:T9))/13),NA()) -> 4.4615385 | U25: =IF(U$1=1,(SUM(SUM(I9:U9))/13),NA()) -> 5 | ... AN25: =IF(AN$1=1,(SUM(SUM(AB9:AN9))/13),NA()) -> #N/A | AO25: =SUM(AC25:AN25) -> #N/A
A26: Movement (Old) | B26: 91.615385 | C26: 92.615385 | D26: 93.615385 | E26: 94.615385 | F26: 95.615385 | G26: 96.615385 | H26: 97.615385 | I26: 98.615385 | J26: 99.615385 | K26: 100.61538 | L26: 101.61538 | M26: 102.61538 | N26: 103.61538 | O26: 104.61538 | P26: 105.61538 | Q26: 106.61538 | R26: 107.61538 | S26: 108.61538 | T26: 109.61538 | U26: 110.61538 | V26: 111.61538 | W26: 112.61538 | X26: 113.61538 | Y26: 114.61538 | Z26: 115.61538 | AA26: 116.61538 | AB26: 117.61538 | AC26: 118.61538 | AD26: 119.61538 | AE26: 120.61538 | AF26: 121.61538 | AG26: 122.61538 | AH26: 123.61538 | AI26: 124.61538 | AJ26: 125.61538 | AK26: 126.61538 | AL26: 127.61538 | AM26: 128.61538 | AN26: 129.61538 | AO26: =SUM(AC26:AN26) -> 1489.3846
A27: Non-Movement MAA | B27: =IF(B$1=1,(SUM(SUM(B10:B10))/13),NA()) -> 0 | C27: =IF(C$1=1,(SUM(SUM(B10:C10))/13),NA()) -> 0 | D27: =IF(D$1=1,(SUM(SUM(B10:D10))/13),NA()) -> 0 | E27: =IF(E$1=1,(SUM(SUM(B10:E10))/13),NA()) -> 0 | F27: =IF(F$1=1,(SUM(SUM(B10:F10))/13),NA()) -> 0 | G27: =IF(G$1=1,(SUM(SUM(B10:G10))/13),NA()) -> 0 | H27: =IF(H$1=1,(SUM(SUM(B10:H10))/13),NA()) -> 0 | I27: =IF(I$1=1,(SUM(SUM(B10:I10))/13),NA()) -> 0 | J27: =IF(J$1=1,(SUM(SUM(B10:J10))/13),NA()) -> 0 | K27: =IF(K$1=1,(SUM(SUM(B10:K10))/13),NA()) -> 0 | L27: =IF(L$1=1,(SUM(SUM(B10:L10))/13),NA()) -> 0 | M27: =IF(M$1=1,(SUM(SUM(B10:M10))/13),NA()) -> 0.076923077 | N27: =IF(N$1=1,(SUM(SUM(B10:N10))/13),NA()) -> 0.076923077 | O27: =IF(O$1=1,(SUM(SUM(C10:O10))/13),NA()) -> 0.15384615 | P27: =IF(P$1=1,(SUM(SUM(D10:P10))/13),NA()) -> 0.23076923 | Q27: =IF(Q$1=1,(SUM(SUM(E10:Q10))/13),NA()) -> 0.23076923 | R27: =IF(R$1=1,(SUM(SUM(F10:R10))/13),NA()) -> 0.38461538 | S27: =IF(S$1=1,(SUM(SUM(G10:S10))/13),NA()) -> 0.38461538 | T27: =IF(T$1=1,(SUM(SUM(H10:T10))/13),NA()) -> 0.38461538 | U27: =IF(U$1=1,(SUM(SUM(I10:U10))/13),NA()) -> 0.46153846 | ... AN27: =IF(AN$1=1,(SUM(SUM(AB10:AN10))/13),NA()) -> #N/A | AO27: =SUM(AC27:AN27) -> #N/A
A28: Non-Movement (Old) | B28: #N/A | C28: #N/A | D28: #N/A | E28: #N/A | F28: #N/A | G28: #N/A | H28: #N/A | I28: #N/A | J28: #N/A | K28: #N/A | L28: #N/A | M28: #N/A | N28: #N/A | O28: #N/A | P28: #N/A | Q28: #N/A | R28: #N/A | S28: #N/A | T28: #N/A | U28: #N/A | V28: #N/A | W28: #N/A | X28: #N/A | Y28: #N/A | Z28: #N/A | AA28: #N/A | AB28: #N/A | AC28: #N/A | AD28: #N/A | AE28: #N/A | AF28: #N/A | AG28: #N/A | AH28: #N/A | AI28: #N/A | AJ28: #N/A | AK28: #N/A | AL28: #N/A | AM28: #N/A | AN28: #N/A | AO28: =SUM(AC28:AN28) -> #N/A
A29: Accidents Total | B29: =IF(B$1=1,SUM(SUM(B11:B11)/13),NA()) -> 0 | C29: =IF(C$1=1,SUM(SUM(B11:C11)/13),NA()) -> 0 | D29: =IF(D$1=1,SUM(SUM(B11:D11)/13),NA()) -> 0 | E29: =IF(E$1=1,SUM(SUM(B11:E11)/13),NA()) -> 0 | F29: =IF(F$1=1,SUM(SUM(B11:F11)/13),NA()) -> 0 | G29: =IF(G$1=1,SUM(SUM(B11:G11)/13),NA()) -> 0 | H29: =IF(H$1=1,SUM(SUM(B11:H11)/13),NA()) -> 0 | I29: =IF(I$1=1,SUM(SUM(B11:I11)/13),NA()) -> 0 | J29: =IF(J$1=1,SUM(SUM(B11:J11)/13),NA()) -> 0.30769231 | K29: =IF(K$1=1,SUM(SUM(B11:K11)/13),NA()) -> 1.0769231 | L29: =IF(L$1=1,SUM(SUM(B11:L11)/13),NA()) -> 2.0769231 | M29: =IF(M$1=1,SUM(SUM(B11:M11)/13),NA()) -> 3.2307692 | N29: =IF(N$1=1,SUM(SUM(B11:N11)/13),NA()) -> 3.2307692 | O29: =IF(O$1=1,SUM(SUM(C11:O11)/13),NA()) -> 4.7692308 | P29: =IF(P$1=1,SUM(SUM(D11:P11)/13),NA()) -> 5.9230769 | Q29: =IF(Q$1=1,SUM(SUM(E11:Q11)/13),NA()) -> 6.9230769 | R29: =IF(R$1=1,SUM(SUM(F11:R11)/13),NA()) -> 8 | S29: =IF(S$1=1,SUM(SUM(G11:S11)/13),NA()) -> 8.6153846 | T29: =IF(T$1=1,SUM(SUM(H11:T11)/13),NA()) -> 9.5384615 | U29: =IF(U$1=1,SUM(SUM(I11:U11)/13),NA()) -> 10.846154 | ... AN29: =IF(AN$1=1,SUM(SUM(AB11:AN11)/13),NA()) -> #N/A | AO29: =SUM(AC29:AN29) -> #N/A
A30: Vandalism | B30: =IF(B$1=1,SUM(SUM(B12:B12)/13),NA()) -> 0 | C30: =IF(C$1=1,SUM(SUM(B12:C12)/13),NA()) -> 0 | D30: =IF(D$1=1,SUM(SUM(B12:D12)/13),NA()) -> 0 | E30: =IF(E$1=1,SUM(SUM(B12:E12)/13),NA()) -> 0 | F30: =IF(F$1=1,SUM(SUM(B12:F12)/13),NA()) -> 0 | G30: =IF(G$1=1,SUM(SUM(B12:G12)/13),NA()) -> 0 | H30: =IF(H$1=1,SUM(SUM(B12:H12)/13),NA()) -> 0 | I30: =IF(I$1=1,SUM(SUM(B12:I12)/13),NA()) -> 0 | J30: =IF(J$1=1,SUM(SUM(B12:J12)/13),NA()) -> 0.076923077 | K30: =IF(K$1=1,SUM(SUM(B12:K12)/13),NA()) -> 0.76923077 | L30: =IF(L$1=1,SUM(SUM(B12:L12)/13),NA()) -> 1.0769231 | M30: =IF(M$1=1,SUM(SUM(B12:M12)/13),NA()) -> 1.5384615 | N30: =IF(N$1=1,SUM(SUM(B12:N12)/13),NA()) -> 1.5384615 | O30: =IF(O$1=1,SUM(SUM(C12:O12)/13),NA()) -> 2.0769231 | P30: =IF(P$1=1,SUM(SUM(D12:P12)/13),NA()) -> 2.3846154 | Q30: =IF(Q$1=1,SUM(SUM(E12:Q12)/13),NA()) -> 2.9230769 | R30: =IF(R$1=1,SUM(SUM(F12:R12)/13),NA()) -> 3.3076923 | S30: =IF(S$1=1,SUM(SUM(G12:S12)/13),NA()) -> 3.5384615 | T30: =IF(T$1=1,SUM(SUM(H12:T12)/13),NA()) -> 3.9230769 | U30: =IF(U$1=1,SUM(SUM(I12:U12)/13),NA()) -> 4.3846154 | ... AN30: =IF(AN$1=1,SUM(SUM(AB12:AN12)/13),NA()) -> #N/A | AO30: =SUM(AC30:AN30) -> #N/A
A31: Low Risk Operational | B31: =IF(B$1=1,SUM(SUM(B13:B13)/13),NA()) -> 0 | C31: =IF(C$1=1,SUM(SUM(B13:C13)/13),NA()) -> 0 | D31: =IF(D$1=1,SUM(SUM(B13:D13)/13),NA()) -> 0 | E31: =IF(E$1=1,SUM(SUM(B13:E13)/13),NA()) -> 0 | F31: =IF(F$1=1,SUM(SUM(B13:F13)/13),NA()) -> 0 | G31: =IF(G$1=1,SUM(SUM(B13:G13)/13),NA()) -> 0.076923077 | H31: =IF(H$1=1,SUM(SUM(B13:H13)/13),NA()) -> 0.15384615 | I31: =IF(I$1=1,SUM(SUM(B13:I13)/13),NA()) -> 0.23076923 | J31: =IF(J$1=1,SUM(SUM(B13:J13)/13),NA()) -> 0.46153846 | K31: =IF(K$1=1,SUM(SUM(B13:K13)/13),NA()) -> 1.1538462 | L31: =IF(L$1=1,SUM(SUM(B13:L13)/13),NA()) -> 2 | M31: =IF(M$1=1,SUM(SUM(B13:M13)/13),NA()) -> 2.4615385 | N31: =IF(N$1=1,SUM(SUM(B13:N13)/13),NA()) -> 2.4615385 | O31: =IF(O$1=1,SUM(SUM(C13:O13)/13),NA()) -> 3 | P31: =IF(P$1=1,SUM(SUM(D13:P13)/13),NA()) -> 3.4615385 | Q31: =IF(Q$1=1,SUM(SUM(E13:Q13)/13),NA()) -> 4.0769231 | R31: =IF(R$1=1,SUM(SUM(F13:R13)/13),NA()) -> 4.7692308 | S31: =IF(S$1=1,SUM(SUM(G13:S13)/13),NA()) -> 5.0769231 | T31: =IF(T$1=1,SUM(SUM(H13:T13)/13),NA()) -> 5.3076923 | U31: =IF(U$1=1,SUM(SUM(I13:U13)/13),NA()) -> 5.6153846 | ... AN31: =IF(AN$1=1,SUM(SUM(AB13:AN13)/13),NA()) -> #N/A | AO31: =SUM(AC31:AN31) -> #N/A
A32: High Risk Operational | B32: =IF(B$1=1,SUM(SUM(B14:B14)/13),NA()) -> 0 | C32: =IF(C$1=1,SUM(SUM(B14:C14)/13),NA()) -> 0 | D32: =IF(D$1=1,SUM(SUM(B14:D14)/13),NA()) -> 0 | E32: =IF(E$1=1,SUM(SUM(B14:E14)/13),NA()) -> 0 | F32: =IF(F$1=1,SUM(SUM(B14:F14)/13),NA()) -> 0 | G32: =IF(G$1=1,SUM(SUM(B14:G14)/13),NA()) -> 0 | H32: =IF(H$1=1,SUM(SUM(B14:H14)/13),NA()) -> 0 | I32: =IF(I$1=1,SUM(SUM(B14:I14)/13),NA()) -> 0 | J32: =IF(J$1=1,SUM(SUM(B14:J14)/13),NA()) -> 0.076923077 | K32: =IF(K$1=1,SUM(SUM(B14:K14)/13),NA()) -> 0.076923077 | L32: =IF(L$1=1,SUM(SUM(B14:L14)/13),NA()) -> 0.076923077 | M32: =IF(M$1=1,SUM(SUM(B14:M14)/13),NA()) -> 0.076923077 | N32: =IF(N$1=1,SUM(SUM(B14:N14)/13),NA()) -> 0.076923077 | O32: =IF(O$1=1,SUM(SUM(C14:O14)/13),NA()) -> 0.15384615 | P32: =IF(P$1=1,SUM(SUM(D14:P14)/13),NA()) -> 0.38461538 | Q32: =IF(Q$1=1,SUM(SUM(E14:Q14)/13),NA()) -> 0.38461538 | R32: =IF(R$1=1,SUM(SUM(F14:R14)/13),NA()) -> 0.38461538 | S32: =IF(S$1=1,SUM(SUM(G14:S14)/13),NA()) -> 0.38461538 | T32: =IF(T$1=1,SUM(SUM(H14:T14)/13),NA()) -> 0.46153846 | U32: =IF(U$1=1,SUM(SUM(I14:U14)/13),NA()) -> 0.46153846 | ... AN32: =IF(AN$1=1,SUM(SUM(AB14:AN14)/13),NA()) -> #N/A | AO32: =SUM(AC32:AN32) -> #N/A
A33: SRD | B33: =IF(B$1=1,SUM(SUM(B15:B15)/13),NA()) -> 0 | C33: =IF(C$1=1,SUM(SUM(B15:C15)/13),NA()) -> 0 | D33: =IF(D$1=1,SUM(SUM(B15:D15)/13),NA()) -> 0 | E33: =IF(E$1=1,SUM(SUM(B15:E15)/13),NA()) -> 0 | F33: =IF(F$1=1,SUM(SUM(B15:F15)/13),NA()) -> 0 | G33: =IF(G$1=1,SUM(SUM(B15:G15)/13),NA()) -> 0 | H33: =IF(H$1=1,SUM(SUM(B15:H15)/13),NA()) -> 0 | I33: =IF(I$1=1,SUM(SUM(B15:I15)/13),NA()) -> 0 | J33: =IF(J$1=1,SUM(SUM(B15:J15)/13),NA()) -> 0 | K33: =IF(K$1=1,SUM(SUM(B15:K15)/13),NA()) -> 0 | L33: =IF(L$1=1,SUM(SUM(B15:L15)/13),NA()) -> 0 | M33: =IF(M$1=1,SUM(SUM(B15:M15)/13),NA()) -> 0.076923077 | N33: =IF(N$1=1,SUM(SUM(B15:N15)/13),NA()) -> 0.076923077 | O33: =IF(O$1=1,SUM(SUM(C15:O15)/13),NA()) -> 0.15384615 | P33: =IF(P$1=1,SUM(SUM(D15:P15)/13),NA()) -> 0.15384615 | Q33: =IF(Q$1=1,SUM(SUM(E15:Q15)/13),NA()) -> 0.15384615 | R33: =IF(R$1=1,SUM(SUM(F15:R15)/13),NA()) -> 0.15384615 | S33: =IF(S$1=1,SUM(SUM(G15:S15)/13),NA()) -> 0.15384615 | T33: =IF(T$1=1,SUM(SUM(H15:T15)/13),NA()) -> 0.15384615 | U33: =IF(U$1=1,SUM(SUM(I15:U15)/13),NA()) -> 0.15384615 | ... AN33: =IF(AN$1=1,SUM(SUM(AB15:AN15)/13),NA()) -> #N/A | AO33: =SUM(AC33:AN33) -> #N/A
A34: Incidents Total | B34: =IF(B$1=1,SUM(SUM(B17:B17)/13),NA()) -> 0 | C34: =IF(C$1=1,SUM(SUM(B17:C17)/13),NA()) -> 0 | D34: =IF(D$1=1,SUM(SUM(B17:D17)/13),NA()) -> 0 | E34: =IF(E$1=1,SUM(SUM(B17:E17)/13),NA()) -> 0 | F34: =IF(F$1=1,SUM(SUM(B17:F17)/13),NA()) -> 0 | G34: =IF(G$1=1,SUM(SUM(B17:G17)/13),NA()) -> 0.076923077 | H34: =IF(H$1=1,SUM(SUM(B17:H17)/13),NA()) -> 0.15384615 | I34: =IF(I$1=1,SUM(SUM(B17:I17)/13),NA()) -> 0.23076923 | J34: =IF(J$1=1,SUM(SUM(B17:J17)/13),NA()) -> 0.61538462 | K34: =IF(K$1=1,SUM(SUM(B17:K17)/13),NA()) -> 2 | L34: =IF(L$1=1,SUM(SUM(B17:L17)/13),NA()) -> 3.1538462 | M34: =IF(M$1=1,SUM(SUM(B17:M17)/13),NA()) -> 4.1538462 | N34: =IF(N$1=1,SUM(SUM(B17:N17)/13),NA()) -> 4.1538462 | O34: =IF(O$1=1,SUM(SUM(C17:O17)/13),NA()) -> 5.3846154 | P34: =IF(P$1=1,SUM(SUM(D17:P17)/13),NA()) -> 6.3846154 | Q34: =IF(Q$1=1,SUM(SUM(E17:Q17)/13),NA()) -> 7.5384615 | R34: =IF(R$1=1,SUM(SUM(F17:R17)/13),NA()) -> 8.6153846 | S34: =IF(S$1=1,SUM(SUM(G17:S17)/13),NA()) -> 9.1538462 | T34: =IF(T$1=1,SUM(SUM(H17:T17)/13),NA()) -> 9.8461538 | U34: =IF(U$1=1,SUM(SUM(I17:U17)/13),NA()) -> 10.615385 | ... AN34: =IF(AN$1=1,SUM(SUM(AB17:AN17)/13),NA()) -> #N/A | AO34: =SUM(AC34:AN34) -> #N/A
A35: Total | B35: =IF(B$1=1,SUM(SUM(B18:B18)/13),NA()) -> 0 | C35: =IF(C$1=1,SUM(SUM(B18:C18)/13),NA()) -> 0 | D35: =IF(D$1=1,SUM(SUM(B18:D18)/13),NA()) -> 0 | E35: =IF(E$1=1,SUM(SUM(B18:E18)/13),NA()) -> 0 | F35: =IF(F$1=1,SUM(SUM(B18:F18)/13),NA()) -> 0 | G35: =IF(G$1=1,SUM(SUM(B18:G18)/13),NA()) -> 0.076923077 | H35: =IF(H$1=1,SUM(SUM(B18:H18)/13),NA()) -> 0.15384615 | I35: =IF(I$1=1,SUM(SUM(B18:I18)/13),NA()) -> 0.23076923 | J35: =IF(J$1=1,SUM(SUM(B18:J18)/13),NA()) -> 0.92307692 | K35: =IF(K$1=1,SUM(SUM(B18:K18)/13),NA()) -> 3.0769231 | L35: =IF(L$1=1,SUM(SUM(B18:L18)/13),NA()) -> 5.2307692 | M35: =IF(M$1=1,SUM(SUM(B18:M18)/13),NA()) -> 7.3846154 | N35: =IF(N$1=1,SUM(SUM(B18:N18)/13),NA()) -> 7.3846154 | O35: =IF(O$1=1,SUM(SUM(C18:O18)/13),NA()) -> 10.153846 | P35: =IF(P$1=1,SUM(SUM(D18:P18)/13),NA()) -> 12.307692 | Q35: =IF(Q$1=1,SUM(SUM(E18:Q18)/13),NA()) -> 14.461538 | R35: =IF(R$1=1,SUM(SUM(F18:R18)/13),NA()) -> 16.615385 | S35: =IF(S$1=1,SUM(SUM(G18:S18)/13),NA()) -> 17.769231 | T35: =IF(T$1=1,SUM(SUM(H18:T18)/13),NA()) -> 19.384615 | U35: =IF(U$1=1,SUM(SUM(I18:U18)/13),NA()) -> 21.461538 | ... AN35: =IF(AN$1=1,SUM(SUM(AB18:AN18)/13),NA()) -> #N/A | AO35: =SUM(AC35:AN35) -> #N/A
A37: All Staff Accident
A38: Staff Accident | B38: 2301 | C38: 2302 | D38: 2303 | E38: 2304 | F38: 2305 | G38: 2306 | H38: 2307 | I38: 2308 | J38: 2309 | K38: 2310 | L38: 2311 | M38: 2312 | N38: 2313 | O38: 2401 | P38: 2402 | Q38: 2403 | R38: 2404 | S38: 2405 | T38: 2406 | U38: 2407 | V38: 2408 | W38: 2409 | X38: 2410 | Y38: 2411 | Z38: 2412 | AA38: 2413 | AB38: 2501 | AC38: 2502 | AD38: 2503 | AE38: 2504 | AF38: 2505 | AG38: 2506 | AH38: 2507 | AI38: 2508 | AJ38: 2509 | AK38: 2510 | AL38: 2511 | AM38: 2512 | AN38: 2513
A39: Burn/Scald | B39: {=SUM((B38='Accident & Incident Detail'!$C$2:$C$3433)*($A$38='Accident & Incident Detail'!$I$2:$I$3433)*($A$39='Accident & Incident Detail'!$E$2:$E$3433))} -> 0 | C39: {=SUM((C38='Accident & Incident Detail'!$C$2:$C$3433)*($A$38='Accident & Incident Detail'!$I$2:$I$3433)*($A$39='Accident & Incident Detail'!$E$2:$E$3433))} -> 0 | D39: {=SUM((D38='Accident & Incident Detail'!$C$2:$C$3433)*($A$38='Accident & Incident Detail'!$I$2:$I$3433)*($A$39='Accident & Incident Detail'!$E$2:$E$3433))} -> 0 | E39: {=SUM((E38='Accident & Incident Detail'!$C$2:$C$3433)*($A$38='Accident & Incident Detail'!$I$2:$I$3433)*($A$39='Accident & Incident Detail'!$E$2:$E$3433))} -> 0 | F39: {=SUM((F38='Accident & Incident Detail'!$C$2:$C$3433)*($A$38='Accident & Incident Detail'!$I$2:$I$3433)*($A$39='Accident & Incident Detail'!$E$2:$E$3433))} -> 0 | G39: {=SUM((G38='Accident & Incident Detail'!$C$2:$C$3433)*($A$38='Accident & Incident Detail'!$I$2:$I$3433)*($A$39='Accident & Incident Detail'!$E$2:$E$3433))} -> 0 | H39: {=SUM((H38='Accident & Incident Detail'!$C$2:$C$3433)*($A$38='Accident & Incident Detail'!$I$2:$I$3433)*($A$39='Accident & Incident Detail'!$E$2:$E$3433))} -> 0 | I39: {=SUM((I38='Accident & Incident Detail'!$C$2:$C$3433)*($A$38='Accident & Incident Detail'!$I$2:$I$3433)*($A$39='Accident & Incident Detail'!$E$2:$E$3433))} -> 0 | ... AN39: {=SUM((AN38='Accident & Incident Detail'!$C$2:$C$3433)*($A$38='Accident & Incident Detail'!$I$2:$I$3433)*($A$39='Accident & Incident Detail'!$E$2:$E$3433))} -> 0
A40: MAA | B40: =IF(B$1=1,(SUM(B39:B39)/13),0) -> 0 | C40: =IF(C$1=1,(SUM(B39:C39)/13),0) -> 0 | D40: =IF(D$1=1,(SUM(B39:D39)/13),0) -> 0 | E40: =IF(E$1=1,(SUM(B39:E39)/13),0) -> 0 | F40: =IF(F$1=1,(SUM(B39:F39)/13),0) -> 0 | G40: =IF(G$1=1,(SUM(B39:G39)/13),0) -> 0 | H40: =IF(H$1=1,(SUM(B39:H39)/13),0) -> 0 | I40: =IF(I$1=1,(SUM(B39:I39)/13),0) -> 0 | J40: =IF(J$1=1,(SUM(B39:J39)/13),0) -> 0 | K40: =IF(K$1=1,(SUM(B39:K39)/13),0) -> 0 | L40: =IF(L$1=1,(SUM(B39:L39)/13),0) -> 0 | M40: =IF(M$1=1,(SUM(B39:M39)/13),0) -> 0 | N40: =IF(N$1=1,(SUM(B39:N39)/13),0) -> 0 | O40: =IF(O$1=1,(SUM(C39:O39)/13),0) -> 0 | P40: =IF(P$1=1,(SUM(D39:P39)/13),0) -> 0 | Q40: =IF(Q$1=1,(SUM(E39:Q39)/13),0) -> 0 | R40: =IF(R$1=1,(SUM(F39:R39)/13),0) -> 0 | S40: =IF(S$1=1,(SUM(G39:S39)/13),0) -> 0 | T40: =IF(T$1=1,(SUM(H39:T39)/13),0) -> 0 | U40: =IF(U$1=1,(SUM(I39:U39)/13),0) -> 0 | ... AN40: =IF(AN$1=1,(SUM(AB39:AN39)/13),0) -> 0
A41: Contact | B41: {=SUM((B38='Accident & Incident Detail'!$C$2:$C$3433)*($A$38='Accident & Incident Detail'!$I$2:$I$3433)*($A$41='Accident & Incident Detail'!$E$2:$E$3433))} -> 0 | C41: {=SUM((C38='Accident & Incident Detail'!$C$2:$C$3433)*($A$38='Accident & Incident Detail'!$I$2:$I$3433)*($A$41='Accident & Incident Detail'!$E$2:$E$3433))} -> 0 | D41: {=SUM((D38='Accident & Incident Detail'!$C$2:$C$3433)*($A$38='Accident & Incident Detail'!$I$2:$I$3433)*($A$41='Accident & Incident Detail'!$E$2:$E$3433))} -> 0 | E41: {=SUM((E38='Accident & Incident Detail'!$C$2:$C$3433)*($A$38='Accident & Incident Detail'!$I$2:$I$3433)*($A$41='Accident & Incident Detail'!$E$2:$E$3433))} -> 0 | F41: {=SUM((F38='Accident & Incident Detail'!$C$2:$C$3433)*($A$38='Accident & Incident Detail'!$I$2:$I$3433)*($A$41='Accident & Incident Detail'!$E$2:$E$3433))} -> 0 | G41: {=SUM((G38='Accident & Incident Detail'!$C$2:$C$3433)*($A$38='Accident & Incident Detail'!$I$2:$I$3433)*($A$41='Accident & Incident Detail'!$E$2:$E$3433))} -> 0 | H41: {=SUM((H38='Accident & Incident Detail'!$C$2:$C$3433)*($A$38='Accident & Incident Detail'!$I$2:$I$3433)*($A$41='Accident & Incident Detail'!$E$2:$E$3433))} -> 0 | I41: {=SUM((I38='Accident & Incident Detail'!$C$2:$C$3433)*($A$38='Accident & Incident Detail'!$I$2:$I$3433)*($A$41='Accident & Incident Detail'!$E$2:$E$3433))} -> 0 | ... AN41: {=SUM((AN38='Accident & Incident Detail'!$C$2:$C$3433)*($A$38='Accident & Incident Detail'!$I$2:$I$3433)*($A$41='Accident & Incident Detail'!$E$2:$E$3433))} -> 0
A42: MAA | B42: =IF(B$1=1,(SUM(B41:B41)/13),0) -> 0 | C42: =IF(C$1=1,(SUM(B41:C41)/13),0) -> 0 | D42: =IF(D$1=1,(SUM(B41:D41)/13),0) -> 0 | E42: =IF(E$1=1,(SUM(B41:E41)/13),0) -> 0 | F42: =IF(F$1=1,(SUM(B41:F41)/13),0) -> 0 | G42: =IF(G$1=1,(SUM(B41:G41)/13),0) -> 0 | H42: =IF(H$1=1,(SUM(B41:H41)/13),0) -> 0 | I42: =IF(I$1=1,(SUM(B41:I41)/13),0) -> 0 | J42: =IF(J$1=1,(SUM(B41:J41)/13),0) -> 0 | K42: =IF(K$1=1,(SUM(B41:K41)/13),0) -> 0 | L42: =IF(L$1=1,(SUM(B41:L41)/13),0) -> 0 | M42: =IF(M$1=1,(SUM(B41:M41)/13),0) -> 0 | N42: =IF(N$1=1,(SUM(B41:N41)/13),0) -> 0 | O42: =IF(O$1=1,(SUM(C41:O41)/13),0) -> 0 | P42: =IF(P$1=1,(SUM(D41:P41)/13),0) -> 0 | Q42: =IF(Q$1=1,(SUM(E41:Q41)/13),0) -> 0 | R42: =IF(R$1=1,(SUM(F41:R41)/13),0) -> 0 | S42: =IF(S$1=1,(SUM(G41:S41)/13),0) -> 0 | T42: =IF(T$1=1,(SUM(H41:T41)/13),0) -> 0 | U42: =IF(U$1=1,(SUM(I41:U41)/13),0) -> 0 | ... AN42: =IF(AN$1=1,(SUM(AB41:AN41)/13),0) -> 0
A43: Door trap | B43: {=SUM((B38='Accident & Incident Detail'!$C$2:$C$3433)*($A$38='Accident & Incident Detail'!$I$2:$I$3433)*($A$43='Accident & Incident Detail'!$E$2:$E$3433))} -> 0 | C43: {=SUM((C38='Accident & Incident Detail'!$C$2:$C$3433)*($A$38='Accident & Incident Detail'!$I$2:$I$3433)*($A$43='Accident & Incident Detail'!$E$2:$E$3433))} -> 0 | D43: {=SUM((D38='Accident & Incident Detail'!$C$2:$C$3433)*($A$38='Accident & Incident Detail'!$I$2:$I$3433)*($A$43='Accident & Incident Detail'!$E$2:$E$3433))} -> 0 | E43: {=SUM((E38='Accident & Incident Detail'!$C$2:$C$3433)*($A$38='Accident & Incident Detail'!$I$2:$I$3433)*($A$43='Accident & Incident Detail'!$E$2:$E$3433))} -> 0 | F43: {=SUM((F38='Accident & Incident Detail'!$C$2:$C$3433)*($A$38='Accident & Incident Detail'!$I$2:$I$3433)*($A$43='Accident & Incident Detail'!$E$2:$E$3433))} -> 0 | G43: {=SUM((G38='Accident & Incident Detail'!$C$2:$C$3433)*($A$38='Accident & Incident Detail'!$I$2:$I$3433)*($A$43='Accident & Incident Detail'!$E$2:$E$3433))} -> 0 | H43: {=SUM((H38='Accident & Incident Detail'!$C$2:$C$3433)*($A$38='Accident & Incident Detail'!$I$2:$I$3433)*($A$43='Accident & Incident Detail'!$E$2:$E$3433))} -> 0 | I43: {=SUM((I38='Accident & Incident Detail'!$C$2:$C$3433)*($A$38='Accident & Incident Detail'!$I$2:$I$3433)*($A$43='Accident & Incident Detail'!$E$2:$E$3433))} -> 0 | ... AN43: {=SUM((AN38='Accident & Incident Detail'!$C$2:$C$3433)*($A$38='Accident & Incident Detail'!$I$2:$I$3433)*($A$43='Accident & Incident Detail'!$E$2:$E$3433))} -> 0
A44: MAA | B44: =IF(B$1=1,(SUM(B43:B43)/13),0) -> 0 | C44: =IF(C$1=1,(SUM(B43:C43)/13),0) -> 0 | D44: =IF(D$1=1,(SUM(B43:D43)/13),0) -> 0 | E44: =IF(E$1=1,(SUM(B43:E43)/13),0) -> 0 | F44: =IF(F$1=1,(SUM(B43:F43)/13),0) -> 0 | G44: =IF(G$1=1,(SUM(B43:G43)/13),0) -> 0 | H44: =IF(H$1=1,(SUM(B43:H43)/13),0) -> 0 | I44: =IF(I$1=1,(SUM(B43:I43)/13),0) -> 0 | J44: =IF(J$1=1,(SUM(B43:J43)/13),0) -> 0 | K44: =IF(K$1=1,(SUM(B43:K43)/13),0) -> 0 | L44: =IF(L$1=1,(SUM(B43:L43)/13),0) -> 0 | M44: =IF(M$1=1,(SUM(B43:M43)/13),0) -> 0 | N44: =IF(N$1=1,(SUM(B43:N43)/13),0) -> 0 | O44: =IF(O$1=1,(SUM(C43:O43)/13),0) -> 0 | P44: =IF(P$1=1,(SUM(D43:P43)/13),0) -> 0 | Q44: =IF(Q$1=1,(SUM(E43:Q43)/13),0) -> 0 | R44: =IF(R$1=1,(SUM(F43:R43)/13),0) -> 0 | S44: =IF(S$1=1,(SUM(G43:S43)/13),0) -> 0 | T44: =IF(T$1=1,(SUM(H43:T43)/13),0) -> 0 | U44: =IF(U$1=1,(SUM(I43:U43)/13),0) -> 0 | ... AN44: =IF(AN$1=1,(SUM(AB43:AN43)/13),0) -> 0
A45: Other Accident | B45: {=SUM((B38='Accident & Incident Detail'!$C$2:$C$3433)*($A$38='Accident & Incident Detail'!$I$2:$I$3433)*($A$45='Accident & Incident Detail'!$E$2:$E$3433))} -> 0 | C45: {=SUM((C38='Accident & Incident Detail'!$C$2:$C$3433)*($A$38='Accident & Incident Detail'!$I$2:$I$3433)*($A$45='Accident & Incident Detail'!$E$2:$E$3433))} -> 0 | D45: {=SUM((D38='Accident & Incident Detail'!$C$2:$C$3433)*($A$38='Accident & Incident Detail'!$I$2:$I$3433)*($A$45='Accident & Incident Detail'!$E$2:$E$3433))} -> 0 | E45: {=SUM((E38='Accident & Incident Detail'!$C$2:$C$3433)*($A$38='Accident & Incident Detail'!$I$2:$I$3433)*($A$45='Accident & Incident Detail'!$E$2:$E$3433))} -> 0 | F45: {=SUM((F38='Accident & Incident Detail'!$C$2:$C$3433)*($A$38='Accident & Incident Detail'!$I$2:$I$3433)*($A$45='Accident & Incident Detail'!$E$2:$E$3433))} -> 0 | G45: {=SUM((G38='Accident & Incident Detail'!$C$2:$C$3433)*($A$38='Accident & Incident Detail'!$I$2:$I$3433)*($A$45='Accident & Incident Detail'!$E$2:$E$3433))} -> 0 | H45: {=SUM((H38='Accident & Incident Detail'!$C$2:$C$3433)*($A$38='Accident & Incident Detail'!$I$2:$I$3433)*($A$45='Accident & Incident Detail'!$E$2:$E$3433))} -> 0 | I45: {=SUM((I38='Accident & Incident Detail'!$C$2:$C$3433)*($A$38='Accident & Incident Detail'!$I$2:$I$3433)*($A$45='Accident & Incident Detail'!$E$2:$E$3433))} -> 0 | ... AN45: {=SUM((AN38='Accident & Incident Detail'!$C$2:$C$3433)*($A$38='Accident & Incident Detail'!$I$2:$I$3433)*($A$45='Accident & Incident Detail'!$E$2:$E$3433))} -> 0
A46: MAA | B46: =IF(B$1=1,(SUM(B45:B45)/13),0) -> 0 | C46: =IF(C$1=1,(SUM(B45:C45)/13),0) -> 0 | D46: =IF(D$1=1,(SUM(B45:D45)/13),0) -> 0 | E46: =IF(E$1=1,(SUM(B45:E45)/13),0) -> 0 | F46: =IF(F$1=1,(SUM(B45:F45)/13),0) -> 0 | G46: =IF(G$1=1,(SUM(B45:G45)/13),0) -> 0 | H46: =IF(H$1=1,(SUM(B45:H45)/13),0) -> 0 | I46: =IF(I$1=1,(SUM(B45:I45)/13),0) -> 0 | J46: =IF(J$1=1,(SUM(B45:J45)/13),0) -> 0 | K46: =IF(K$1=1,(SUM(B45:K45)/13),0) -> 0 | L46: =IF(L$1=1,(SUM(B45:L45)/13),0) -> 0 | M46: =IF(M$1=1,(SUM(B45:M45)/13),0) -> 0 | N46: =IF(N$1=1,(SUM(B45:N45)/13),0) -> 0 | O46: =IF(O$1=1,(SUM(C45:O45)/13),0) -> 0 | P46: =IF(P$1=1,(SUM(D45:P45)/13),0) -> 0 | Q46: =IF(Q$1=1,(SUM(E45:Q45)/13),0) -> 0 | R46: =IF(R$1=1,(SUM(F45:R45)/13),0) -> 0 | S46: =IF(S$1=1,(SUM(G45:S45)/13),0) -> 0.076923077 | T46: =IF(T$1=1,(SUM(H45:T45)/13),0) -> 0.076923077 | U46: =IF(U$1=1,(SUM(I45:U45)/13),0) -> 0.076923077 | ... AN46: =IF(AN$1=1,(SUM(AB45:AN45)/13),0) -> 0
A47: STF on Tram | B47: {=SUM((B38='Accident & Incident Detail'!$C$2:$C$3433)*($A$38='Accident & Incident Detail'!$I$2:$I$3433)*($A$47='Accident & Incident Detail'!$E$2:$E$3433))} -> 0 | C47: {=SUM((C38='Accident & Incident Detail'!$C$2:$C$3433)*($A$38='Accident & Incident Detail'!$I$2:$I$3433)*($A$47='Accident & Incident Detail'!$E$2:$E$3433))} -> 0 | D47: {=SUM((D38='Accident & Incident Detail'!$C$2:$C$3433)*($A$38='Accident & Incident Detail'!$I$2:$I$3433)*($A$47='Accident & Incident Detail'!$E$2:$E$3433))} -> 0 | E47: {=SUM((E38='Accident & Incident Detail'!$C$2:$C$3433)*($A$38='Accident & Incident Detail'!$I$2:$I$3433)*($A$47='Accident & Incident Detail'!$E$2:$E$3433))} -> 0 | F47: {=SUM((F38='Accident & Incident Detail'!$C$2:$C$3433)*($A$38='Accident & Incident Detail'!$I$2:$I$3433)*($A$47='Accident & Incident Detail'!$E$2:$E$3433))} -> 0 | G47: {=SUM((G38='Accident & Incident Detail'!$C$2:$C$3433)*($A$38='Accident & Incident Detail'!$I$2:$I$3433)*($A$47='Accident & Incident Detail'!$E$2:$E$3433))} -> 0 | H47: {=SUM((H38='Accident & Incident Detail'!$C$2:$C$3433)*($A$38='Accident & Incident Detail'!$I$2:$I$3433)*($A$47='Accident & Incident Detail'!$E$2:$E$3433))} -> 0 | I47: {=SUM((I38='Accident & Incident Detail'!$C$2:$C$3433)*($A$38='Accident & Incident Detail'!$I$2:$I$3433)*($A$47='Accident & Incident Detail'!$E$2:$E$3433))} -> 0 | ... AN47: {=SUM((AN38='Accident & Incident Detail'!$C$2:$C$3433)*($A$38='Accident & Incident Detail'!$I$2:$I$3433)*($A$47='Accident & Incident Detail'!$E$2:$E$3433))} -> 0
A48: MAA | B48: =IF(B$1=1,(SUM(B47:B47)/13),0) -> 0 | C48: =IF(C$1=1,(SUM(B47:C47)/13),0) -> 0 | D48: =IF(D$1=1,(SUM(B47:D47)/13),0) -> 0 | E48: =IF(E$1=1,(SUM(B47:E47)/13),0) -> 0 | F48: =IF(F$1=1,(SUM(B47:F47)/13),0) -> 0 | G48: =IF(G$1=1,(SUM(B47:G47)/13),0) -> 0 | H48: =IF(H$1=1,(SUM(B47:H47)/13),0) -> 0 | I48: =IF(I$1=1,(SUM(B47:I47)/13),0) -> 0 | J48: =IF(J$1=1,(SUM(B47:J47)/13),0) -> 0 | K48: =IF(K$1=1,(SUM(B47:K47)/13),0) -> 0.076923077 | L48: =IF(L$1=1,(SUM(B47:L47)/13),0) -> 0.076923077 | M48: =IF(M$1=1,(SUM(B47:M47)/13),0) -> 0.076923077 | N48: =IF(N$1=1,(SUM(B47:N47)/13),0) -> 0.076923077 | O48: =IF(O$1=1,(SUM(C47:O47)/13),0) -> 0.076923077 | P48: =IF(P$1=1,(SUM(D47:P47)/13),0) -> 0.076923077 | Q48: =IF(Q$1=1,(SUM(E47:Q47)/13),0) -> 0.076923077 | R48: =IF(R$1=1,(SUM(F47:R47)/13),0) -> 0.15384615 | S48: =IF(S$1=1,(SUM(G47:S47)/13),0) -> 0.15384615 | T48: =IF(T$1=1,(SUM(H47:T47)/13),0) -> 0.23076923 | U48: =IF(U$1=1,(SUM(I47:U47)/13),0) -> 0.23076923 | ... AN48: =IF(AN$1=1,(SUM(AB47:AN47)/13),0) -> 0
A49: STF Other | B49: {=SUM((B38='Accident & Incident Detail'!$C$2:$C$3433)*($A$38='Accident & Incident Detail'!$I$2:$I$3433)*($A$49='Accident & Incident Detail'!$E$2:$E$3433))} -> 0 | C49: {=SUM((C38='Accident & Incident Detail'!$C$2:$C$3433)*($A$38='Accident & Incident Detail'!$I$2:$I$3433)*($A$49='Accident & Incident Detail'!$E$2:$E$3433))} -> 0 | D49: {=SUM((D38='Accident & Incident Detail'!$C$2:$C$3433)*($A$38='Accident & Incident Detail'!$I$2:$I$3433)*($A$49='Accident & Incident Detail'!$E$2:$E$3433))} -> 0 | E49: {=SUM((E38='Accident & Incident Detail'!$C$2:$C$3433)*($A$38='Accident & Incident Detail'!$I$2:$I$3433)*($A$49='Accident & Incident Detail'!$E$2:$E$3433))} -> 0 | F49: {=SUM((F38='Accident & Incident Detail'!$C$2:$C$3433)*($A$38='Accident & Incident Detail'!$I$2:$I$3433)*($A$49='Accident & Incident Detail'!$E$2:$E$3433))} -> 0 | G49: {=SUM((G38='Accident & Incident Detail'!$C$2:$C$3433)*($A$38='Accident & Incident Detail'!$I$2:$I$3433)*($A$49='Accident & Incident Detail'!$E$2:$E$3433))} -> 0 | H49: {=SUM((H38='Accident & Incident Detail'!$C$2:$C$3433)*($A$38='Accident & Incident Detail'!$I$2:$I$3433)*($A$49='Accident & Incident Detail'!$E$2:$E$3433))} -> 0 | I49: {=SUM((I38='Accident & Incident Detail'!$C$2:$C$3433)*($A$38='Accident & Incident Detail'!$I$2:$I$3433)*($A$49='Accident & Incident Detail'!$E$2:$E$3433))} -> 0 | ... AN49: {=SUM((AN38='Accident & Incident Detail'!$C$2:$C$3433)*($A$38='Accident & Incident Detail'!$I$2:$I$3433)*($A$49='Accident & Incident Detail'!$E$2:$E$3433))} -> 0
A50: MAA | B50: =IF(B$1=1,(SUM(B49:B49)/13),0) -> 0 | C50: =IF(C$1=1,(SUM(B49:C49)/13),0) -> 0 | D50: =IF(D$1=1,(SUM(B49:D49)/13),0) -> 0 | E50: =IF(E$1=1,(SUM(B49:E49)/13),0) -> 0 | F50: =IF(F$1=1,(SUM(B49:F49)/13),0) -> 0 | G50: =IF(G$1=1,(SUM(B49:G49)/13),0) -> 0 | H50: =IF(H$1=1,(SUM(B49:H49)/13),0) -> 0 | I50: =IF(I$1=1,(SUM(B49:I49)/13),0) -> 0 | J50: =IF(J$1=1,(SUM(B49:J49)/13),0) -> 0.076923077 | K50: =IF(K$1=1,(SUM(B49:K49)/13),0) -> 0.15384615 | L50: =IF(L$1=1,(SUM(B49:L49)/13),0) -> 0.38461538 | M50: =IF(M$1=1,(SUM(B49:M49)/13),0) -> 0.46153846 | N50: =IF(N$1=1,(SUM(B49:N49)/13),0) -> 0.46153846 | O50: =IF(O$1=1,(SUM(C49:O49)/13),0) -> 0.53846154 | P50: =IF(P$1=1,(SUM(D49:P49)/13),0) -> 0.84615385 | Q50: =IF(Q$1=1,(SUM(E49:Q49)/13),0) -> 0.84615385 | R50: =IF(R$1=1,(SUM(F49:R49)/13),0) -> 0.92307692 | S50: =IF(S$1=1,(SUM(G49:S49)/13),0) -> 1 | T50: =IF(T$1=1,(SUM(H49:T49)/13),0) -> 1 | U50: =IF(U$1=1,(SUM(I49:U49)/13),0) -> 1.2307692 | ... AN50: =IF(AN$1=1,(SUM(AB49:AN49)/13),0) -> 0
A51: STF on Tram | B51: {=SUM((B38='Accident & Incident Detail'!$C$2:$C$3433)*($A$38='Accident & Incident Detail'!$I$2:$I$3433)*($A$51='Accident & Incident Detail'!$E$2:$E$3433))} -> 0 | C51: {=SUM((C38='Accident & Incident Detail'!$C$2:$C$3433)*($A$38='Accident & Incident Detail'!$I$2:$I$3433)*($A$51='Accident & Incident Detail'!$E$2:$E$3433))} -> 0 | D51: {=SUM((D38='Accident & Incident Detail'!$C$2:$C$3433)*($A$38='Accident & Incident Detail'!$I$2:$I$3433)*($A$51='Accident & Incident Detail'!$E$2:$E$3433))} -> 0 | E51: {=SUM((E38='Accident & Incident Detail'!$C$2:$C$3433)*($A$38='Accident & Incident Detail'!$I$2:$I$3433)*($A$51='Accident & Incident Detail'!$E$2:$E$3433))} -> 0 | F51: {=SUM((F38='Accident & Incident Detail'!$C$2:$C$3433)*($A$38='Accident & Incident Detail'!$I$2:$I$3433)*($A$51='Accident & Incident Detail'!$E$2:$E$3433))} -> 0 | G51: {=SUM((G38='Accident & Incident Detail'!$C$2:$C$3433)*($A$38='Accident & Incident Detail'!$I$2:$I$3433)*($A$51='Accident & Incident Detail'!$E$2:$E$3433))} -> 0 | H51: {=SUM((H38='Accident & Incident Detail'!$C$2:$C$3433)*($A$38='Accident & Incident Detail'!$I$2:$I$3433)*($A$51='Accident & Incident Detail'!$E$2:$E$3433))} -> 0 | I51: {=SUM((I38='Accident & Incident Detail'!$C$2:$C$3433)*($A$38='Accident & Incident Detail'!$I$2:$I$3433)*($A$51='Accident & Incident Detail'!$E$2:$E$3433))} -> 0 | ... AN51: {=SUM((AN38='Accident & Incident Detail'!$C$2:$C$3433)*($A$38='Accident & Incident Detail'!$I$2:$I$3433)*($A$51='Accident & Incident Detail'!$E$2:$E$3433))} -> 0
A52: MAA | B52: =IF(B$1=1,(SUM(B51:B51)/13),0) -> 0 | C52: =IF(C$1=1,(SUM(B51:C51)/13),0) -> 0 | D52: =IF(D$1=1,(SUM(B51:D51)/13),0) -> 0 | E52: =IF(E$1=1,(SUM(B51:E51)/13),0) -> 0 | F52: =IF(F$1=1,(SUM(B51:F51)/13),0) -> 0 | G52: =IF(G$1=1,(SUM(B51:G51)/13),0) -> 0 | H52: =IF(H$1=1,(SUM(B51:H51)/13),0) -> 0 | I52: =IF(I$1=1,(SUM(B51:I51)/13),0) -> 0 | J52: =IF(J$1=1,(SUM(B51:J51)/13),0) -> 0 | K52: =IF(K$1=1,(SUM(B51:K51)/13),0) -> 0.076923077 | L52: =IF(L$1=1,(SUM(B51:L51)/13),0) -> 0.076923077 | M52: =IF(M$1=1,(SUM(B51:M51)/13),0) -> 0.076923077 | N52: =IF(N$1=1,(SUM(B51:N51)/13),0) -> 0.076923077 | O52: =IF(O$1=1,(SUM(C51:O51)/13),0) -> 0.076923077 | P52: =IF(P$1=1,(SUM(D51:P51)/13),0) -> 0.076923077 | Q52: =IF(Q$1=1,(SUM(E51:Q51)/13),0) -> 0.076923077 | R52: =IF(R$1=1,(SUM(F51:R51)/13),0) -> 0.15384615 | S52: =IF(S$1=1,(SUM(G51:S51)/13),0) -> 0.15384615 | T52: =IF(T$1=1,(SUM(H51:T51)/13),0) -> 0.23076923 | U52: =IF(U$1=1,(SUM(I51:U51)/13),0) -> 0.23076923 | ... AN52: =IF(AN$1=1,(SUM(AB51:AN51)/13),0) -> 0
A53: Total | B53: =SUM(B39+B41+B43+B45+B47+B49+B51) -> 0 | C53: =SUM(C39+C41+C43+C45+C47+C49+C51) -> 0 | D53: =SUM(D39+D41+D43+D45+D47+D49+D51) -> 0 | E53: =SUM(E39+E41+E43+E45+E47+E49+E51) -> 0 | F53: =SUM(F39+F41+F43+F45+F47+F49+F51) -> 0 | G53: =SUM(G39+G41+G43+G45+G47+G49+G51) -> 0 | H53: =SUM(H39+H41+H43+H45+H47+H49+H51) -> 0 | I53: =SUM(I39+I41+I43+I45+I47+I49+I51) -> 0 | ... AN53: =SUM(AN39+AN41+AN43+AN45+AN47+AN49+AN51) -> 0
A54: MAA | B54: =IF(B1,(SUM(B53:B53)/13),0) -> 0 | C54: =IF(C1,(SUM(B53:C53)/13),0) -> 0 | D54: =IF(D1,(SUM(B53:D53)/13),0) -> 0 | E54: =IF(E1,(SUM(B53:E53)/13),0) -> 0 | F54: =IF(F1,(SUM(B53:F53)/13),0) -> 0 | G54: =IF(G1,(SUM(B53:G53)/13),0) -> 0 | H54: =IF(H1,(SUM(B53:H53)/13),0) -> 0 | I54: =IF(I1,(SUM(B53:I53)/13),0) -> 0 | J54: =IF(J1,(SUM(B53:J53)/13),0) -> 0.076923077 | K54: =IF(K1,(SUM(B53:K53)/13),0) -> 0.30769231 | L54: =IF(L1,(SUM(B53:L53)/13),0) -> 0.53846154 | M54: =IF(M1,(SUM(B53:M53)/13),0) -> 0.61538462 | N54: =IF(N1,(SUM(B53:N53)/13),0) -> 0.61538462 | O54: =IF(O1,(SUM(C53:O53)/13),0) -> 0.69230769 | P54: =IF(P1,(SUM(D53:P53)/13),0) -> 1 | Q54: =IF(Q1,(SUM(E53:Q53)/13),0) -> 1 | R54: =IF(R1,(SUM(F53:R53)/13),0) -> 1.2307692 | S54: =IF(S1,(SUM(G53:S53)/13),0) -> 1.3846154 | T54: =IF(T1,(SUM(H53:T53)/13),0) -> 1.5384615 | U54: =IF(U1,(SUM(I53:U53)/13),0) -> 1.7692308 | ... AN54: =IF(AN1,(SUM(AB53:AN53)/13),0) -> 0
A56: Customer Service Staff Accident
B57: 2301 | C57: 2302 | D57: 2303 | E57: 2304 | F57: 2305 | G57: 2306 | H57: 2307 | I57: 2308 | J57: 2309 | K57: 2310 | L57: 2311 | M57: 2312 | N57: 2313 | O57: 2401 | P57: 2402 | Q57: 2403 | R57: 2404 | S57: 2405 | T57: 2406 | U57: 2407 | V57: 2408 | W57: 2409 | X57: 2410 | Y57: 2411 | Z57: 2412 | AA57: 2413 | AB57: 2501 | AC57: 2502 | AD57: 2503 | AE57: 2504 | AF57: 2505 | AG57: 2506 | AH57: 2507 | AI57: 2508 | AJ57: 2509 | AK57: 2510 | AL57: 2511 | AM57: 2512 | AN57: 2513
A58: Burn/Scald | B58: {=SUM((B$38='Accident & Incident Detail'!$C$2:$C$3433)*("Staff"='Accident & Incident Detail'!$K$2:$K$3433)*($A$58='Accident & Incident Detail'!$E$2:$E$3433)*("CS"='Accident & Incident Detail'!$R$2:$R$3433))} -> 0 | C58: {=SUM((C$38='Accident & Incident Detail'!$C$2:$C$3433)*("Staff"='Accident & Incident Detail'!$K$2:$K$3433)*($A$58='Accident & Incident Detail'!$E$2:$E$3433)*("CS"='Accident & Incident Detail'!$R$2:$R$3433))} -> 0 | D58: {=SUM((D$38='Accident & Incident Detail'!$C$2:$C$3433)*("Staff"='Accident & Incident Detail'!$K$2:$K$3433)*($A$58='Accident & Incident Detail'!$E$2:$E$3433)*("CS"='Accident & Incident Detail'!$R$2:$R$3433))} -> 0 | E58: {=SUM((E$38='Accident & Incident Detail'!$C$2:$C$3433)*("Staff"='Accident & Incident Detail'!$K$2:$K$3433)*($A$58='Accident & Incident Detail'!$E$2:$E$3433)*("CS"='Accident & Incident Detail'!$R$2:$R$3433))} -> 0 | F58: {=SUM((F$38='Accident & Incident Detail'!$C$2:$C$3433)*("Staff"='Accident & Incident Detail'!$K$2:$K$3433)*($A$58='Accident & Incident Detail'!$E$2:$E$3433)*("CS"='Accident & Incident Detail'!$R$2:$R$3433))} -> 0 | G58: {=SUM((G$38='Accident & Incident Detail'!$C$2:$C$3433)*("Staff"='Accident & Incident Detail'!$K$2:$K$3433)*($A$58='Accident & Incident Detail'!$E$2:$E$3433)*("CS"='Accident & Incident Detail'!$R$2:$R$3433))} -> 0 | H58: {=SUM((H$38='Accident & Incident Detail'!$C$2:$C$3433)*("Staff"='Accident & Incident Detail'!$K$2:$K$3433)*($A$58='Accident & Incident Detail'!$E$2:$E$3433)*("CS"='Accident & Incident Detail'!$R$2:$R$3433))} -> 0 | I58: {=SUM((I$38='Accident & Incident Detail'!$C$2:$C$3433)*("Staff"='Accident & Incident Detail'!$K$2:$K$3433)*($A$58='Accident & Incident Detail'!$E$2:$E$3433)*("CS"='Accident & Incident Detail'!$R$2:$R$3433))} -> 0 | ... AN58: {=SUM((AN$38='Accident & Incident Detail'!$C$2:$C$3433)*("Staff"='Accident & Incident Detail'!$K$2:$K$3433)*($A$58='Accident & Incident Detail'!$E$2:$E$3433)*("CS"='Accident & Incident Detail'!$R$2:$R$3433))} -> 0
A59: MAA | B59: =IF(B$1=1,(SUM(B58:B58)/13),0) -> 0 | C59: =IF(C$1=1,(SUM(B58:C58)/13),0) -> 0 | D59: =IF(D$1=1,(SUM(B58:D58)/13),0) -> 0 | E59: =IF(E$1=1,(SUM(B58:E58)/13),0) -> 0 | F59: =IF(F$1=1,(SUM(B58:F58)/13),0) -> 0 | G59: =IF(G$1=1,(SUM(B58:G58)/13),0) -> 0 | H59: =IF(H$1=1,(SUM(B58:H58)/13),0) -> 0 | I59: =IF(I$1=1,(SUM(B58:I58)/13),0) -> 0 | J59: =IF(J$1=1,(SUM(B58:J58)/13),0) -> 0 | K59: =IF(K$1=1,(SUM(B58:K58)/13),0) -> 0 | L59: =IF(L$1=1,(SUM(B58:L58)/13),0) -> 0 | M59: =IF(M$1=1,(SUM(B58:M58)/13),0) -> 0 | N59: =IF(N$1=1,(SUM(B58:N58)/13),0) -> 0 | O59: =IF(O$1=1,(SUM(C58:O58)/13),0) -> 0 | P59: =IF(P$1=1,(SUM(D58:P58)/13),0) -> 0 | Q59: =IF(Q$1=1,(SUM(E58:Q58)/13),0) -> 0 | R59: =IF(R$1=1,(SUM(F58:R58)/13),0) -> 0 | S59: =IF(S$1=1,(SUM(G58:S58)/13),0) -> 0 | T59: =IF(T$1=1,(SUM(H58:T58)/13),0) -> 0 | U59: =IF(U$1=1,(SUM(I58:U58)/13),0) -> 0 | ... AN59: =IF(AN$1=1,(SUM(AB58:AN58)/13),0) -> 0
A60: Contact | B60: {=SUM((B$38='Accident & Incident Detail'!$C$2:$C$3433)*("Staff"='Accident & Incident Detail'!$K$2:$K$3433)*($A$60='Accident & Incident Detail'!$E$2:$E$3433)*("CS"='Accident & Incident Detail'!$R$2:$R$3433))} -> 0 | C60: {=SUM((C$38='Accident & Incident Detail'!$C$2:$C$3433)*("Staff"='Accident & Incident Detail'!$K$2:$K$3433)*($A$60='Accident & Incident Detail'!$E$2:$E$3433)*("CS"='Accident & Incident Detail'!$R$2:$R$3433))} -> 0 | D60: {=SUM((D$38='Accident & Incident Detail'!$C$2:$C$3433)*("Staff"='Accident & Incident Detail'!$K$2:$K$3433)*($A$60='Accident & Incident Detail'!$E$2:$E$3433)*("CS"='Accident & Incident Detail'!$R$2:$R$3433))} -> 0 | E60: {=SUM((E$38='Accident & Incident Detail'!$C$2:$C$3433)*("Staff"='Accident & Incident Detail'!$K$2:$K$3433)*($A$60='Accident & Incident Detail'!$E$2:$E$3433)*("CS"='Accident & Incident Detail'!$R$2:$R$3433))} -> 0 | F60: {=SUM((F$38='Accident & Incident Detail'!$C$2:$C$3433)*("Staff"='Accident & Incident Detail'!$K$2:$K$3433)*($A$60='Accident & Incident Detail'!$E$2:$E$3433)*("CS"='Accident & Incident Detail'!$R$2:$R$3433))} -> 0 | G60: {=SUM((G$38='Accident & Incident Detail'!$C$2:$C$3433)*("Staff"='Accident & Incident Detail'!$K$2:$K$3433)*($A$60='Accident & Incident Detail'!$E$2:$E$3433)*("CS"='Accident & Incident Detail'!$R$2:$R$3433))} -> 0 | H60: {=SUM((H$38='Accident & Incident Detail'!$C$2:$C$3433)*("Staff"='Accident & Incident Detail'!$K$2:$K$3433)*($A$60='Accident & Incident Detail'!$E$2:$E$3433)*("CS"='Accident & Incident Detail'!$R$2:$R$3433))} -> 0 | I60: {=SUM((I$38='Accident & Incident Detail'!$C$2:$C$3433)*("Staff"='Accident & Incident Detail'!$K$2:$K$3433)*($A$60='Accident & Incident Detail'!$E$2:$E$3433)*("CS"='Accident & Incident Detail'!$R$2:$R$3433))} -> 0 | ... AN60: {=SUM((AN$38='Accident & Incident Detail'!$C$2:$C$3433)*("Staff"='Accident & Incident Detail'!$K$2:$K$3433)*($A$60='Accident & Incident Detail'!$E$2:$E$3433)*("CS"='Accident & Incident Detail'!$R$2:$R$3433))} -> 0
A61: MAA | B61: =IF(B$1=1,(SUM(B60:B60)/13),0) -> 0 | C61: =IF(C$1=1,(SUM(B60:C60)/13),0) -> 0 | D61: =IF(D$1=1,(SUM(B60:D60)/13),0) -> 0 | E61: =IF(E$1=1,(SUM(B60:E60)/13),0) -> 0 | F61: =IF(F$1=1,(SUM(B60:F60)/13),0) -> 0 | G61: =IF(G$1=1,(SUM(B60:G60)/13),0) -> 0 | H61: =IF(H$1=1,(SUM(B60:H60)/13),0) -> 0 | I61: =IF(I$1=1,(SUM(B60:I60)/13),0) -> 0 | J61: =IF(J$1=1,(SUM(B60:J60)/13),0) -> 0 | K61: =IF(K$1=1,(SUM(B60:K60)/13),0) -> 0 | L61: =IF(L$1=1,(SUM(B60:L60)/13),0) -> 0 | M61: =IF(M$1=1,(SUM(B60:M60)/13),0) -> 0 | N61: =IF(N$1=1,(SUM(B60:N60)/13),0) -> 0 | O61: =IF(O$1=1,(SUM(C60:O60)/13),0) -> 0 | P61: =IF(P$1=1,(SUM(D60:P60)/13),0) -> 0 | Q61: =IF(Q$1=1,(SUM(E60:Q60)/13),0) -> 0 | R61: =IF(R$1=1,(SUM(F60:R60)/13),0) -> 0 | S61: =IF(S$1=1,(SUM(G60:S60)/13),0) -> 0 | T61: =IF(T$1=1,(SUM(H60:T60)/13),0) -> 0 | U61: =IF(U$1=1,(SUM(I60:U60)/13),0) -> 0 | ... AN61: =IF(AN$1=1,(SUM(AB60:AN60)/13),0) -> 0
A62: Door trap | B62: {=SUM((B$38='Accident & Incident Detail'!$C$2:$C$3433)*("Staff"='Accident & Incident Detail'!$K$2:$K$3433)*($A$62='Accident & Incident Detail'!$E$2:$E$3433)*("CS"='Accident & Incident Detail'!$R$2:$R$3433))} -> 0 | C62: {=SUM((C$38='Accident & Incident Detail'!$C$2:$C$3433)*("Staff"='Accident & Incident Detail'!$K$2:$K$3433)*($A$62='Accident & Incident Detail'!$E$2:$E$3433)*("CS"='Accident & Incident Detail'!$R$2:$R$3433))} -> 0 | D62: {=SUM((D$38='Accident & Incident Detail'!$C$2:$C$3433)*("Staff"='Accident & Incident Detail'!$K$2:$K$3433)*($A$62='Accident & Incident Detail'!$E$2:$E$3433)*("CS"='Accident & Incident Detail'!$R$2:$R$3433))} -> 0 | E62: {=SUM((E$38='Accident & Incident Detail'!$C$2:$C$3433)*("Staff"='Accident & Incident Detail'!$K$2:$K$3433)*($A$62='Accident & Incident Detail'!$E$2:$E$3433)*("CS"='Accident & Incident Detail'!$R$2:$R$3433))} -> 0 | F62: {=SUM((F$38='Accident & Incident Detail'!$C$2:$C$3433)*("Staff"='Accident & Incident Detail'!$K$2:$K$3433)*($A$62='Accident & Incident Detail'!$E$2:$E$3433)*("CS"='Accident & Incident Detail'!$R$2:$R$3433))} -> 0 | G62: {=SUM((G$38='Accident & Incident Detail'!$C$2:$C$3433)*("Staff"='Accident & Incident Detail'!$K$2:$K$3433)*($A$62='Accident & Incident Detail'!$E$2:$E$3433)*("CS"='Accident & Incident Detail'!$R$2:$R$3433))} -> 0 | H62: {=SUM((H$38='Accident & Incident Detail'!$C$2:$C$3433)*("Staff"='Accident & Incident Detail'!$K$2:$K$3433)*($A$62='Accident & Incident Detail'!$E$2:$E$3433)*("CS"='Accident & Incident Detail'!$R$2:$R$3433))} -> 0 | I62: {=SUM((I$38='Accident & Incident Detail'!$C$2:$C$3433)*("Staff"='Accident & Incident Detail'!$K$2:$K$3433)*($A$62='Accident & Incident Detail'!$E$2:$E$3433)*("CS"='Accident & Incident Detail'!$R$2:$R$3433))} -> 0 | ... AN62: {=SUM((AN$38='Accident & Incident Detail'!$C$2:$C$3433)*("Staff"='Accident & Incident Detail'!$K$2:$K$3433)*($A$62='Accident & Incident Detail'!$E$2:$E$3433)*("CS"='Accident & Incident Detail'!$R$2:$R$3433))} -> 0
A63: MAA | B63: =IF(B$1=1,(SUM(B62:B62)/13),0) -> 0 | C63: =IF(C$1=1,(SUM(B62:C62)/13),0) -> 0 | D63: =IF(D$1=1,(SUM(B62:D62)/13),0) -> 0 | E63: =IF(E$1=1,(SUM(B62:E62)/13),0) -> 0 | F63: =IF(F$1=1,(SUM(B62:F62)/13),0) -> 0 | G63: =IF(G$1=1,(SUM(B62:G62)/13),0) -> 0 | H63: =IF(H$1=1,(SUM(B62:H62)/13),0) -> 0 | I63: =IF(I$1=1,(SUM(B62:I62)/13),0) -> 0 | J63: =IF(J$1=1,(SUM(B62:J62)/13),0) -> 0 | K63: =IF(K$1=1,(SUM(B62:K62)/13),0) -> 0 | L63: =IF(L$1=1,(SUM(B62:L62)/13),0) -> 0 | M63: =IF(M$1=1,(SUM(B62:M62)/13),0) -> 0 | N63: =IF(N$1=1,(SUM(B62:N62)/13),0) -> 0 | O63: =IF(O$1=1,(SUM(C62:O62)/13),0) -> 0 | P63: =IF(P$1=1,(SUM(D62:P62)/13),0) -> 0 | Q63: =IF(Q$1=1,(SUM(E62:Q62)/13),0) -> 0 | R63: =IF(R$1=1,(SUM(F62:R62)/13),0) -> 0 | S63: =IF(S$1=1,(SUM(G62:S62)/13),0) -> 0 | T63: =IF(T$1=1,(SUM(H62:T62)/13),0) -> 0 | U63: =IF(U$1=1,(SUM(I62:U62)/13),0) -> 0 | ... AN63: =IF(AN$1=1,(SUM(AB62:AN62)/13),0) -> 0
A64: Other Accident | B64: {=SUM((B$38='Accident & Incident Detail'!$C$2:$C$3433)*("Staff"='Accident & Incident Detail'!$K$2:$K$3433)*($A$64='Accident & Incident Detail'!$E$2:$E$3433)*("CS"='Accident & Incident Detail'!$R$2:$R$3433))} -> 0 | C64: {=SUM((C$38='Accident & Incident Detail'!$C$2:$C$3433)*("Staff"='Accident & Incident Detail'!$K$2:$K$3433)*($A$64='Accident & Incident Detail'!$E$2:$E$3433)*("CS"='Accident & Incident Detail'!$R$2:$R$3433))} -> 0 | D64: {=SUM((D$38='Accident & Incident Detail'!$C$2:$C$3433)*("Staff"='Accident & Incident Detail'!$K$2:$K$3433)*($A$64='Accident & Incident Detail'!$E$2:$E$3433)*("CS"='Accident & Incident Detail'!$R$2:$R$3433))} -> 0 | E64: {=SUM((E$38='Accident & Incident Detail'!$C$2:$C$3433)*("Staff"='Accident & Incident Detail'!$K$2:$K$3433)*($A$64='Accident & Incident Detail'!$E$2:$E$3433)*("CS"='Accident & Incident Detail'!$R$2:$R$3433))} -> 0 | F64: {=SUM((F$38='Accident & Incident Detail'!$C$2:$C$3433)*("Staff"='Accident & Incident Detail'!$K$2:$K$3433)*($A$64='Accident & Incident Detail'!$E$2:$E$3433)*("CS"='Accident & Incident Detail'!$R$2:$R$3433))} -> 0 | G64: {=SUM((G$38='Accident & Incident Detail'!$C$2:$C$3433)*("Staff"='Accident & Incident Detail'!$K$2:$K$3433)*($A$64='Accident & Incident Detail'!$E$2:$E$3433)*("CS"='Accident & Incident Detail'!$R$2:$R$3433))} -> 0 | H64: {=SUM((H$38='Accident & Incident Detail'!$C$2:$C$3433)*("Staff"='Accident & Incident Detail'!$K$2:$K$3433)*($A$64='Accident & Incident Detail'!$E$2:$E$3433)*("CS"='Accident & Incident Detail'!$R$2:$R$3433))} -> 0 | I64: {=SUM((I$38='Accident & Incident Detail'!$C$2:$C$3433)*("Staff"='Accident & Incident Detail'!$K$2:$K$3433)*($A$64='Accident & Incident Detail'!$E$2:$E$3433)*("CS"='Accident & Incident Detail'!$R$2:$R$3433))} -> 0 | ... AN64: {=SUM((AN$38='Accident & Incident Detail'!$C$2:$C$3433)*("Staff"='Accident & Incident Detail'!$K$2:$K$3433)*($A$64='Accident & Incident Detail'!$E$2:$E$3433)*("CS"='Accident & Incident Detail'!$R$2:$R$3433))} -> 0
A65: MAA | B65: =IF(B$1=1,(SUM(B64:B64)/13),0) -> 0 | C65: =IF(C$1=1,(SUM(B64:C64)/13),0) -> 0 | D65: =IF(D$1=1,(SUM(B64:D64)/13),0) -> 0 | E65: =IF(E$1=1,(SUM(B64:E64)/13),0) -> 0 | F65: =IF(F$1=1,(SUM(B64:F64)/13),0) -> 0 | G65: =IF(G$1=1,(SUM(B64:G64)/13),0) -> 0 | H65: =IF(H$1=1,(SUM(B64:H64)/13),0) -> 0 | I65: =IF(I$1=1,(SUM(B64:I64)/13),0) -> 0 | J65: =IF(J$1=1,(SUM(B64:J64)/13),0) -> 0 | K65: =IF(K$1=1,(SUM(B64:K64)/13),0) -> 0 | L65: =IF(L$1=1,(SUM(B64:L64)/13),0) -> 0 | M65: =IF(M$1=1,(SUM(B64:M64)/13),0) -> 0 | N65: =IF(N$1=1,(SUM(B64:N64)/13),0) -> 0 | O65: =IF(O$1=1,(SUM(C64:O64)/13),0) -> 0 | P65: =IF(P$1=1,(SUM(D64:P64)/13),0) -> 0 | Q65: =IF(Q$1=1,(SUM(E64:Q64)/13),0) -> 0 | R65: =IF(R$1=1,(SUM(F64:R64)/13),0) -> 0 | S65: =IF(S$1=1,(SUM(G64:S64)/13),0) -> 0 | T65: =IF(T$1=1,(SUM(H64:T64)/13),0) -> 0 | U65: =IF(U$1=1,(SUM(I64:U64)/13),0) -> 0 | ... AN65: =IF(AN$1=1,(SUM(AB64:AN64)/13),0) -> 0
A66: STF on Tram | B66: {=SUM((B$38='Accident & Incident Detail'!$C$2:$C$3433)*("Staff"='Accident & Incident Detail'!$K$2:$K$3433)*($A$66='Accident & Incident Detail'!$E$2:$E$3433)*("CS"='Accident & Incident Detail'!$R$2:$R$3433))} -> 0 | C66: {=SUM((C$38='Accident & Incident Detail'!$C$2:$C$3433)*("Staff"='Accident & Incident Detail'!$K$2:$K$3433)*($A$66='Accident & Incident Detail'!$E$2:$E$3433)*("CS"='Accident & Incident Detail'!$R$2:$R$3433))} -> 0 | D66: {=SUM((D$38='Accident & Incident Detail'!$C$2:$C$3433)*("Staff"='Accident & Incident Detail'!$K$2:$K$3433)*($A$66='Accident & Incident Detail'!$E$2:$E$3433)*("CS"='Accident & Incident Detail'!$R$2:$R$3433))} -> 0 | E66: {=SUM((E$38='Accident & Incident Detail'!$C$2:$C$3433)*("Staff"='Accident & Incident Detail'!$K$2:$K$3433)*($A$66='Accident & Incident Detail'!$E$2:$E$3433)*("CS"='Accident & Incident Detail'!$R$2:$R$3433))} -> 0 | F66: {=SUM((F$38='Accident & Incident Detail'!$C$2:$C$3433)*("Staff"='Accident & Incident Detail'!$K$2:$K$3433)*($A$66='Accident & Incident Detail'!$E$2:$E$3433)*("CS"='Accident & Incident Detail'!$R$2:$R$3433))} -> 0 | G66: {=SUM((G$38='Accident & Incident Detail'!$C$2:$C$3433)*("Staff"='Accident & Incident Detail'!$K$2:$K$3433)*($A$66='Accident & Incident Detail'!$E$2:$E$3433)*("CS"='Accident & Incident Detail'!$R$2:$R$3433))} -> 0 | H66: {=SUM((H$38='Accident & Incident Detail'!$C$2:$C$3433)*("Staff"='Accident & Incident Detail'!$K$2:$K$3433)*($A$66='Accident & Incident Detail'!$E$2:$E$3433)*("CS"='Accident & Incident Detail'!$R$2:$R$3433))} -> 0 | I66: {=SUM((I$38='Accident & Incident Detail'!$C$2:$C$3433)*("Staff"='Accident & Incident Detail'!$K$2:$K$3433)*($A$66='Accident & Incident Detail'!$E$2:$E$3433)*("CS"='Accident & Incident Detail'!$R$2:$R$3433))} -> 0 | ... AN66: {=SUM((AN$38='Accident & Incident Detail'!$C$2:$C$3433)*("Staff"='Accident & Incident Detail'!$K$2:$K$3433)*($A$66='Accident & Incident Detail'!$E$2:$E$3433)*("CS"='Accident & Incident Detail'!$R$2:$R$3433))} -> 0
A67: MAA | B67: =IF(B$1=1,(SUM(B66:B66)/13),0) -> 0 | C67: =IF(C$1=1,(SUM(B66:C66)/13),0) -> 0 | D67: =IF(D$1=1,(SUM(B66:D66)/13),0) -> 0 | E67: =IF(E$1=1,(SUM(B66:E66)/13),0) -> 0 | F67: =IF(F$1=1,(SUM(B66:F66)/13),0) -> 0 | G67: =IF(G$1=1,(SUM(B66:G66)/13),0) -> 0 | H67: =IF(H$1=1,(SUM(B66:H66)/13),0) -> 0 | I67: =IF(I$1=1,(SUM(B66:I66)/13),0) -> 0 | J67: =IF(J$1=1,(SUM(B66:J66)/13),0) -> 0 | K67: =IF(K$1=1,(SUM(B66:K66)/13),0) -> 0.076923077 | L67: =IF(L$1=1,(SUM(B66:L66)/13),0) -> 0.076923077 | M67: =IF(M$1=1,(SUM(B66:M66)/13),0) -> 0.076923077 | N67: =IF(N$1=1,(SUM(B66:N66)/13),0) -> 0.076923077 | O67: =IF(O$1=1,(SUM(C66:O66)/13),0) -> 0.076923077 | P67: =IF(P$1=1,(SUM(D66:P66)/13),0) -> 0.076923077 | Q67: =IF(Q$1=1,(SUM(E66:Q66)/13),0) -> 0.076923077 | R67: =IF(R$1=1,(SUM(F66:R66)/13),0) -> 0.15384615 | S67: =IF(S$1=1,(SUM(G66:S66)/13),0) -> 0.15384615 | T67: =IF(T$1=1,(SUM(H66:T66)/13),0) -> 0.23076923 | U67: =IF(U$1=1,(SUM(I66:U66)/13),0) -> 0.23076923 | ... AN67: =IF(AN$1=1,(SUM(AB66:AN66)/13),0) -> 0
A68: STF Other | B68: {=SUM((B$38='Accident & Incident Detail'!$C$2:$C$3433)*("Staff"='Accident & Incident Detail'!$K$2:$K$3433)*($A$68='Accident & Incident Detail'!$E$2:$E$3433)*("CS"='Accident & Incident Detail'!$R$2:$R$3433))} -> 0 | C68: {=SUM((C$38='Accident & Incident Detail'!$C$2:$C$3433)*("Staff"='Accident & Incident Detail'!$K$2:$K$3433)*($A$68='Accident & Incident Detail'!$E$2:$E$3433)*("CS"='Accident & Incident Detail'!$R$2:$R$3433))} -> 0 | D68: {=SUM((D$38='Accident & Incident Detail'!$C$2:$C$3433)*("Staff"='Accident & Incident Detail'!$K$2:$K$3433)*($A$68='Accident & Incident Detail'!$E$2:$E$3433)*("CS"='Accident & Incident Detail'!$R$2:$R$3433))} -> 0 | E68: {=SUM((E$38='Accident & Incident Detail'!$C$2:$C$3433)*("Staff"='Accident & Incident Detail'!$K$2:$K$3433)*($A$68='Accident & Incident Detail'!$E$2:$E$3433)*("CS"='Accident & Incident Detail'!$R$2:$R$3433))} -> 0 | F68: {=SUM((F$38='Accident & Incident Detail'!$C$2:$C$3433)*("Staff"='Accident & Incident Detail'!$K$2:$K$3433)*($A$68='Accident & Incident Detail'!$E$2:$E$3433)*("CS"='Accident & Incident Detail'!$R$2:$R$3433))} -> 0 | G68: {=SUM((G$38='Accident & Incident Detail'!$C$2:$C$3433)*("Staff"='Accident & Incident Detail'!$K$2:$K$3433)*($A$68='Accident & Incident Detail'!$E$2:$E$3433)*("CS"='Accident & Incident Detail'!$R$2:$R$3433))} -> 0 | H68: {=SUM((H$38='Accident & Incident Detail'!$C$2:$C$3433)*("Staff"='Accident & Incident Detail'!$K$2:$K$3433)*($A$68='Accident & Incident Detail'!$E$2:$E$3433)*("CS"='Accident & Incident Detail'!$R$2:$R$3433))} -> 0 | I68: {=SUM((I$38='Accident & Incident Detail'!$C$2:$C$3433)*("Staff"='Accident & Incident Detail'!$K$2:$K$3433)*($A$68='Accident & Incident Detail'!$E$2:$E$3433)*("CS"='Accident & Incident Detail'!$R$2:$R$3433))} -> 0 | ... AN68: {=SUM((AN$38='Accident & Incident Detail'!$C$2:$C$3433)*("Staff"='Accident & Incident Detail'!$K$2:$K$3433)*($A$68='Accident & Incident Detail'!$E$2:$E$3433)*("CS"='Accident & Incident Detail'!$R$2:$R$3433))} -> 0
A69: MAA | B69: =IF(B$1=1,(SUM(B68:B68)/13),0) -> 0 | C69: =IF(C$1=1,(SUM(B68:C68)/13),0) -> 0 | D69: =IF(D$1=1,(SUM(B68:D68)/13),0) -> 0 | E69: =IF(E$1=1,(SUM(B68:E68)/13),0) -> 0 | F69: =IF(F$1=1,(SUM(B68:F68)/13),0) -> 0 | G69: =IF(G$1=1,(SUM(B68:G68)/13),0) -> 0 | H69: =IF(H$1=1,(SUM(B68:H68)/13),0) -> 0 | I69: =IF(I$1=1,(SUM(B68:I68)/13),0) -> 0 | J69: =IF(J$1=1,(SUM(B68:J68)/13),0) -> 0.076923077 | K69: =IF(K$1=1,(SUM(B68:K68)/13),0) -> 0.076923077 | L69: =IF(L$1=1,(SUM(B68:L68)/13),0) -> 0.23076923 | M69: =IF(M$1=1,(SUM(B68:M68)/13),0) -> 0.30769231 | N69: =IF(N$1=1,(SUM(B68:N68)/13),0) -> 0.30769231 | O69: =IF(O$1=1,(SUM(C68:O68)/13),0) -> 0.30769231 | P69: =IF(P$1=1,(SUM(D68:P68)/13),0) -> 0.61538462 | Q69: =IF(Q$1=1,(SUM(E68:Q68)/13),0) -> 0.61538462 | R69: =IF(R$1=1,(SUM(F68:R68)/13),0) -> 0.69230769 | S69: =IF(S$1=1,(SUM(G68:S68)/13),0) -> 0.69230769 | T69: =IF(T$1=1,(SUM(H68:T68)/13),0) -> 0.69230769 | U69: =IF(U$1=1,(SUM(I68:U68)/13),0) -> 0.84615385 | ... AN69: =IF(AN$1=1,(SUM(AB68:AN68)/13),0) -> 0
A70: STF Tramstop | B70: {=SUM((B$38='Accident & Incident Detail'!$C$2:$C$3433)*("Staff"='Accident & Incident Detail'!$K$2:$K$3433)*($A$70='Accident & Incident Detail'!$E$2:$E$3433)*("CS"='Accident & Incident Detail'!$R$2:$R$3433))} -> 0 | C70: {=SUM((C$38='Accident & Incident Detail'!$C$2:$C$3433)*("Staff"='Accident & Incident Detail'!$K$2:$K$3433)*($A$70='Accident & Incident Detail'!$E$2:$E$3433)*("CS"='Accident & Incident Detail'!$R$2:$R$3433))} -> 0 | D70: {=SUM((D$38='Accident & Incident Detail'!$C$2:$C$3433)*("Staff"='Accident & Incident Detail'!$K$2:$K$3433)*($A$70='Accident & Incident Detail'!$E$2:$E$3433)*("CS"='Accident & Incident Detail'!$R$2:$R$3433))} -> 0 | E70: {=SUM((E$38='Accident & Incident Detail'!$C$2:$C$3433)*("Staff"='Accident & Incident Detail'!$K$2:$K$3433)*($A$70='Accident & Incident Detail'!$E$2:$E$3433)*("CS"='Accident & Incident Detail'!$R$2:$R$3433))} -> 0 | F70: {=SUM((F$38='Accident & Incident Detail'!$C$2:$C$3433)*("Staff"='Accident & Incident Detail'!$K$2:$K$3433)*($A$70='Accident & Incident Detail'!$E$2:$E$3433)*("CS"='Accident & Incident Detail'!$R$2:$R$3433))} -> 0 | G70: {=SUM((G$38='Accident & Incident Detail'!$C$2:$C$3433)*("Staff"='Accident & Incident Detail'!$K$2:$K$3433)*($A$70='Accident & Incident Detail'!$E$2:$E$3433)*("CS"='Accident & Incident Detail'!$R$2:$R$3433))} -> 0 | H70: {=SUM((H$38='Accident & Incident Detail'!$C$2:$C$3433)*("Staff"='Accident & Incident Detail'!$K$2:$K$3433)*($A$70='Accident & Incident Detail'!$E$2:$E$3433)*("CS"='Accident & Incident Detail'!$R$2:$R$3433))} -> 0 | I70: {=SUM((I$38='Accident & Incident Detail'!$C$2:$C$3433)*("Staff"='Accident & Incident Detail'!$K$2:$K$3433)*($A$70='Accident & Incident Detail'!$E$2:$E$3433)*("CS"='Accident & Incident Detail'!$R$2:$R$3433))} -> 0 | ... AN70: {=SUM((AN$38='Accident & Incident Detail'!$C$2:$C$3433)*("Staff"='Accident & Incident Detail'!$K$2:$K$3433)*($A$70='Accident & Incident Detail'!$E$2:$E$3433)*("CS"='Accident & Incident Detail'!$R$2:$R$3433))} -> 0
A71: MAA | B71: =IF(B$1=1,(SUM(B70:B70)/13),0) -> 0 | C71: =IF(C$1=1,(SUM(B70:C70)/13),0) -> 0 | D71: =IF(D$1=1,(SUM(B70:D70)/13),0) -> 0 | E71: =IF(E$1=1,(SUM(B70:E70)/13),0) -> 0 | F71: =IF(F$1=1,(SUM(B70:F70)/13),0) -> 0 | G71: =IF(G$1=1,(SUM(B70:G70)/13),0) -> 0 | H71: =IF(H$1=1,(SUM(B70:H70)/13),0) -> 0 | I71: =IF(I$1=1,(SUM(B70:I70)/13),0) -> 0 | J71: =IF(J$1=1,(SUM(B70:J70)/13),0) -> 0 | K71: =IF(K$1=1,(SUM(B70:K70)/13),0) -> 0 | L71: =IF(L$1=1,(SUM(B70:L70)/13),0) -> 0 | M71: =IF(M$1=1,(SUM(B70:M70)/13),0) -> 0 | N71: =IF(N$1=1,(SUM(B70:N70)/13),0) -> 0 | O71: =IF(O$1=1,(SUM(C70:O70)/13),0) -> 0 | P71: =IF(P$1=1,(SUM(D70:P70)/13),0) -> 0 | Q71: =IF(Q$1=1,(SUM(E70:Q70)/13),0) -> 0 | R71: =IF(R$1=1,(SUM(F70:R70)/13),0) -> 0 | S71: =IF(S$1=1,(SUM(G70:S70)/13),0) -> 0 | T71: =IF(T$1=1,(SUM(H70:T70)/13),0) -> 0 | U71: =IF(U$1=1,(SUM(I70:U70)/13),0) -> 0 | ... AN71: =IF(AN$1=1,(SUM(AB70:AN70)/13),0) -> 0
A72: Near Miss | B72: {=SUM((B$38='Accident & Incident Detail'!$C$2:$C$3433)*("Staff"='Accident & Incident Detail'!$K$2:$K$3433)*($A$72='Accident & Incident Detail'!$E$2:$E$3433)*("CS"='Accident & Incident Detail'!$R$2:$R$3433))} -> 0 | C72: {=SUM((C$38='Accident & Incident Detail'!$C$2:$C$3433)*("Staff"='Accident & Incident Detail'!$K$2:$K$3433)*($A$72='Accident & Incident Detail'!$E$2:$E$3433)*("CS"='Accident & Incident Detail'!$R$2:$R$3433))} -> 0 | D72: {=SUM((D$38='Accident & Incident Detail'!$C$2:$C$3433)*("Staff"='Accident & Incident Detail'!$K$2:$K$3433)*($A$72='Accident & Incident Detail'!$E$2:$E$3433)*("CS"='Accident & Incident Detail'!$R$2:$R$3433))} -> 0 | E72: {=SUM((E$38='Accident & Incident Detail'!$C$2:$C$3433)*("Staff"='Accident & Incident Detail'!$K$2:$K$3433)*($A$72='Accident & Incident Detail'!$E$2:$E$3433)*("CS"='Accident & Incident Detail'!$R$2:$R$3433))} -> 0 | F72: {=SUM((F$38='Accident & Incident Detail'!$C$2:$C$3433)*("Staff"='Accident & Incident Detail'!$K$2:$K$3433)*($A$72='Accident & Incident Detail'!$E$2:$E$3433)*("CS"='Accident & Incident Detail'!$R$2:$R$3433))} -> 0 | G72: {=SUM((G$38='Accident & Incident Detail'!$C$2:$C$3433)*("Staff"='Accident & Incident Detail'!$K$2:$K$3433)*($A$72='Accident & Incident Detail'!$E$2:$E$3433)*("CS"='Accident & Incident Detail'!$R$2:$R$3433))} -> 0 | H72: {=SUM((H$38='Accident & Incident Detail'!$C$2:$C$3433)*("Staff"='Accident & Incident Detail'!$K$2:$K$3433)*($A$72='Accident & Incident Detail'!$E$2:$E$3433)*("CS"='Accident & Incident Detail'!$R$2:$R$3433))} -> 0 | I72: {=SUM((I$38='Accident & Incident Detail'!$C$2:$C$3433)*("Staff"='Accident & Incident Detail'!$K$2:$K$3433)*($A$72='Accident & Incident Detail'!$E$2:$E$3433)*("CS"='Accident & Incident Detail'!$R$2:$R$3433))} -> 0 | ... AN72: {=SUM((AN$38='Accident & Incident Detail'!$C$2:$C$3433)*("Staff"='Accident & Incident Detail'!$K$2:$K$3433)*($A$72='Accident & Incident Detail'!$E$2:$E$3433)*("CS"='Accident & Incident Detail'!$R$2:$R$3433))} -> 0
A73: MAA | B73: =IF(B$1=1,(SUM(B72:B72)/13),0) -> 0 | C73: =IF(C$1=1,(SUM(B72:C72)/13),0) -> 0 | D73: =IF(D$1=1,(SUM(B72:D72)/13),0) -> 0 | E73: =IF(E$1=1,(SUM(B72:E72)/13),0) -> 0 | F73: =IF(F$1=1,(SUM(B72:F72)/13),0) -> 0 | G73: =IF(G$1=1,(SUM(B72:G72)/13),0) -> 0 | H73: =IF(H$1=1,(SUM(B72:H72)/13),0) -> 0 | I73: =IF(I$1=1,(SUM(B72:I72)/13),0) -> 0 | J73: =IF(J$1=1,(SUM(B72:J72)/13),0) -> 0 | K73: =IF(K$1=1,(SUM(B72:K72)/13),0) -> 0 | L73: =IF(L$1=1,(SUM(B72:L72)/13),0) -> 0 | M73: =IF(M$1=1,(SUM(B72:M72)/13),0) -> 0 | N73: =IF(N$1=1,(SUM(B72:N72)/13),0) -> 0 | O73: =IF(O$1=1,(SUM(C72:O72)/13),0) -> 0 | P73: =IF(P$1=1,(SUM(D72:P72)/13),0) -> 0 | Q73: =IF(Q$1=1,(SUM(E72:Q72)/13),0) -> 0 | R73: =IF(R$1=1,(SUM(F72:R72)/13),0) -> 0 | S73: =IF(S$1=1,(SUM(G72:S72)/13),0) -> 0 | T73: =IF(T$1=1,(SUM(H72:T72)/13),0) -> 0 | U73: =IF(U$1=1,(SUM(I72:U72)/13),0) -> 0 | ... AN73: =IF(AN$1=1,(SUM(AB72:AN72)/13),0) -> 0
A74: Total | B74: =SUM(B58+B60+B62+B64+B66+B68+B70+B72) -> 0 | C74: =SUM(C58+C60+C62+C64+C66+C68+C70+C72) -> 0 | D74: =SUM(D58+D60+D62+D64+D66+D68+D70+D72) -> 0 | E74: =SUM(E58+E60+E62+E64+E66+E68+E70+E72) -> 0 | F74: =SUM(F58+F60+F62+F64+F66+F68+F70+F72) -> 0 | G74: =SUM(G58+G60+G62+G64+G66+G68+G70+G72) -> 0 | H74: =SUM(H58+H60+H62+H64+H66+H68+H70+H72) -> 0 | I74: =SUM(I58+I60+I62+I64+I66+I68+I70+I72) -> 0 | ... AN74: =SUM(AN58+AN60+AN62+AN64+AN66+AN68+AN70+AN72) -> 0
A75: MAA | B75: =IF(B31,(SUM(B74:B74)/13),0) -> 0 | C75: =IF(C31,(SUM(B74:C74)/13),0) -> 0 | D75: =IF(D31,(SUM(B74:D74)/13),0) -> 0 | E75: =IF(E31,(SUM(B74:E74)/13),0) -> 0 | F75: =IF(F31,(SUM(B74:F74)/13),0) -> 0 | G75: =IF(G31,(SUM(B74:G74)/13),0) -> 0 | H75: =IF(H31,(SUM(B74:H74)/13),0) -> 0 | I75: =IF(I31,(SUM(B74:I74)/13),0) -> 0 | J75: =IF(J31,(SUM(B74:J74)/13),0) -> 0.076923077 | K75: =IF(K31,(SUM(B74:K74)/13),0) -> 0.15384615 | L75: =IF(L31,(SUM(B74:L74)/13),0) -> 0.30769231 | M75: =IF(M31,(SUM(B74:M74)/13),0) -> 0.38461538 | N75: =IF(N31,(SUM(B74:N74)/13),0) -> 0.38461538 | O75: =IF(O31,(SUM(C74:O74)/13),0) -> 0.38461538 | P75: =IF(P31,(SUM(D74:P74)/13),0) -> 0.69230769 | Q75: =IF(Q31,(SUM(E74:Q74)/13),0) -> 0.69230769 | R75: =IF(R31,(SUM(F74:R74)/13),0) -> 0.84615385 | S75: =IF(S31,(SUM(G74:S74)/13),0) -> 0.84615385 | T75: =IF(T31,(SUM(H74:T74)/13),0) -> 0.92307692 | U75: =IF(U31,(SUM(I74:U74)/13),0) -> 1.0769231 | ... AN75: =IF(AN31,(SUM(AB74:AN74)/13),0) -> #N/A
A77: Engineering Staff Accident
A79: Burn/Scald
A80: MAA
A81: Contact
A82: MAA
A83: Door trap
A84: MAA
A85: Other Accident
A86: MAA
A87: STF on Tram
A88: MAA
A89: STF Other
... A96: Movement Accidents
B97: 2301 | C97: 2302 | D97: 2303 | E97: 2304 | F97: 2305 | G97: 2306 | H97: 2307 | I97: 2308 | J97: 2309 | K97: 2310 | L97: 2311 | M97: 2312 | N97: 2313 | O97: 2401 | P97: 2402 | Q97: 2403 | R97: 2404 | S97: 2405 | T97: 2406 | U97: 2407 | V97: 2408 | W97: 2409 | X97: 2410 | Y97: 2411 | Z97: 2412 | AA97: 2413 | AB97: 2501 | AC97: 2502 | AD97: 2503 | AE97: 2504 | AF97: 2505 | AG97: 2506 | AH97: 2507 | AI97: 2508 | AJ97: 2509 | AK97: 2510 | AL97: 2511 | AM97: 2512 | AN97: 2513
A98: Burn/Scald | B98: {=SUM((B$97='Accident & Incident Detail'!$C$2:$C$3433)*(Data!$A$98='Accident & Incident Detail'!$E$2:$E$3433)*("Movement"='Accident & Incident Detail'!$I$2:$I$3433))} -> 0 | C98: {=SUM((C$97='Accident & Incident Detail'!$C$2:$C$3433)*(Data!$A$98='Accident & Incident Detail'!$E$2:$E$3433)*("Movement"='Accident & Incident Detail'!$I$2:$I$3433))} -> 0 | D98: {=SUM((D$97='Accident & Incident Detail'!$C$2:$C$3433)*(Data!$A$98='Accident & Incident Detail'!$E$2:$E$3433)*("Movement"='Accident & Incident Detail'!$I$2:$I$3433))} -> 0 | E98: {=SUM((E$97='Accident & Incident Detail'!$C$2:$C$3433)*(Data!$A$98='Accident & Incident Detail'!$E$2:$E$3433)*("Movement"='Accident & Incident Detail'!$I$2:$I$3433))} -> 0 | F98: {=SUM((F$97='Accident & Incident Detail'!$C$2:$C$3433)*(Data!$A$98='Accident & Incident Detail'!$E$2:$E$3433)*("Movement"='Accident & Incident Detail'!$I$2:$I$3433))} -> 0 | G98: {=SUM((G$97='Accident & Incident Detail'!$C$2:$C$3433)*(Data!$A$98='Accident & Incident Detail'!$E$2:$E$3433)*("Movement"='Accident & Incident Detail'!$I$2:$I$3433))} -> 0 | H98: {=SUM((H$97='Accident & Incident Detail'!$C$2:$C$3433)*(Data!$A$98='Accident & Incident Detail'!$E$2:$E$3433)*("Movement"='Accident & Incident Detail'!$I$2:$I$3433))} -> 0 | I98: {=SUM((I$97='Accident & Incident Detail'!$C$2:$C$3433)*(Data!$A$98='Accident & Incident Detail'!$E$2:$E$3433)*("Movement"='Accident & Incident Detail'!$I$2:$I$3433))} -> 0 | ... AN98: {=SUM((AN$97='Accident & Incident Detail'!$C$2:$C$3433)*(Data!$A$98='Accident & Incident Detail'!$E$2:$E$3433)*("Movement"='Accident & Incident Detail'!$I$2:$I$3433))} -> 0
A99: MAA | B99: =IF(B$1=1,(SUM(B98:B98)/13),0) -> 0 | C99: =IF(C$1=1,(SUM(B98:C98)/13),0) -> 0 | D99: =IF(D$1=1,(SUM(B98:D98)/13),0) -> 0 | E99: =IF(E$1=1,(SUM(B98:E98)/13),0) -> 0 | F99: =IF(F$1=1,(SUM(B98:F98)/13),0) -> 0 | G99: =IF(G$1=1,(SUM(B98:G98)/13),0) -> 0 | H99: =IF(H$1=1,(SUM(B98:H98)/13),0) -> 0 | I99: =IF(I$1=1,(SUM(B98:I98)/13),0) -> 0 | J99: =IF(J$1=1,(SUM(B98:J98)/13),0) -> 0 | K99: =IF(K$1=1,(SUM(B98:K98)/13),0) -> 0 | L99: =IF(L$1=1,(SUM(B98:L98)/13),0) -> 0 | M99: =IF(M$1=1,(SUM(B98:M98)/13),0) -> 0 | N99: =IF(N$1=1,(SUM(B98:N98)/13),0) -> 0 | O99: =IF(O$1=1,(SUM(C98:O98)/13),0) -> 0 | P99: =IF(P$1=1,(SUM(D98:P98)/13),0) -> 0 | Q99: =IF(Q$1=1,(SUM(E98:Q98)/13),0) -> 0 | R99: =IF(R$1=1,(SUM(F98:R98)/13),0) -> 0 | S99: =IF(S$1=1,(SUM(G98:S98)/13),0) -> 0 | T99: =IF(T$1=1,(SUM(H98:T98)/13),0) -> 0 | U99: =IF(U$1=1,(SUM(I98:U98)/13),0) -> 0 | ... AN99: =IF(AN$1=1,(SUM(AB98:AN98)/13),0) -> 0
A100: Contact | B100: {=SUM((B$97='Accident & Incident Detail'!$C$2:$C$3433)*(Data!$A$100='Accident & Incident Detail'!$E$2:$E$3433)*("Movement"='Accident & Incident Detail'!$I$2:$I$3433))} -> 0 | C100: {=SUM((C$97='Accident & Incident Detail'!$C$2:$C$3433)*(Data!$A$100='Accident & Incident Detail'!$E$2:$E$3433)*("Movement"='Accident & Incident Detail'!$I$2:$I$3433))} -> 0 | D100: {=SUM((D$97='Accident & Incident Detail'!$C$2:$C$3433)*(Data!$A$100='Accident & Incident Detail'!$E$2:$E$3433)*("Movement"='Accident & Incident Detail'!$I$2:$I$3433))} -> 0 | E100: {=SUM((E$97='Accident & Incident Detail'!$C$2:$C$3433)*(Data!$A$100='Accident & Incident Detail'!$E$2:$E$3433)*("Movement"='Accident & Incident Detail'!$I$2:$I$3433))} -> 0 | F100: {=SUM((F$97='Accident & Incident Detail'!$C$2:$C$3433)*(Data!$A$100='Accident & Incident Detail'!$E$2:$E$3433)*("Movement"='Accident & Incident Detail'!$I$2:$I$3433))} -> 0 | G100: {=SUM((G$97='Accident & Incident Detail'!$C$2:$C$3433)*(Data!$A$100='Accident & Incident Detail'!$E$2:$E$3433)*("Movement"='Accident & Incident Detail'!$I$2:$I$3433))} -> 0 | H100: {=SUM((H$97='Accident & Incident Detail'!$C$2:$C$3433)*(Data!$A$100='Accident & Incident Detail'!$E$2:$E$3433)*("Movement"='Accident & Incident Detail'!$I$2:$I$3433))} -> 0 | I100: {=SUM((I$97='Accident & Incident Detail'!$C$2:$C$3433)*(Data!$A$100='Accident & Incident Detail'!$E$2:$E$3433)*("Movement"='Accident & Incident Detail'!$I$2:$I$3433))} -> 0 | ... AN100: {=SUM((AN$97='Accident & Incident Detail'!$C$2:$C$3433)*(Data!$A$100='Accident & Incident Detail'!$E$2:$E$3433)*("Movement"='Accident & Incident Detail'!$I$2:$I$3433))} -> 0
A101: MAA | B101: =IF(B$1=1,(SUM(B100:B100)/13),0) -> 0 | C101: =IF(C$1=1,(SUM(B100:C100)/13),0) -> 0 | D101: =IF(D$1=1,(SUM(B100:D100)/13),0) -> 0 | E101: =IF(E$1=1,(SUM(B100:E100)/13),0) -> 0 | F101: =IF(F$1=1,(SUM(B100:F100)/13),0) -> 0 | G101: =IF(G$1=1,(SUM(B100:G100)/13),0) -> 0 | H101: =IF(H$1=1,(SUM(B100:H100)/13),0) -> 0 | I101: =IF(I$1=1,(SUM(B100:I100)/13),0) -> 0 | J101: =IF(J$1=1,(SUM(B100:J100)/13),0) -> 0 | K101: =IF(K$1=1,(SUM(B100:K100)/13),0) -> 0 | L101: =IF(L$1=1,(SUM(B100:L100)/13),0) -> 0 | M101: =IF(M$1=1,(SUM(B100:M100)/13),0) -> 0 | N101: =IF(N$1=1,(SUM(B100:N100)/13),0) -> 0 | O101: =IF(O$1=1,(SUM(C100:O100)/13),0) -> 0 | P101: =IF(P$1=1,(SUM(D100:P100)/13),0) -> 0 | Q101: =IF(Q$1=1,(SUM(E100:Q100)/13),0) -> 0 | R101: =IF(R$1=1,(SUM(F100:R100)/13),0) -> 0 | S101: =IF(S$1=1,(SUM(G100:S100)/13),0) -> 0 | T101: =IF(T$1=1,(SUM(H100:T100)/13),0) -> 0 | U101: =IF(U$1=1,(SUM(I100:U100)/13),0) -> 0 | ... AN101: =IF(AN$1=1,(SUM(AB100:AN100)/13),0) -> 0
A102: Door trap | B102: {=SUM((B$97='Accident & Incident Detail'!$C$2:$C$3433)*(Data!$A$102='Accident & Incident Detail'!$E$2:$E$3433)*("Movement"='Accident & Incident Detail'!$I$2:$I$3433))} -> 0 | C102: {=SUM((C$97='Accident & Incident Detail'!$C$2:$C$3433)*(Data!$A$102='Accident & Incident Detail'!$E$2:$E$3433)*("Movement"='Accident & Incident Detail'!$I$2:$I$3433))} -> 0 | D102: {=SUM((D$97='Accident & Incident Detail'!$C$2:$C$3433)*(Data!$A$102='Accident & Incident Detail'!$E$2:$E$3433)*("Movement"='Accident & Incident Detail'!$I$2:$I$3433))} -> 0 | E102: {=SUM((E$97='Accident & Incident Detail'!$C$2:$C$3433)*(Data!$A$102='Accident & Incident Detail'!$E$2:$E$3433)*("Movement"='Accident & Incident Detail'!$I$2:$I$3433))} -> 0 | F102: {=SUM((F$97='Accident & Incident Detail'!$C$2:$C$3433)*(Data!$A$102='Accident & Incident Detail'!$E$2:$E$3433)*("Movement"='Accident & Incident Detail'!$I$2:$I$3433))} -> 0 | G102: {=SUM((G$97='Accident & Incident Detail'!$C$2:$C$3433)*(Data!$A$102='Accident & Incident Detail'!$E$2:$E$3433)*("Movement"='Accident & Incident Detail'!$I$2:$I$3433))} -> 0 | H102: {=SUM((H$97='Accident & Incident Detail'!$C$2:$C$3433)*(Data!$A$102='Accident & Incident Detail'!$E$2:$E$3433)*("Movement"='Accident & Incident Detail'!$I$2:$I$3433))} -> 0 | I102: {=SUM((I$97='Accident & Incident Detail'!$C$2:$C$3433)*(Data!$A$102='Accident & Incident Detail'!$E$2:$E$3433)*("Movement"='Accident & Incident Detail'!$I$2:$I$3433))} -> 0 | ... AN102: {=SUM((AN$97='Accident & Incident Detail'!$C$2:$C$3433)*(Data!$A$102='Accident & Incident Detail'!$E$2:$E$3433)*("Movement"='Accident & Incident Detail'!$I$2:$I$3433))} -> 0
A103: MAA | B103: =IF(B$1=1,(SUM(B102:B102)/13),0) -> 0 | C103: =IF(C$1=1,(SUM(B102:C102)/13),0) -> 0 | D103: =IF(D$1=1,(SUM(B102:D102)/13),0) -> 0 | E103: =IF(E$1=1,(SUM(B102:E102)/13),0) -> 0 | F103: =IF(F$1=1,(SUM(B102:F102)/13),0) -> 0 | G103: =IF(G$1=1,(SUM(B102:G102)/13),0) -> 0 | H103: =IF(H$1=1,(SUM(B102:H102)/13),0) -> 0 | I103: =IF(I$1=1,(SUM(B102:I102)/13),0) -> 0 | J103: =IF(J$1=1,(SUM(B102:J102)/13),0) -> 0 | K103: =IF(K$1=1,(SUM(B102:K102)/13),0) -> 0 | L103: =IF(L$1=1,(SUM(B102:L102)/13),0) -> 0 | M103: =IF(M$1=1,(SUM(B102:M102)/13),0) -> 0 | N103: =IF(N$1=1,(SUM(B102:N102)/13),0) -> 0 | O103: =IF(O$1=1,(SUM(C102:O102)/13),0) -> 0.076923077 | P103: =IF(P$1=1,(SUM(D102:P102)/13),0) -> 0.15384615 | Q103: =IF(Q$1=1,(SUM(E102:Q102)/13),0) -> 0.30769231 | R103: =IF(R$1=1,(SUM(F102:R102)/13),0) -> 0.46153846 | S103: =IF(S$1=1,(SUM(G102:S102)/13),0) -> 0.53846154 | T103: =IF(T$1=1,(SUM(H102:T102)/13),0) -> 0.69230769 | U103: =IF(U$1=1,(SUM(I102:U102)/13),0) -> 0.69230769 | ... AN103: =IF(AN$1=1,(SUM(AB102:AN102)/13),0) -> 0
A104: Other Accident | B104: {=SUM((B$97='Accident & Incident Detail'!$C$2:$C$3433)*(Data!$A$104='Accident & Incident Detail'!$E$2:$E$3433)*("Movement"='Accident & Incident Detail'!$I$2:$I$3433))} -> 0 | C104: {=SUM((C$97='Accident & Incident Detail'!$C$2:$C$3433)*(Data!$A$104='Accident & Incident Detail'!$E$2:$E$3433)*("Movement"='Accident & Incident Detail'!$I$2:$I$3433))} -> 0 | D104: {=SUM((D$97='Accident & Incident Detail'!$C$2:$C$3433)*(Data!$A$104='Accident & Incident Detail'!$E$2:$E$3433)*("Movement"='Accident & Incident Detail'!$I$2:$I$3433))} -> 0 | E104: {=SUM((E$97='Accident & Incident Detail'!$C$2:$C$3433)*(Data!$A$104='Accident & Incident Detail'!$E$2:$E$3433)*("Movement"='Accident & Incident Detail'!$I$2:$I$3433))} -> 0 | F104: {=SUM((F$97='Accident & Incident Detail'!$C$2:$C$3433)*(Data!$A$104='Accident & Incident Detail'!$E$2:$E$3433)*("Movement"='Accident & Incident Detail'!$I$2:$I$3433))} -> 0 | G104: {=SUM((G$97='Accident & Incident Detail'!$C$2:$C$3433)*(Data!$A$104='Accident & Incident Detail'!$E$2:$E$3433)*("Movement"='Accident & Incident Detail'!$I$2:$I$3433))} -> 0 | H104: {=SUM((H$97='Accident & Incident Detail'!$C$2:$C$3433)*(Data!$A$104='Accident & Incident Detail'!$E$2:$E$3433)*("Movement"='Accident & Incident Detail'!$I$2:$I$3433))} -> 0 | I104: {=SUM((I$97='Accident & Incident Detail'!$C$2:$C$3433)*(Data!$A$104='Accident & Incident Detail'!$E$2:$E$3433)*("Movement"='Accident & Incident Detail'!$I$2:$I$3433))} -> 0 | ... AN104: {=SUM((AN$97='Accident & Incident Detail'!$C$2:$C$3433)*(Data!$A$104='Accident & Incident Detail'!$E$2:$E$3433)*("Movement"='Accident & Incident Detail'!$I$2:$I$3433))} -> 0
A105: MAA | B105: =IF(B$1=1,(SUM(B104:B104)/13),0) -> 0 | C105: =IF(C$1=1,(SUM(B104:C104)/13),0) -> 0 | D105: =IF(D$1=1,(SUM(B104:D104)/13),0) -> 0 | E105: =IF(E$1=1,(SUM(B104:E104)/13),0) -> 0 | F105: =IF(F$1=1,(SUM(B104:F104)/13),0) -> 0 | G105: =IF(G$1=1,(SUM(B104:G104)/13),0) -> 0 | H105: =IF(H$1=1,(SUM(B104:H104)/13),0) -> 0 | I105: =IF(I$1=1,(SUM(B104:I104)/13),0) -> 0 | J105: =IF(J$1=1,(SUM(B104:J104)/13),0) -> 0 | K105: =IF(K$1=1,(SUM(B104:K104)/13),0) -> 0 | L105: =IF(L$1=1,(SUM(B104:L104)/13),0) -> 0 | M105: =IF(M$1=1,(SUM(B104:M104)/13),0) -> 0 | N105: =IF(N$1=1,(SUM(B104:N104)/13),0) -> 0 | O105: =IF(O$1=1,(SUM(C104:O104)/13),0) -> 0 | P105: =IF(P$1=1,(SUM(D104:P104)/13),0) -> 0 | Q105: =IF(Q$1=1,(SUM(E104:Q104)/13),0) -> 0 | R105: =IF(R$1=1,(SUM(F104:R104)/13),0) -> 0 | S105: =IF(S$1=1,(SUM(G104:S104)/13),0) -> 0 | T105: =IF(T$1=1,(SUM(H104:T104)/13),0) -> 0 | U105: =IF(U$1=1,(SUM(I104:U104)/13),0) -> 0 | ... AN105: =IF(AN$1=1,(SUM(AB104:AN104)/13),0) -> 0
A106: STF on Tram | B106: {=SUM((B$97='Accident & Incident Detail'!$C$2:$C$3433)*(Data!$A$106='Accident & Incident Detail'!$E$2:$E$3433)*("Movement"='Accident & Incident Detail'!$I$2:$I$3433))} -> 0 | C106: {=SUM((C$97='Accident & Incident Detail'!$C$2:$C$3433)*(Data!$A$106='Accident & Incident Detail'!$E$2:$E$3433)*("Movement"='Accident & Incident Detail'!$I$2:$I$3433))} -> 0 | D106: {=SUM((D$97='Accident & Incident Detail'!$C$2:$C$3433)*(Data!$A$106='Accident & Incident Detail'!$E$2:$E$3433)*("Movement"='Accident & Incident Detail'!$I$2:$I$3433))} -> 0 | E106: {=SUM((E$97='Accident & Incident Detail'!$C$2:$C$3433)*(Data!$A$106='Accident & Incident Detail'!$E$2:$E$3433)*("Movement"='Accident & Incident Detail'!$I$2:$I$3433))} -> 0 | F106: {=SUM((F$97='Accident & Incident Detail'!$C$2:$C$3433)*(Data!$A$106='Accident & Incident Detail'!$E$2:$E$3433)*("Movement"='Accident & Incident Detail'!$I$2:$I$3433))} -> 0 | G106: {=SUM((G$97='Accident & Incident Detail'!$C$2:$C$3433)*(Data!$A$106='Accident & Incident Detail'!$E$2:$E$3433)*("Movement"='Accident & Incident Detail'!$I$2:$I$3433))} -> 0 | H106: {=SUM((H$97='Accident & Incident Detail'!$C$2:$C$3433)*(Data!$A$106='Accident & Incident Detail'!$E$2:$E$3433)*("Movement"='Accident & Incident Detail'!$I$2:$I$3433))} -> 0 | I106: {=SUM((I$97='Accident & Incident Detail'!$C$2:$C$3433)*(Data!$A$106='Accident & Incident Detail'!$E$2:$E$3433)*("Movement"='Accident & Incident Detail'!$I$2:$I$3433))} -> 0 | ... AN106: {=SUM((AN$97='Accident & Incident Detail'!$C$2:$C$3433)*(Data!$A$106='Accident & Incident Detail'!$E$2:$E$3433)*("Movement"='Accident & Incident Detail'!$I$2:$I$3433))} -> 0
A107: MAA | B107: =IF(B$1=1,(SUM(B106:B106)/13),0) -> 0 | C107: =IF(C$1=1,(SUM(B106:C106)/13),0) -> 0 | D107: =IF(D$1=1,(SUM(B106:D106)/13),0) -> 0 | E107: =IF(E$1=1,(SUM(B106:E106)/13),0) -> 0 | F107: =IF(F$1=1,(SUM(B106:F106)/13),0) -> 0 | G107: =IF(G$1=1,(SUM(B106:G106)/13),0) -> 0 | H107: =IF(H$1=1,(SUM(B106:H106)/13),0) -> 0 | I107: =IF(I$1=1,(SUM(B106:I106)/13),0) -> 0 | J107: =IF(J$1=1,(SUM(B106:J106)/13),0) -> 0.076923077 | K107: =IF(K$1=1,(SUM(B106:K106)/13),0) -> 0.30769231 | L107: =IF(L$1=1,(SUM(B106:L106)/13),0) -> 0.84615385 | M107: =IF(M$1=1,(SUM(B106:M106)/13),0) -> 1.3846154 | N107: =IF(N$1=1,(SUM(B106:N106)/13),0) -> 1.3846154 | O107: =IF(O$1=1,(SUM(C106:O106)/13),0) -> 2 | P107: =IF(P$1=1,(SUM(D106:P106)/13),0) -> 2.3846154 | Q107: =IF(Q$1=1,(SUM(E106:Q106)/13),0) -> 2.9230769 | R107: =IF(R$1=1,(SUM(F106:R106)/13),0) -> 3.2307692 | S107: =IF(S$1=1,(SUM(G106:S106)/13),0) -> 3.3846154 | T107: =IF(T$1=1,(SUM(H106:T106)/13),0) -> 3.7692308 | U107: =IF(U$1=1,(SUM(I106:U106)/13),0) -> 4.2307692 | ... AN107: =IF(AN$1=1,(SUM(AB106:AN106)/13),0) -> 0
A108: STF Other | B108: {=SUM((B$97='Accident & Incident Detail'!$C$2:$C$3433)*(Data!$A$108='Accident & Incident Detail'!$E$2:$E$3433)*("Movement"='Accident & Incident Detail'!$I$2:$I$3433))} -> 0 | C108: {=SUM((C$97='Accident & Incident Detail'!$C$2:$C$3433)*(Data!$A$108='Accident & Incident Detail'!$E$2:$E$3433)*("Movement"='Accident & Incident Detail'!$I$2:$I$3433))} -> 0 | D108: {=SUM((D$97='Accident & Incident Detail'!$C$2:$C$3433)*(Data!$A$108='Accident & Incident Detail'!$E$2:$E$3433)*("Movement"='Accident & Incident Detail'!$I$2:$I$3433))} -> 0 | E108: {=SUM((E$97='Accident & Incident Detail'!$C$2:$C$3433)*(Data!$A$108='Accident & Incident Detail'!$E$2:$E$3433)*("Movement"='Accident & Incident Detail'!$I$2:$I$3433))} -> 0 | F108: {=SUM((F$97='Accident & Incident Detail'!$C$2:$C$3433)*(Data!$A$108='Accident & Incident Detail'!$E$2:$E$3433)*("Movement"='Accident & Incident Detail'!$I$2:$I$3433))} -> 0 | G108: {=SUM((G$97='Accident & Incident Detail'!$C$2:$C$3433)*(Data!$A$108='Accident & Incident Detail'!$E$2:$E$3433)*("Movement"='Accident & Incident Detail'!$I$2:$I$3433))} -> 0 | H108: {=SUM((H$97='Accident & Incident Detail'!$C$2:$C$3433)*(Data!$A$108='Accident & Incident Detail'!$E$2:$E$3433)*("Movement"='Accident & Incident Detail'!$I$2:$I$3433))} -> 0 | I108: {=SUM((I$97='Accident & Incident Detail'!$C$2:$C$3433)*(Data!$A$108='Accident & Incident Detail'!$E$2:$E$3433)*("Movement"='Accident & Incident Detail'!$I$2:$I$3433))} -> 0 | ... AN108: {=SUM((AN$97='Accident & Incident Detail'!$C$2:$C$3433)*(Data!$A$108='Accident & Incident Detail'!$E$2:$E$3433)*("Movement"='Accident & Incident Detail'!$I$2:$I$3433))} -> 0
A109: MAA | B109: =IF(B$1=1,(SUM(B108:B108)/13),0) -> 0 | C109: =IF(C$1=1,(SUM(B108:C108)/13),0) -> 0 | D109: =IF(D$1=1,(SUM(B108:D108)/13),0) -> 0 | E109: =IF(E$1=1,(SUM(B108:E108)/13),0) -> 0 | F109: =IF(F$1=1,(SUM(B108:F108)/13),0) -> 0 | G109: =IF(G$1=1,(SUM(B108:G108)/13),0) -> 0 | H109: =IF(H$1=1,(SUM(B108:H108)/13),0) -> 0 | I109: =IF(I$1=1,(SUM(B108:I108)/13),0) -> 0 | J109: =IF(J$1=1,(SUM(B108:J108)/13),0) -> 0 | K109: =IF(K$1=1,(SUM(B108:K108)/13),0) -> 0 | L109: =IF(L$1=1,(SUM(B108:L108)/13),0) -> 0 | M109: =IF(M$1=1,(SUM(B108:M108)/13),0) -> 0 | N109: =IF(N$1=1,(SUM(B108:N108)/13),0) -> 0 | O109: =IF(O$1=1,(SUM(C108:O108)/13),0) -> 0 | P109: =IF(P$1=1,(SUM(D108:P108)/13),0) -> 0 | Q109: =IF(Q$1=1,(SUM(E108:Q108)/13),0) -> 0 | R109: =IF(R$1=1,(SUM(F108:R108)/13),0) -> 0 | S109: =IF(S$1=1,(SUM(G108:S108)/13),0) -> 0 | T109: =IF(T$1=1,(SUM(H108:T108)/13),0) -> 0 | U109: =IF(U$1=1,(SUM(I108:U108)/13),0) -> 0 | ... AN109: =IF(AN$1=1,(SUM(AB108:AN108)/13),0) -> 0
A110: Mobility | B110: {=SUM((B$97='Accident & Incident Detail'!$C$2:$C$3433)*(Data!$A$110='Accident & Incident Detail'!$E$2:$E$3433)*("Movement"='Accident & Incident Detail'!$I$2:$I$3433))} -> 0 | C110: {=SUM((C$97='Accident & Incident Detail'!$C$2:$C$3433)*(Data!$A$110='Accident & Incident Detail'!$E$2:$E$3433)*("Movement"='Accident & Incident Detail'!$I$2:$I$3433))} -> 0 | D110: {=SUM((D$97='Accident & Incident Detail'!$C$2:$C$3433)*(Data!$A$110='Accident & Incident Detail'!$E$2:$E$3433)*("Movement"='Accident & Incident Detail'!$I$2:$I$3433))} -> 0 | E110: {=SUM((E$97='Accident & Incident Detail'!$C$2:$C$3433)*(Data!$A$110='Accident & Incident Detail'!$E$2:$E$3433)*("Movement"='Accident & Incident Detail'!$I$2:$I$3433))} -> 0 | F110: {=SUM((F$97='Accident & Incident Detail'!$C$2:$C$3433)*(Data!$A$110='Accident & Incident Detail'!$E$2:$E$3433)*("Movement"='Accident & Incident Detail'!$I$2:$I$3433))} -> 0 | G110: {=SUM((G$97='Accident & Incident Detail'!$C$2:$C$3433)*(Data!$A$110='Accident & Incident Detail'!$E$2:$E$3433)*("Movement"='Accident & Incident Detail'!$I$2:$I$3433))} -> 0 | H110: {=SUM((H$97='Accident & Incident Detail'!$C$2:$C$3433)*(Data!$A$110='Accident & Incident Detail'!$E$2:$E$3433)*("Movement"='Accident & Incident Detail'!$I$2:$I$3433))} -> 0 | I110: {=SUM((I$97='Accident & Incident Detail'!$C$2:$C$3433)*(Data!$A$110='Accident & Incident Detail'!$E$2:$E$3433)*("Movement"='Accident & Incident Detail'!$I$2:$I$3433))} -> 0 | ... AN110: {=SUM((AN$97='Accident & Incident Detail'!$C$2:$C$3433)*(Data!$A$110='Accident & Incident Detail'!$E$2:$E$3433)*("Movement"='Accident & Incident Detail'!$I$2:$I$3433))} -> 0
A111: MAA | B111: =IF(B$1=1,(SUM(B110:B110)/13),0) -> 0 | C111: =IF(C$1=1,(SUM(B110:C110)/13),0) -> 0 | D111: =IF(D$1=1,(SUM(B110:D110)/13),0) -> 0 | E111: =IF(E$1=1,(SUM(B110:E110)/13),0) -> 0 | F111: =IF(F$1=1,(SUM(B110:F110)/13),0) -> 0 | G111: =IF(G$1=1,(SUM(B110:G110)/13),0) -> 0 | H111: =IF(H$1=1,(SUM(B110:H110)/13),0) -> 0 | I111: =IF(I$1=1,(SUM(B110:I110)/13),0) -> 0 | J111: =IF(J$1=1,(SUM(B110:J110)/13),0) -> 0 | K111: =IF(K$1=1,(SUM(B110:K110)/13),0) -> 0 | L111: =IF(L$1=1,(SUM(B110:L110)/13),0) -> 0 | M111: =IF(M$1=1,(SUM(B110:M110)/13),0) -> 0 | N111: =IF(N$1=1,(SUM(B110:N110)/13),0) -> 0 | O111: =IF(O$1=1,(SUM(C110:O110)/13),0) -> 0 | P111: =IF(P$1=1,(SUM(D110:P110)/13),0) -> 0 | Q111: =IF(Q$1=1,(SUM(E110:Q110)/13),0) -> 0 | R111: =IF(R$1=1,(SUM(F110:R110)/13),0) -> 0 | S111: =IF(S$1=1,(SUM(G110:S110)/13),0) -> 0 | T111: =IF(T$1=1,(SUM(H110:T110)/13),0) -> 0 | U111: =IF(U$1=1,(SUM(I110:U110)/13),0) -> 0 | ... AN111: =IF(AN$1=1,(SUM(AB110:AN110)/13),0) -> 0
A112: Tip Up seats | B112: {=SUM((B$97='Accident & Incident Detail'!$C$2:$C$3433)*(Data!$A$112='Accident & Incident Detail'!$E$2:$E$3433)*("Movement"='Accident & Incident Detail'!$I$2:$I$3433))} -> 0 | C112: {=SUM((C$97='Accident & Incident Detail'!$C$2:$C$3433)*(Data!$A$112='Accident & Incident Detail'!$E$2:$E$3433)*("Movement"='Accident & Incident Detail'!$I$2:$I$3433))} -> 0 | D112: {=SUM((D$97='Accident & Incident Detail'!$C$2:$C$3433)*(Data!$A$112='Accident & Incident Detail'!$E$2:$E$3433)*("Movement"='Accident & Incident Detail'!$I$2:$I$3433))} -> 0 | E112: {=SUM((E$97='Accident & Incident Detail'!$C$2:$C$3433)*(Data!$A$112='Accident & Incident Detail'!$E$2:$E$3433)*("Movement"='Accident & Incident Detail'!$I$2:$I$3433))} -> 0 | F112: {=SUM((F$97='Accident & Incident Detail'!$C$2:$C$3433)*(Data!$A$112='Accident & Incident Detail'!$E$2:$E$3433)*("Movement"='Accident & Incident Detail'!$I$2:$I$3433))} -> 0 | G112: {=SUM((G$97='Accident & Incident Detail'!$C$2:$C$3433)*(Data!$A$112='Accident & Incident Detail'!$E$2:$E$3433)*("Movement"='Accident & Incident Detail'!$I$2:$I$3433))} -> 0 | H112: {=SUM((H$97='Accident & Incident Detail'!$C$2:$C$3433)*(Data!$A$112='Accident & Incident Detail'!$E$2:$E$3433)*("Movement"='Accident & Incident Detail'!$I$2:$I$3433))} -> 0 | I112: {=SUM((I$97='Accident & Incident Detail'!$C$2:$C$3433)*(Data!$A$112='Accident & Incident Detail'!$E$2:$E$3433)*("Movement"='Accident & Incident Detail'!$I$2:$I$3433))} -> 0 | ... AN112: {=SUM((AN$97='Accident & Incident Detail'!$C$2:$C$3433)*(Data!$A$112='Accident & Incident Detail'!$E$2:$E$3433)*("Movement"='Accident & Incident Detail'!$I$2:$I$3433))} -> 0
...

Sheet Lookup Sheets
A1: Status | B1: Date | C1: Reporting Period | D1: Accident/ Incident Reference | E1: Accident/Incident Type | F1: Location | G1: Tram | H1: Catergory | I1: Person Type | J1: Description of incident | K1: Total Number of days Lost | L1: RIDDOR | M1: Initial Report Recived? | N1: Type of investigation carried out | O1: Investigating Manager | P1: Investigation Due | Q1: Investigation Completion date | R1: Immediate Cause | S1: Underlying Cause | T1: Recommendations Made? | U1: Comments | W1: Claim received? | X1: Investigation type
C2: 1613 | E2: Cab Indicators | G2: 106 | H2: Non-Movement | I2: n/a | O2: Alan Barclay | X2: Accident
C3: 1701 | E3: Air Conditioning | G3: 101 | H3: Staff Accident | I3: Staff | O3: Andy Roberts | X3: Assault
C4: 1702 | E4: AVL | G4: 103 | H4: INFO ONLY | I4: Public | O4: Dave Bridges | X4: Info only/SAFE
C5: 1703 | E5: Brake | G5: 104 | H5: Infrastructure | I5: Cyclist | O5: Dave Hallam | X5: Level 1
C6: 1704 | E6: Anti - social behaviour | G6: 102 | H6: Assaults | I6: Passenger | O6: Dave Marrison | X6: Level 2
C7: 1705 | E7: Burn/Scald | G7: 105 | H7: Movement | I7: Taxis | O7: David Tingle | X7: None
C8: 1706 | E8: Contact | G8: 107 | H8: Operational | I8: Eldery | O8: Emma Cooper | X8: SRD
C9: 1707 | E9: Control | G9: 108 | H9: Siemens SRD | I9: Vunrable | O9: Gary Seaborn | X9: Safety Digest
C10: 1708 | E10: Cyclist Fall | G10: 109 | I10: Third Party | O10: Glin Stanford
C11: 1709 | E11: Derailment | G11: 110 | H11: SRD | O11: Infra Dept
C12: 1710 | E12: Derailment -Multi-Car | G12: 111 | O12: IT Dept
C13: 1711 | E13: Door Open in Traffic | G13: 112 | O13: James Stewart
C14: 1712 | E14: Door Trap | G14: 113 | O14: John Cawthorn
C15: 1713 | E15: Doors | G15: 114 | O15: John Kolchuk
C16: 1801 | E16: Driver Seats | G16: 115 | O16: Josh Keeling
C17: 1802 | E17: Electricity Fire/Smoke | G17: 116 | O17: Mark Blackwell
C18: 1803 | E18: Fire | G18: 117 | O18: Neill Barraclough
C19: 1804 | E19: Headlights/Tail Lights | G19: 118 | O19: Nikolas Dobbs
C20: 1805 | E20: Heating | G20: 119 | O20: Nina Wybrant
C21: 1806 | E21: Horn/Bell | G21: 120 | O21: Rachel Bridges
C22: 1906 | E22: Physical Assault | O22: RSM Dept
C23: 1807 | E23: Incorrect VIS | G23: 121 | O23: Russ Wild
C24: 1808 | E24: Communication | G24: 122 | O24: Safety Reps
C25: 1809 | E25: Non-Tram RTC | G25: 123 | O25: Sean Cuckson
C26: 1810 | E26: Low Adhesion | G26: 124 | O26: Sharon Galloway
C27: 1907 | E27: Points | G27: 125 | O27: Andy Buckley
C28: 1811 | E28: Mirrors | G28: 201 | O28: Danielle Willey
C29: 1812 | E29: Mobility | G29: 202 | O29: Wayne Clay
E30: Near Miss - Red Light | G30: 203 | O30: James Gilbert
C31: 1813 | E31: Near Miss | G31: 204 | O31: Paul Holdsworth
C32: 1901 | E32: OHLE | G32: 205 | O32: Keith Sockett
C33: 1902 | E33: Other Accident | G33: 206 | O33: Alex Wray
C34: 1903 | E34: Other | G34: 207 | O34: Tom Harrison
C35: 1904 | E35: Pantagraph | G35: n/a
C36: 1905 | E36: Person in Cab
E37: Minor - PTC
C38: 1908 | E38: Major - PTC
C39: 1909 | E39: Radio & Communications Systems
C40: 1910 | E40: Minor - RTC
C41: 1911 | E41: Major - RTC
C42: 1912 | E42: Sanders
C43: 1913 | E43: SCADA
C44: 2001 | E44: Seperation
C45: 2002 | E45: Signal Passed against Bar (SPAS)
C46: 2003 | E46: Signals
C47: 2004 | E47: Slip/Slide
C48: 2005 | E48: Speedometer
C49: 2006 | E49: STF on Tram
... C68: 2112 | E68: Car on Ballast/Tracks
A69: Action/Recommendation Type | C69: 2113 | D69: Action Owner | E69: Speeding
A70: BOSRIA Action | C70: 2201 | D70: Andy Roberts, Duty Manager | E70: Passenger
A71: External Audit Corrective Action | C71: 2202 | D71: Dave Bridges, Network Co-ordinator | E71: Pasenger assault
A72: Safety Inspection Action | C72: 2203 | D72: Dave Hallam, Signalling & Control Manager | E72: Passenger on Passenger Assault
A73: Internal Audit Corrective Action | C73: 2204 | D73: Dave Marrison, OCC Manager | E73: Dog
A74: Level 1 Investigation Recommendation | C74: 2205 | D74: Jay Brooks, Stores Person | E74: Tresspass
A75: Level 2 Investigation Recommendation | C75: 2206 | D75: Emma Cooper, Duty Manager | E75: Infrastructure/ Equipment failure
A76: Quarterly Exec Safety Meeting Action | C76: 2207 | D76: Gary Seaborn RSM Production Manager | E76: Other
A77: Quarterly Safety Representatives Meeting Action | C77: 2208 | D77: Glin Stanford, Project Co-ordinator
A78: Safety Concern Action | C78: 2209 | D78: HR
A79: Safety Plan Action | C79: 2210 | D79: IT Dept
A80: SRD investigation Recommendation | C80: 2211 | D80: James Stewart, Head of Customer Services
A81: RAIB | C81: 2212 | D81: John Cawthorn Duty Manager
A82: Safety Plan Sub-Action | C82: 2213 | D82: Gareth Fairweather, OHL Supervsior
A83: Tram Train | C83: 2201 | D83: John Kolchuk Permanent Way Supervisor
A84: TWYM | C84: 2202 | D84: Alex Wray Surveying Technician
A85: CS | C85: 2203 | D85: Keith Swallow, Head of Finance & Commercial
A86: ENG | C86: 2204 | D86: Kelly Henley-Smith, Safety Co-ordinator
A87: FIN/COMM | C87: 2205 | D87: Josh Keeling, Safety Manager
A88: HR | C88: 2206 | D88: Andy Buckley, Safety Officer
A89: 0
A90: SAFE | C90: 2207 | D90: Wayne Clay - Head of SHEQ
A91: Winterisation Meeting | C91: 2208 | D91: Nikolas Dobbs Head of Engineering
A92: Risk Review | C92: 2209 | D92: Michelle Walch, Procurement Manager
A93: Engineering Safety Meeting | C93: 2210 | D93: Mark Blackwell Cleaning Manager
A94: Training Team meeting | C94: 2211 | D94: Neill Barraclough Deputy Head of Engineering
A95: Speed Checks | C95: 2212 | D95: Nigel Wragg Commercial Manager
A96: NMU Risk Assesment | C96: 2213 | D96: Nina Wybrant Duty Manager
A97: Monthly Walkarounds | C97: 2301 | D97: Rachel Bridges, Duty Manager
A98: Management Walkarounds | C98: 2302 | D98: Resource Coordinator
C99: 2303 | D99: George Lilley, Safety Representative
C100: 2304 | D100: RSM Dept
C101: 2305 | D101: Russ Wild, Duty Manager
C102: 2306 | D102: Sharon Galloway, Senior Customer Service Manager
C103: 2307 | D103: Andy Rathbone ,Training Standards & Competency Manager
C104: 2308 | D104: Third Party
C105: 2309 | D105: Sean English, Managing Director
C106: 2310 | D106: Training Department
C107: 2311 | D107: David Tingle - Duty Manager
C108: 2312 | D108: Josh Keeling, Safety Manager
C109: 2313 | D109: Alan Barclay - Duty Manager
C110: 2401 | D110: Heads of
... C118: 2409 | D118: Keith Sockett -Stanadrds & Competency Coordinator
C119: 2410
C120: 2411
C121: 2412
C122: 2413
C123: 2501
C124: 2502
C125: 2503
...

Sheet Summary
A1: Reporting Period | B1: 2510 | C1: Period | D1: 2510
A2: Last Period | B2: 2059
A4: Safety Performance Summary - Actual Vs Target | M4: Safety Actions | AB4: BOSRIA
B5: =B1 -> 2510 | C5: 2024/25 Period Target | D5: YTD Actual | E5: 2025/26 YTD Target | F5: 2024/2025
B6: Period Actual | F6: Target | M6: Safety Actions All | N6: 2411 | O6: 2412 | P6: 2413 | Q6: 2501 | R6: 2502 | S6: 2503 | T6: 2504 | U6: 2505 | V6: 2506 | W6: 2507 | X6: 2508 | Y6: 2509 | Z6: 2510 | AC6: 2411 | AD6: 2412 | AE6: 2413 | AF6: 2501 | AG6: 2502 | AH6: 2503 | AI6: 2504 | AJ6: 2505 | AK6: 2506 | AL6: 2507 | AM6: 2508 | AN6: 2509 | AO6: 2510
A7: Staff Accidents (Excluding LTA) | B7: =HLOOKUP(B1,Data!$AB$4:$AN$18,3) -> 1 | C7: =F7/13 -> 1.3846154 | D7: =Data!AO6 -> 22 | E7: 18 | F7: 18 | M7: Overdue | N7: =HLOOKUP(N6,Data!$O317:$AN$320,4) -> 0 | O7: =HLOOKUP(O6,Data!$O317:$AN$320,4) -> 0 | P7: =HLOOKUP(P6,Data!$O317:$AN$320,4) -> 0 | Q7: =HLOOKUP(Q6,Data!$O317:$AN$320,4) -> 1 | R7: =HLOOKUP(R6,Data!$O317:$AN$320,4) -> 1 | S7: =HLOOKUP(S6,Data!$O317:$AN$320,4) -> 0 | T7: =HLOOKUP(T6,Data!$O317:$AN$320,4) -> 2 | U7: =HLOOKUP(U6,Data!$O317:$AN$320,4) -> 0 | ... Z7: =HLOOKUP(Z6,Data!$O317:$AN$320,4) -> 3 | AB7: Overdue | AC7: =HLOOKUP(AC6,Data!$O$307:$AN$315,5) -> 0 | AD7: =HLOOKUP(AD6,Data!$O$307:$AN$315,5) -> 0 | AE7: =HLOOKUP(AE6,Data!$O$307:$AN$315,5) -> 0 | AF7: =HLOOKUP(AF6,Data!$O$307:$AN$315,5) -> 0 | AG7: =HLOOKUP(AG6,Data!$O$307:$AN$315,5) -> 1 | AH7: =HLOOKUP(AH6,Data!$O$307:$AN$315,5) -> 0 | AI7: =HLOOKUP(AI6,Data!$O$307:$AN$315,5) -> 1 | AJ7: =HLOOKUP(AJ6,Data!$O$307:$AN$315,5) -> 0 | ... AO7: =HLOOKUP(AO6,Data!$O$307:$AN$315,5) -> 3
A8: Staff Lost Time Accidents | B8: =HLOOKUP(B1,Data!$AB$4:$AN$18,4) -> 0 | C8: =F8/13 -> 0.30769231 | D8: =Data!AO7 -> 2 | E8: 5 | F8: 4 | M8: Open | N8: =HLOOKUP(N6,Data!$O$317:$AN$318,2) -> 1 | O8: =HLOOKUP(O6,Data!$O$317:$AN$318,2) -> 1 | P8: =HLOOKUP(P6,Data!$O$317:$AN$318,2) -> 0 | Q8: =HLOOKUP(Q6,Data!$O$317:$AN$318,2) -> 0 | R8: =HLOOKUP(R6,Data!$O$317:$AN$318,2) -> 0 | S8: =HLOOKUP(S6,Data!$O$317:$AN$318,2) -> 0 | T8: =HLOOKUP(T6,Data!$O$317:$AN$318,2) -> 0 | U8: =HLOOKUP(U6,Data!$O$317:$AN$318,2) -> 0 | ... Z8: =HLOOKUP(Z6,Data!$O$317:$AN$318,2) -> 1 | AB8: Open | AC8: =HLOOKUP(AC6,Data!$O$307:$AN$315,3) -> 0 | AD8: =HLOOKUP(AD6,Data!$O$307:$AN$315,3) -> 0 | AE8: =HLOOKUP(AE6,Data!$O$307:$AN$315,3) -> 0 | AF8: =HLOOKUP(AF6,Data!$O$307:$AN$315,3) -> 0 | AG8: =HLOOKUP(AG6,Data!$O$307:$AN$315,3) -> 0 | AH8: =HLOOKUP(AH6,Data!$O$307:$AN$315,3) -> 0 | AI8: =HLOOKUP(AI6,Data!$O$307:$AN$315,3) -> 0 | AJ8: =HLOOKUP(AJ6,Data!$O$307:$AN$315,3) -> 0 | ... AO8: =HLOOKUP(AO6,Data!$O$307:$AN$315,3) -> 0
A9: Assaults | B9: =HLOOKUP(B1,Data!$AB$4:$AN$18,5) -> 3 | C9: =F9/13 -> 3.4615385 | D9: =Data!AO8 -> 22 | E9: 37 | F9: 45 | M9: Closed | N9: =HLOOKUP(N6,Data!$O$317:$AN$319,3) -> 6 | O9: =HLOOKUP(O6,Data!$O$317:$AN$319,3) -> 14 | P9: =HLOOKUP(P6,Data!$O$317:$AN$319,3) -> 13 | Q9: =HLOOKUP(Q6,Data!$O$317:$AN$319,3) -> 7 | R9: =HLOOKUP(R6,Data!$O$317:$AN$319,3) -> 8 | S9: =HLOOKUP(S6,Data!$O$317:$AN$319,3) -> 4 | T9: =HLOOKUP(T6,Data!$O$317:$AN$319,3) -> 3 | U9: =HLOOKUP(U6,Data!$O$317:$AN$319,3) -> 2 | ... Z9: =HLOOKUP(Z6,Data!$O$317:$AN$319,3) -> 6 | AB9: Closed | AC9: =HLOOKUP(AC6,Data!$O$307:$AN$315,4) -> 0 | AD9: =HLOOKUP(AD6,Data!$O$307:$AN$315,4) -> 6 | AE9: =HLOOKUP(AE6,Data!$O$307:$AN$315,4) -> 2 | AF9: =HLOOKUP(AF6,Data!$O$307:$AN$315,4) -> 1 | AG9: =HLOOKUP(AG6,Data!$O$307:$AN$315,4) -> 0 | AH9: =HLOOKUP(AH6,Data!$O$307:$AN$315,4) -> 2 | AI9: =HLOOKUP(AI6,Data!$O$307:$AN$315,4) -> 0 | AJ9: =HLOOKUP(AJ6,Data!$O$307:$AN$315,4) -> 0 | ... AO9: =HLOOKUP(AO6,Data!$O$307:$AN$315,4) -> 6
A10: Movement | B10: =HLOOKUP(B1,Data!$AB$4:$AN$18,6) -> 3 | C10: =F10/13 -> 5.5384615 | D10: =Data!AO9 -> 46 | E10: 102 | F10: 72 | M10: Total | N10: =SUM(N7:N9) -> 7 | O10: =SUM(O7:O9) -> 15 | P10: =SUM(P7:P9) -> 13 | Q10: =SUM(Q7:Q9) -> 8 | R10: =SUM(R7:R9) -> 9 | S10: =SUM(S7:S9) -> 4 | T10: =SUM(T7:T9) -> 5 | U10: =SUM(U7:U9) -> 2 | ... Z10: =SUM(Z7:Z9) -> 10 | AB10: Total Anom | AC10: =HLOOKUP(AC6,Data!$O$307:$AN$315,8) -> 0 | AD10: =HLOOKUP(AD6,Data!$O$307:$AN$315,8) -> 6 | AE10: =HLOOKUP(AE6,Data!$O$307:$AN$315,8) -> 0 | AF10: =HLOOKUP(AF6,Data!$O$307:$AN$315,8) -> 0 | AG10: =HLOOKUP(AG6,Data!$O$307:$AN$315,8) -> 0 | AH10: =HLOOKUP(AH6,Data!$O$307:$AN$315,8) -> 0 | AI10: =HLOOKUP(AI6,Data!$O$307:$AN$315,8) -> 0 | AJ10: =HLOOKUP(AJ6,Data!$O$307:$AN$315,8) -> 0 | ... AO10: =HLOOKUP(AO6,Data!$O$307:$AN$315,8) -> 0
A11: Non-Movement | B11: =HLOOKUP(B1,Data!$AB$4:$AN$18,7) -> 0 | C11: =F11/13 -> 0.46153846 | D11: =Data!AO10 -> 1 | E11: 13 | F11: 6 | AB11: Total Name | AC11: =HLOOKUP(AC6,Data!$O$307:$AN$315,9) -> 0 | AD11: =HLOOKUP(AD6,Data!$O$307:$AN$315,9) -> 0 | AE11: =HLOOKUP(AE6,Data!$O$307:$AN$315,9) -> 0 | AF11: =HLOOKUP(AF6,Data!$O$307:$AN$315,9) -> 0 | AG11: =HLOOKUP(AG6,Data!$O$307:$AN$315,9) -> 0 | AH11: =HLOOKUP(AH6,Data!$O$307:$AN$315,9) -> 0 | AI11: =HLOOKUP(AI6,Data!$O$307:$AN$315,9) -> 0 | AJ11: =HLOOKUP(AJ6,Data!$O$307:$AN$315,9) -> 0 | ... AO11: =HLOOKUP(AO6,Data!$O$307:$AN$315,9) -> 0
A12: Total | B12: =HLOOKUP(B1,Data!$AB$4:$AN$18,8) -> 7 | C12: 18 | D12: =SUM(D7:D11) -> 93 | E12: =SUM(E7:E11) -> 175 | F12: =SUM(F7:F11) -> 145 | M12: Safety Action - Breakdown | AB12: Grand Total | AC12: =SUM(AC7:AC9) -> 0 | AD12: =SUM(AD7:AD9) -> 6 | AE12: =SUM(AE7:AE9) -> 2 | AF12: =SUM(AF7:AF9) -> 1 | AG12: =SUM(AG7:AG9) -> 1 | AH12: =SUM(AH7:AH9) -> 2 | AI12: =SUM(AI7:AI9) -> 1 | AJ12: =SUM(AJ7:AJ9) -> 0 | ... AO12: =SUM(AO7:AO9) -> 9
A13: Vandalism | B13: =HLOOKUP(B1,Data!$AB$4:$AN$18,9) -> 11 | C13: =F13/13 -> 8.8461538 | D13: =Data!AO12 -> 113 | E13: 106 | F13: 115 | M13: Action | S13: Overdue | U13: Open | W13: Closed | Y13: Total
A14: Low Risk Total | B14: =HLOOKUP(B1,Data!$AB$4:$AO$18,10) -> 5 | C14: =F14/13 -> 6.1538462 | D14: =Data!AO13 -> 66 | E14: 74 | F14: 80 | M14: BOSRIA Action | S14: =SUM(Data!$O$270:$AN$270) -> #N/A | U14: =SUM(Data!$O$270:$AN$270) -> #N/A | W14: =SUM(Data!$O$270:$AN$270) -> #N/A | Y14: =SUM(Data!$O$270:$AN$270) -> #N/A
A15: High Risk Total | B15: =HLOOKUP(B1,Data!$AB$4:$AO$18,11) -> 0 | C15: =F15/13 -> 0.53846154 | D15: =Data!AA14 -> 1 | E15: 6 | F15: 7 | M15: External Audit Corrective Action | S15: =SUM(Data!$O$273:$AN$273) -> 0 | U15: =SUM(Data!$O$273:$AN$273) -> 0 | W15: =SUM(Data!$O$273:$AN$273) -> 0 | Y15: =SUM(Data!$O$273:$AN$273) -> 0
A16: Near Miss Total | B16: 0 | C16: =F16/13 -> 2 | D16: =Data!AO218 -> 45 | E16: 24 | F16: 26 | M16: Safety Inspection Action | S16: =SUM(Data!$O$276:$AN$276) -> 0 | U16: =SUM(Data!$O$276:$AN$276) -> 0 | W16: =SUM(Data!$O$276:$AN$276) -> 0 | Y16: =SUM(Data!$O$276:$AN$276) -> 0
A17: BOSRIA Action | B17: 8 | C17: =F17/13 -> 7.0769231 | D17: =Data!AO309 -> 6 | E17: 85 | F17: 92 | M17: Internal Audit Corrective Action | S17: =SUM(Data!$O$279:$AN$279) -> 0 | U17: =SUM(Data!$O$279:$AN$279) -> 0 | W17: =SUM(Data!$O$279:$AN$279) -> 0 | Y17: =SUM(Data!$O$279:$AN$279) -> 0
A18: Monthly Walkarounds | B18: 0 | C18: =F18/13 -> 0.69230769 | D18: =Data!AO313 -> 0 | E18: 8 | F18: 9 | M18: Level 2 Investigation Recommendation | S18: =SUM(Data!$O$285:$AN$285) -> 0 | U18: =SUM(Data!$O$285:$AN$285) -> 0 | W18: =SUM(Data!$O$285:$AN$285) -> 0 | Y18: =SUM(Data!$O$285:$AN$285) -> 0
A19: Management Walkarounds | B19: 0 | C19: =F19/13 -> 0.30769231 | D19: =Data!AO339 -> #REF! | E19: 4 | F19: 4 | M19: Quarterly Exec Safety Meeting Action | S19: =SUM(Data!$O$288:$AN$288) -> 0 | U19: =SUM(Data!$O$288:$AN$288) -> 0 | W19: =SUM(Data!$O$288:$AN$288) -> 0 | Y19: =SUM(Data!$O$288:$AN$288) -> 0
D20: ` | M20: Quarterly Safety Representatives Meeting Action | S20: =SUM(Data!$O$291:$AN$291) -> 0 | U20: =SUM(Data!$O$291:$AN$291) -> 0 | W20: =SUM(Data!$O$291:$AN$291) -> 0 | Y20: =SUM(Data!$O$291:$AN$291) -> 0
M21: Safety Concern Action | S21: =SUM(Data!$O$294:$AN$294) -> #N/A | U21: =SUM(Data!$O$294:$AN$294) -> #N/A | W21: =SUM(Data!$O$294:$AN$294) -> #N/A | Y21: =SUM(Data!$O$294:$AN$294) -> #N/A
M22: Safety Plan Action | S22: =SUM(Data!$O$296:$AN$296) -> 0 | U22: =SUM(Data!$O$296:$AN$296) -> 0 | W22: =SUM(Data!$O$296:$AN$296) -> 0 | Y22: =SUM(Data!$O$296:$AN$296) -> 0
M23: RAIB | S23: =SUM(Data!$O$303:$Z$303) -> 0 | U23: =SUM(Data!$O$303:$Z$303) -> 0 | W23: =SUM(Data!$O$303:$Z$303) -> 0 | Y23: =SUM(Data!$O$303:$Z$303) -> 0
M24: Total | S24: =SUM(S14:T23) -> #N/A | U24: =SUM(U14:V23) -> #N/A | W24: =SUM(W14:X23) -> #N/A | Y24: =SUM(S24:X24) -> #N/A
M26: Safety Investigations
M28: Safety Investigations all | N28: 2411 | O28: 2412 | P28: 2413 | Q28: 2501 | R28: 2502 | S28: 2503 | T28: 2504 | U28: 2505 | V28: 2506 | W28: 2507 | X28: 2508 | Y28: 2509 | Z28: 2510
A29: RIDDOR | M29: Overdue | N29: =HLOOKUP(Summary!N28,Data!$O$323:$AN326,4) -> 0 | O29: =HLOOKUP(Summary!O28,Data!$O$323:$AN326,4) -> 0 | P29: =HLOOKUP(Summary!P28,Data!$O$323:$AN326,4) -> 0 | Q29: =HLOOKUP(Summary!Q28,Data!$O$323:$AN326,4) -> 0 | R29: =HLOOKUP(Summary!R28,Data!$O$323:$AN326,4) -> 0 | S29: =HLOOKUP(Summary!S28,Data!$O$323:$AN326,4) -> 0 | T29: =HLOOKUP(Summary!T28,Data!$O$323:$AN326,4) -> 4 | U29: =HLOOKUP(Summary!U28,Data!$O$323:$AN326,4) -> 6 | ... Z29: =HLOOKUP(Summary!Z28,Data!$O$323:$AN326,4) -> 8
A30: RIDDOR | M30: Open | N30: =HLOOKUP(Summary!N28,Data!$O$323:$AN324,2) -> 0 | O30: =HLOOKUP(Summary!O28,Data!$O$323:$AN324,2) -> 0 | P30: =HLOOKUP(Summary!P28,Data!$O$323:$AN324,2) -> 0 | Q30: =HLOOKUP(Summary!Q28,Data!$O$323:$AN324,2) -> 0 | R30: =HLOOKUP(Summary!R28,Data!$O$323:$AN324,2) -> 0 | S30: =HLOOKUP(Summary!S28,Data!$O$323:$AN324,2) -> 0 | T30: =HLOOKUP(Summary!T28,Data!$O$323:$AN324,2) -> 0 | U30: =HLOOKUP(Summary!U28,Data!$O$323:$AN324,2) -> 0 | ... Z30: =HLOOKUP(Summary!Z28,Data!$O$323:$AN324,2) -> 0
B31: Actual | C31: YTD | M31: Closed | N31: =HLOOKUP(Summary!N28,Data!$O$323:$AN325,3) -> 77 | O31: =HLOOKUP(Summary!O28,Data!$O$323:$AN325,3) -> 61 | P31: =HLOOKUP(Summary!P28,Data!$O$323:$AN325,3) -> 68 | Q31: =HLOOKUP(Summary!Q28,Data!$O$323:$AN325,3) -> 53 | R31: =HLOOKUP(Summary!R28,Data!$O$323:$AN325,3) -> 55 | S31: =HLOOKUP(Summary!S28,Data!$O$323:$AN325,3) -> 58 | T31: =HLOOKUP(Summary!T28,Data!$O$323:$AN325,3) -> 39 | U31: =HLOOKUP(Summary!U28,Data!$O$323:$AN325,3) -> 34 | ... Z31: =HLOOKUP(Summary!Z28,Data!$O$323:$AN325,3) -> 35
A32: RIDDOR | B32: =HLOOKUP(B1,Data!AB256:AN258,2) -> 3 | C32: =Data!AO257 -> 27 | M32: Total | N32: =SUM(N29:N31) -> 77 | O32: =SUM(O29:O31) -> 61 | P32: =SUM(P29:P31) -> 68 | Q32: =SUM(Q29:Q31) -> 53 | R32: =SUM(R29:R31) -> 55 | S32: =SUM(S29:S31) -> 58 | T32: =SUM(T29:T31) -> 43 | U32: =SUM(U29:U31) -> 40 | ... Z32: =SUM(Z29:Z31) -> 43
A35: Staff Accidents
A53: Staff Assaults
A70: Vandalism
A87: Surfing
A106: Movement Accidents
A124: Low Risk Operational Incidents
A150: High Risk Operational Incidents
A175: Near Miss
A192: Safety Performance Summary - Trends
B193: MAA - Current Period | C193: MAA - Last Period
A194: Staff Accidents (Excluding LTA) | B194: =HLOOKUP(Summary!B1,Data!$O$21:$AN$35,2) -> 1.7692308 | C194: 1.77
A195: Staff Lost Time Accidents | B195: =HLOOKUP(Summary!B1,Data!$O$21:$AN$35,3) -> 0.15384615 | C195: 0.08
A196: Assaults | B196: =HLOOKUP(Summary!B1,Data!$O$21:$AN$35,4) -> 1.6923077 | C196: 4.23
A197: Movement | B197: =HLOOKUP(Summary!B1,Data!$O$21:$AN$35,5) -> 3.6153846 | C197: 5.96
A198: Non-Movement | B198: =HLOOKUP(Summary!B1,Data!$O$21:$AN$35,7) -> 0.076923077 | C198: 0.54
A199: Total | B199: =HLOOKUP(Summary!B1,Data!$I$21:$AN$35,9) -> 7.3076923 | C199: =SUM(C194:C198) -> 12.58
A200: Vandalism | B200: =HLOOKUP(Summary!B1,Data!$O$21:$AN$35,10) -> 10.076923 | C200: 6.38
A201: Low Risk Total | B201: =HLOOKUP(Summary!B1,Data!$O$21:$AN$35,11) -> 6.3076923 | C201: 5.46
A202: High Risk Total | B202: =HLOOKUP(Summary!B1,Data!$B$21:$AN$35,12) -> 0.61538462 | C202: 1.23
A204: Non Movement Accidents
A224: Signal Passed at Bar
A244: RIDDOR

Sheet Safety Action Tracking
A2: ='Accident & Incident Detail'!A1 -> 46057
A3: Status | B3: Action/Recommendation Type | C3: Action/Rec Raised by (If BOSRIA Anom if unknown) | D3: Date Action Raised | E3: Period Action Raised | F3: Investigation Ref (if applicable) | G3: Incident Title | H3: Recommendation Number | I3: Action/Recommendation | J3: Dept | K3: Action Owner | L3: Function | M3: Action Completion Target Date | O3: Action Completed | P3: Letter sent | Q3: Comments | R3: Number of days taken to close | S3: DWPI Days | T3: Closed | U3: Open | V3: Overdue
A4: =IF(O4>1,"Closed",IF(N4=1,"Overdue",IF(N4=3,"","Open"))) -> Closed | B4: BOSRIA Action | C4: Anom | D4: 45292 | E4: 2402 | G4: =VLOOKUP(F4,'Accident & Incident Detail'!$D$3:$E$165,2,FALSE) -> #N/A | H4: 2023/2024-141 | I4: None of the loop signals work | J4: INFRA | K4: Dave Hallam, Signalling & Control Manager | L4: ENG | M4: =IF(D4="","",D4+28) -> 45320 | N4: =IF(D4="",3,IF(M4<$A$2,1,0)) -> 1 | O4: 45637 | Q4: Matter has been resolved and fire call point has been cleared
A5: =IF(O5>1,"Closed",IF(N5=1,"Overdue",IF(N5=3,"","Open"))) -> Closed | B5: Level 1 Investigation Recommendation | C5: Alan Barclay | D5: 45300 | E5: 2310 | F5: 2309-51 | G5: =VLOOKUP(F5,'Accident & Incident Detail'!$D$3:$E$165,2,FALSE) -> Near Miss | H5: 2023/2024-82 | I5: Although not at fault the driver is to be spoken to about observations being better | J5: CS | K5: Alan Barclay - Duty Manager | L5: CS | M5: =IF(D5="","",D5+28) -> 45328 | N5: =IF(D5="",3,IF(M5<$A$2,1,0)) -> 1 | O5: 45350
A6: =IF(O6>1,"Closed",IF(N6=1,"Overdue",IF(N6=3,"","Open"))) -> Closed | B6: BOSRIA Action | C6: Anom | D6: 45304 | E6: 2310 | G6: =VLOOKUP(F6,'Accident & Incident Detail'!$D$3:$E$165,2,FALSE) -> #N/A | H6: 2023/2024-08 | I6: Taxis are stopping in the inbound track to pick up passengers from the 2 clubs here. I feel we shouldn't have to deal with this extra hazard in what is an already challenging part of the system - More signage explaining the non-stop rules for car drivers, liaison with the major taxi companies, a system in which taxis and cars can be reported for offences such as stopping on the tracks, entering bus lanes, etc | J6: SAFE | K6: Josh Keeling, Safety Manager | L6: SAFE | M6: =IF(D6="","",D6+28) -> 45332 | N6: =IF(D6="",3,IF(M6<$A$2,1,0)) -> 1 | O6: 45304 | Q6: Comms now shared with staff asking to report through OCC
A7: =IF(O7>1,"Closed",IF(N7=1,"Overdue",IF(N7=3,"","Open"))) -> Closed | B7: Level 1 Investigation Recommendation | C7: Rachel Bridges | D7: 45305 | E7: 2310 | F7: 2309-35 | G7: =VLOOKUP(F7,'Accident & Incident Detail'!$D$3:$E$165,2,FALSE) -> #N/A | H7: 2023/2024-21 | I7: HR Investigation | J7: CS | K7: Rachel Bridges, Duty Manager | L7: CS | M7: =IF(D7="","",D7+28) -> 45333 | N7: =IF(D7="",3,IF(M7<$A$2,1,0)) -> 1 | O7: 45336
A8: =IF(O8>1,"Closed",IF(N8=1,"Overdue",IF(N8=3,"","Open"))) -> Closed | B8: Safety Inspection Action | D8: 45308 | E8: 2310 | G8: =VLOOKUP(F8,'Accident & Incident Detail'!$D$3:$E$165,2,FALSE) -> #N/A | H8: 2023/2024-22 | I8: Hollinsend tram stop inbound, accessibility for maintenance cleaning | J8: INFRA | K8: Neill Barraclough Deputy Head of Engineering | L8: ENG | M8: =IF(D8="","",D8+28) -> 45336 | N8: =IF(D8="",3,IF(M8<$A$2,1,0)) -> 1 | O8: 45902 | Q8: Closed due to time elapsed
A9: =IF(O9>1,"Closed",IF(N9=1,"Overdue",IF(N9=3,"","Open"))) -> Closed | B9: Safety Inspection Action | D9: 45308 | E9: 2310 | G9: =VLOOKUP(F9,'Accident & Incident Detail'!$D$3:$E$165,2,FALSE) -> #N/A | H9: 2023/2024-23 | I9: Posters cases – not fastened properly top bolt missing all locations | J9: FACILITIES | L9: ENG | M9: =IF(D9="","",D9+28) -> 45336 | N9: =IF(D9="",3,IF(M9<$A$2,1,0)) -> 1 | O9: 45311 | Q9: Tacted
A10: =IF(O10>1,"Closed",IF(N10=1,"Overdue",IF(N10=3,"","Open"))) -> Closed | B10: Safety Inspection Action | D10: 45308 | E10: 2310 | G10: =VLOOKUP(F10,'Accident & Incident Detail'!$D$3:$E$165,2,FALSE) -> #N/A | H10: 2023/2024-24 | I10: Consider additional signage on ped crossing MTE | J10: FACILITIES | K10: Mark Blackwell Cleaning Manager | L10: ENG | M10: =IF(D10="","",D10+28) -> 45336 | N10: =IF(D10="",3,IF(M10<$A$2,1,0)) -> 1 | O10: 45902 | P10: 02/809/2025 | Q10: Not assigned to right action owner slosed due to time elapsed
A11: =IF(O11>1,"Closed",IF(N11=1,"Overdue",IF(N11=3,"","Open"))) -> Closed | B11: Safety Inspection Action | D11: 45308 | E11: 2310 | G11: =VLOOKUP(F11,'Accident & Incident Detail'!$D$3:$E$165,2,FALSE) -> #N/A | H11: 2023/2024-25 | I11: Anti trespass Moss Way outbound does not go all the way up to the border fence creating desire line | J11: SAFE | K11: Josh Keeling, Safety Manager | L11: SAFE | M11: 45687 | N11: =IF(D11="",3,IF(M11<$A$2,1,0)) -> 1 | O11: 45902 | Q11: JK has sumbmitted paperwork to KS for approval - date extended procurement lead time -10/06/2025 PO approved and sent after no quotes received from othwer parties AB to liase with Forward Fencing at arrange a date for works to start - Contractor has not been able to complete this work a neww PO has been raised and new contractor will be sought
A12: =IF(O12>1,"Closed",IF(N12=1,"Overdue",IF(N12=3,"","Open"))) -> Closed | B12: Safety Inspection Action | D12: 45308 | E12: 2310 | G12: =VLOOKUP(F12,'Accident & Incident Detail'!$D$3:$E$165,2,FALSE) -> #N/A | H12: 2023/2024-26 | I12: Moss Way - Install fence to stop cyclists cutting through ped crossing inbound side | J12: FACILITIES | K12: Josh Keeling, Safety Manager | L12: ENG | M12: 45687 | N12: =IF(D12="",3,IF(M12<$A$2,1,0)) -> 1 | O12: 45902 | Q12: JK has sumbmitted paperwork to KS for approval - date extended procurement lead time - 10/06/2025 PO approved and sent after no quotes received from othwer parties AB to liase with Forward Fencing at arrange a date for works to start- see previous action regarding contractor.
A13: =IF(O13>1,"Closed",IF(N13=1,"Overdue",IF(N13=3,"","Open"))) -> Closed | B13: Safety Inspection Action | D13: 45308 | E13: 2310 | G13: =VLOOKUP(F13,'Accident & Incident Detail'!$D$3:$E$165,2,FALSE) -> #N/A | H13: 2023/2024-27 | I13: Moss Way outbound ped crossing -cut back vegetation (both sides) to comply with sighting distance for peds using crossing. | J13: FACILITIES | K13: Mark Blackwell Cleaning Manager | L13: ENG | M13: =IF(D13="","",D13+28) -> 45336 | N13: =IF(D13="",3,IF(M13<$A$2,1,0)) -> 1 | O13: 45381
A14: =IF(O14>1,"Closed",IF(N14=1,"Overdue",IF(N14=3,"","Open"))) -> Closed | B14: Management Walkarounds | C14: Josh Keeling | D14: 45308 | E14: 2310 | G14: =VLOOKUP(F14,'Accident & Incident Detail'!$D$3:$E$165,2,FALSE) -> #N/A | H14: 2023/2024-44 | I14: Completed track walk from Moss Way- Hollinsend- Manor Top as part of QSRM | J14: SAFE | K14: Josh Keeling, Safety Manager | L14: SAFE | M14: =IF(D14="","",D14+28) -> 45336 | N14: =IF(D14="",3,IF(M14<$A$2,1,0)) -> 1 | O14: 45308
A15: =IF(O15>1,"Closed",IF(N15=1,"Overdue",IF(N15=3,"","Open"))) -> Closed | B15: BOSRIA Action | C15: George Lilley | D15: 45308 | E15: 2310 | G15: =VLOOKUP(F15,'Accident & Incident Detail'!$D$3:$E$165,2,FALSE) -> #N/A | H15: 2023/2024-11 | I15: Moss way outbound near pole - Cyclists going around staggered fence - A little fence | J15: FACILITIES | K15: Mark Blackwell Cleaning Manager | L15: ENG | M15: =IF(D15="","",D15+28) -> 45336 | N15: =IF(D15="",3,IF(M15<$A$2,1,0)) -> 1 | O15: 45308 | Q15: 17/01/2024 After visiting site safety it was agreed that the Vegetation will be cut back and fence installed Moss Way ped crossing inboud, vegetation will be cut back to ensure adquate site lines at Moss Way ped crossing out bound
A16: =IF(O16>1,"Closed",IF(N16=1,"Overdue",IF(N16=3,"","Open"))) -> Closed | B16: BOSRIA Action | C16: Matt Wright | D16: 45308 | E16: 2310 | G16: =VLOOKUP(F16,'Accident & Incident Detail'!$D$3:$E$165,2,FALSE) -> #N/A | H16: 2023/2024-12 | I16: Nunnery depot 9W Stood against racking wooden ladders no inspection date not stored anywhere in particular - Who deals with ladder inspections and why have these had none. | J16: SAFE | K16: Andy Buckley, Safety Officer | L16: SAFE | M16: =IF(D16="","",D16+28) -> 45336 | N16: =IF(D16="",3,IF(M16<$A$2,1,0)) -> 1 | O16: 45336 | Q16: The ladders have been taken out of action and awaiting login details for XV plus to ensure maintenance schedule is taking place
A17: =IF(O17>1,"Closed",IF(N17=1,"Overdue",IF(N17=3,"","Open"))) -> Closed | B17: Safety Inspection Action | C17: Tony Waddingham | D17: 45309 | E17: 2310 | G17: =VLOOKUP(F17,'Accident & Incident Detail'!$D$3:$E$165,2,FALSE) -> #N/A | H17: 2023/2024-02 | I17: Safety clasp is missing off bogie crane | J17: RSM | K17: Nikolas Dobbs Head of Engineering | L17: ENG | M17: =IF(D17="","",D17+28) -> 45337 | N17: =IF(D17="",3,IF(M17<$A$2,1,0)) -> 1 | O17: 45536
A18: =IF(O18>1,"Closed",IF(N18=1,"Overdue",IF(N18=3,"","Open"))) -> Closed | B18: Safety Inspection Action | C18: Tony Waddingham | D18: 45309 | E18: 2310 | G18: =VLOOKUP(F18,'Accident & Incident Detail'!$D$3:$E$165,2,FALSE) -> #N/A | H18: 2023/2024-03 | I18: Bolier broken staff canteen | J18: RSM | K18: Nikolas Dobbs Head of Engineering | L18: ENG | M18: =IF(D18="","",D18+28) -> 45337 | N18: =IF(D18="",3,IF(M18<$A$2,1,0)) -> 1 | O18: 45320 | Q18: Has been replaced
A19: =IF(O19>1,"Closed",IF(N19=1,"Overdue",IF(N19=3,"","Open"))) -> Closed | B19: Safety Inspection Action | C19: Tony Waddingham | D19: 45309 | E19: 2310 | G19: =VLOOKUP(F19,'Accident & Incident Detail'!$D$3:$E$165,2,FALSE) -> #N/A | H19: 2023/2024-04 | I19: Eyewash missing from station located near toliets in engineering depot | J19: FACILITIES | K19: Mark Blackwell Cleaning Manager | L19: ENG | M19: =IF(D19="","",D19+28) -> 45337 | N19: =IF(D19="",3,IF(M19<$A$2,1,0)) -> 1 | O19: 45311 | Q19: Has been replaced
A20: =IF(O20>1,"Closed",IF(N20=1,"Overdue",IF(N20=3,"","Open"))) -> Closed | B20: BOSRIA Action | C20: Anom | D20: 45309 | E20: 2310 | G20: =VLOOKUP(F20,'Accident & Incident Detail'!$D$3:$E$165,2,FALSE) -> #N/A | H20: 2023/2024-06 | I20: TAXI heading illegally using Tram Only lane heading Inbound towards Cathedral causing near-miss potential for accident and causing potential signalling issue. VEHICLE REG WJ69FH - Report to SCC via taxilicensing@sheffield.gov.uk and feedback. | J20: SAFE | K20: Josh Keeling, Safety Manager | L20: SAFE | M20: =IF(D20="","",D20+28) -> 45337 | N20: =IF(D20="",3,IF(M20<$A$2,1,0)) -> 1 | O20: 45309 | Q20: Comms now shared with staff asking to report through OCC
A21: =IF(O21>1,"Closed",IF(N21=1,"Overdue",IF(N21=3,"","Open"))) -> Closed | B21: BOSRIA Action | C21: Gage West | D21: 45309 | E21: 2310 | G21: =VLOOKUP(F21,'Accident & Incident Detail'!$D$3:$E$165,2,FALSE) -> #N/A | H21: 2023/2024-07 | I21: I'm sure most drivers will agree with me on this one.A lately signals have been playing up all over the system. Until they are fixed properly is there a chance we could have permission to go through Green and bar signal that have NO conflicting traffic moves when in this phase, for example; Infirmary road/Flora street, infirmary Road/Albert Terrace Road, West street/Carver street, West street/Holly Street, Etc. Not only would it help drivers run on time, it would benefit OCC as they would not get as many calls regarding signals. - Allow drivers to go through Green and bar at NON-CONFLICTING Junctions. (No conflicting traffic moves) | J21: SAFE | K21: Josh Keeling, Safety Manager | L21: SAFE | M21: =IF(D21="","",D21+28) -> 45337 | N21: =IF(D21="",3,IF(M21<$A$2,1,0)) -> 1 | O21: 44952 | Q21: This concern has been considered by JK SG &SG and it has been identfied that the safest option is to continue reporting green & bar and working under OCC instruction, to note the timetable is not considered priority when tramway signalling causes an issue.
A22: =IF(O22>1,"Closed",IF(N22=1,"Overdue",IF(N22=3,"","Open"))) -> Closed | B22: BOSRIA Action | C22: George Lilley | D22: 45309 | E22: 2310 | G22: =VLOOKUP(F22,'Accident & Incident Detail'!$D$3:$E$165,2,FALSE) -> #N/A | H22: 2023/2024-10 | I22: The tramway look both way signs are not designed for anyone that doesn't speak English - Pictures in corners of eyes with arrows | J22: SAFE | K22: Josh Keeling, Safety Manager | L22: SAFE | M22: =IF(D22="","",D22+28) -> 45337 | N22: =IF(D22="",3,IF(M22<$A$2,1,0)) -> 1 | O22: 45331 | Q22: Cannot change standard signage look to introduce "look both ways" paint at ground level
A23: =IF(O23>1,"Closed",IF(N23=1,"Overdue",IF(N23=3,"","Open"))) -> Closed | B23: BOSRIA Action | C23: Anom | D23: 45310 | E23: 2310 | G23: =VLOOKUP(F23,'Accident & Incident Detail'!$D$3:$E$165,2,FALSE) -> #N/A | H23: 2023/2024-19 | I23: Crystal Peaks rear NMUS crossings -Possibly local educating by training at schools/colleges etc. Crossing is due to be risk assessed shortly. Near Miss: Whilst undertaking checks of anti-vandal posts at crossing with JK at approx time witnessed a group of youths meandering across tracks not using crossing. Positive Intervention: Asked them not to walk on the tracks, although ignored they completed their crossing safely and exited on the crossing- Possibly local educating by training at schools/colleges etc. Crossing is due to be risk assessed shortly. | J23: SAFE | K23: Josh Keeling, Safety Manager | L23: SAFE | M23: =IF(D23="","",D23+28) -> 45338 | N23: 0 | O23: 45413 | Q23: Closed to be picked up by the rail safe friendly team
A24: =IF(O24>1,"Closed",IF(N24=1,"Overdue",IF(N24=3,"","Open"))) -> Closed | B24: BOSRIA Action | C24: Andrew Buckley | D24: 45313 | E24: 2310 | G24: =VLOOKUP(F24,'Accident & Incident Detail'!$D$3:$E$165,2,FALSE) -> #N/A | H24: 2023/2024-09 | I24: Anti-vandal posts at crossing with JK at approx time witnessed a group of youths meandering across tracks not using crossing. Positive Intervention: Asked them not to walk on the tracks, although ignored they completed their crossing safely and exited on the crossing-Possibly local educating by training at schools/colleges etc. Crossing is due to be risk assessed shortly. | J24: SAFE | K24: Josh Keeling, Safety Manager | L24: SAFE | M24: =IF(D24="","",D24+28) -> 45341 | N24: =IF(D24="",3,IF(M24<$A$2,1,0)) -> 1 | O24: 45353 | Q24: AB- to review all risk assessments of all NMU crossings action ongoing - Email from JK 02/04/2024 - AB carried out RA for this crossing. Schools programme considered through Rail Safety group for Year 1 plan - check with WD at Safety Board meeting
A25: =IF(O25>1,"Closed",IF(N25=1,"Overdue",IF(N25=3,"","Open"))) -> Closed | B25: Level 1 Investigation Recommendation | C25: Andy Roberts | D25: 45313 | E25: 2310 | F25: 2310-22 | G25: =VLOOKUP(F25,'Accident & Incident Detail'!$D$3:$E$165,2,FALSE) -> Verbal Abuse | H25: 2023/2024-43 | I25: Reinforce coflict aviodance techniques and remind not to hold trams creating further hazardous situation | J25: CS | K25: Andy Roberts, Duty Manager | L25: CS | M25: =IF(D25="","",D25+28) -> 45341 | N25: =IF(D25="",3,IF(M25<$A$2,1,0)) -> 1 | O25: 45313 | Q25: Completed at the time of the interview
A26: =IF(O26>1,"Closed",IF(N26=1,"Overdue",IF(N26=3,"","Open"))) -> Closed | B26: Level 1 Investigation Recommendation | C26: Gary Seaborn | D26: 45313 | E26: 2310 | F26: 2308-40 | G26: =VLOOKUP(F26,'Accident & Incident Detail'!$D$3:$E$165,2,FALSE) -> #N/A | H26: 2023/2024-45 | I26: Driver Carol Harrison to have refresher course on procedure of how to enter the depot shed and what safety checks to follow. | J26: TRAINING | K26: Training Department | L26: CS | M26: =IF(D26="","",D26+28) -> 45341 | N26: =IF(D26="",3,IF(M26<$A$2,1,0)) -> 1 | O26: 45321
A27: =IF(O27>1,"Closed",IF(N27=1,"Overdue",IF(N27=3,"","Open"))) -> Closed | B27: Level 1 Investigation Recommendation | C27: Gary Seaborn | D27: 45313 | E27: 2310 | F27: 2308-40 | G27: =VLOOKUP(F27,'Accident & Incident Detail'!$D$3:$E$165,2,FALSE) -> #N/A | H27: 2023/2024-46 | I27: All RSM personnel to take part in a toolbox talk regrading procedure to follow when guiding a tram in to the depot shed | J27: RSM | K27: Training Department | L27: ENG | M27: =IF(D27="","",D27+28) -> 45341 | N27: =IF(D27="",3,IF(M27<$A$2,1,0)) -> 1 | O27: 45746 | Q27: 27/02/2025 Email received from A Rathbone - 18/02/2025 - Action owner has been reassigned to training dept - technically not overdue. Not aware of this till today 27/02/2025, we will develop a toolbox talk and deliver by end of March 2025
A28: =IF(O28>1,"Closed",IF(N28=1,"Overdue",IF(N28=3,"","Open"))) -> Closed | B28: BOSRIA Action | C28: Nigel Wragg | D28: 45314 | E28: 2310 | G28: =VLOOKUP(F28,'Accident & Incident Detail'!$D$3:$E$165,2,FALSE) -> #N/A | H28: 2023/2024-13 | I28: At busy events could staff wear hivis caps so that staff can be easily identified amongst the crowd. This will enable managers to better understand the location of staff and ensure that they are located in a safe position | J28: SAFE | K28: Josh Keeling, Safety Manager | L28: SAFE | M28: =IF(D28="","",D28+28) -> 45342 | N28: =IF(D28="",3,IF(M28<$A$2,1,0)) -> 1 | O28: 45353 | Q28: Email from JK 02/04/2024 - Staff already wear hivis jackets for events - feel that this is enough to spot in crowds caps could be taken off by members of the public
A29: =IF(O29>1,"Closed",IF(N29=1,"Overdue",IF(N29=3,"","Open"))) -> Closed | B29: BOSRIA Action | C29: Dave Johnson | D29: 45314 | E29: 2310 | G29: =VLOOKUP(F29,'Accident & Incident Detail'!$D$3:$E$165,2,FALSE) -> #N/A | H29: 2023/2024-42 | I29: For the second time recently I have had to give out my personal mobile number because the tram mobile number was not known - Please ensure that all tram phone numbers are clearly written on the phone cases | J29: OPS | K29: Dave Marrison, OCC Manager | L29: CS | M29: =IF(D29="","",D29+28) -> 45342 | N29: =IF(D29="",3,IF(M29<$A$2,1,0)) -> 1 | O29: 45331 | Q29: All mobile phones have number dynamo stickered to back of phone case
A30: =IF(O30>1,"Closed",IF(N30=1,"Overdue",IF(N30=3,"","Open"))) -> Closed | B30: BOSRIA Action | C30: Anom | D30: 45315 | E30: 2310 | G30: =VLOOKUP(F30,'Accident & Incident Detail'!$D$3:$E$165,2,FALSE) -> #N/A | H30: 2023/2024-14 | I30: Nunnery Depot Main vehicle gate - Gates open due to severe winds and held with tie wraps- Suggest welding and using sufficient drop bolts as tie wraps/rope or other could snap/break and potentially cause an incident. | J30: ENG | K30: Nikolas Dobbs Head of Engineering | L30: ENG | M30: =IF(D30="","",D30+28) -> 45343 | N30: =IF(D30="",3,IF(M30<$A$2,1,0)) -> 1 | O30: 45320 | Q30: New actuators should be sufficient to maintain position - this is being investigated by the supplier
A31: =IF(O30>1,"Closed",IF(N31=1,"Overdue",IF(N31=3,"","Open"))) -> Closed | B31: Level 1 Investigation Recommendation | C31: Andy Roberts | D31: 45315 | E31: 2310 | F31: 2309-43 | G31: =VLOOKUP(F31,'Accident & Incident Detail'!$D$3:$E$165,2,FALSE) -> #N/A | H31: 2023/2024-89 | I31: Discuss non escalation during next scheduled TWYM meeting | J31: CS | K31: Andy Roberts, Duty Manager | L31: CS | M31: =IF(D31="","",D31+28) -> 45343 | N31: =IF(D31="",3,IF(M31<$A$2,1,0)) -> 1 | O31: 45350
A32: =IF(O32>1,"Closed",IF(N32=1,"Overdue",IF(N32=3,"","Open"))) -> Closed | B32: BOSRIA Action | C32: Anom | D32: 45316 | E32: 2310 | G32: =VLOOKUP(F32,'Accident & Incident Detail'!$D$3:$E$165,2,FALSE) -> #N/A | H32: 2023/2024-17 | I32: Approx between 1505-1515 CK04YEL Yaris causing near miss overtaking Tram and using tram only lane towards Cathedral. CCTV- Report to relevant authority. | J32: SAFE | K32: Josh Keeling, Safety Manager | L32: SAFE | M32: =IF(D32="","",D32+28) -> 45344 | N32: =IF(D32="",3,IF(M32<$A$2,1,0)) -> 1 | O32: 45331 | Q32: Is being picked up as part of workstream around this junction - a notice has been posted to staff via Blink asking them to repoat all near misses at this location through to OCC
A33: =IF(O33>1,"Closed",IF(N33=1,"Overdue",IF(N33=3,"","Open"))) -> Closed | B33: BOSRIA Action | C33: Jason Lawrie | D33: 45317 | E33: 2310 | G33: =VLOOKUP(F33,'Accident & Incident Detail'!$D$3:$E$165,2,FALSE) -> #N/A | H33: 2023/2024-16 | I33: Platform lighting comes on 30 mins after going dark. Massive safety concerns, pulling into a busy unlit platform, anyone sat on edge platform, too close edge, can't see back of platform when shut the doors etc etc. Been reported to OCC who say it's a known issue, been reported to Duty Managers.... Nothing gets done. Even know when gets lighter in evening still comes on 30 mins after dark. Stops like Gleadless and Hollisend lighting turns off before midnight when there are still 3 service trams due through - Either regulate all platform lighting to come on when goes dusk or fit sensors to trigger them to come on automatically at dusk. | J33: ENG | K33: Nikolas Dobbs Head of Engineering | L33: ENG | M33: =IF(D33="","",D33+28) -> 45345 | N33: =IF(D33="",3,IF(M33<$A$2,1,0)) -> 1 | O33: 45323 | Q33: 01/02/2024 response sent back to Jlawrie, OCC updated - Joe/Jack asked in OCC for a list of potential problem areas but none of the controllers on shift were aware of any list. We will attend to any lights reported to us which have a timer issue and if required will disconnect the time clock unit. Once disconnected the lights will be illuminated via the Photo-electric cell 24/7 and will switch on/off depending on the ambient light levels at each location. Originally the timers were fitted to the tower lights on each platform to help with energy saving. Since replacing all the lamps with more efficient LED types there is no longer a need for the timers in circuit. Going forward if there are any locations where the timers fail we will just revert back to relying on the PE cells to control the lighting. Also require drivers to now inform in lights are on during daylight hours as will indicate photo senso failure and need to be addressed
A34: =IF(O34>1,"Closed",IF(N34=1,"Overdue",IF(N34=3,"","Open"))) -> Closed | B34: BOSRIA Action | C34: Anom | D34: 45317 | E34: 2310 | G34: =VLOOKUP(F34,'Accident & Incident Detail'!$D$3:$E$165,2,FALSE) -> #N/A | H34: 2023/2024-18 | I34: The number of bulbs not working/missing in the older style LRT’s now is getting a little ridiculous. Over a few duty’s covering MAB, HAL, MID, MEH, I roughly counted over 250 bulbs not lit. This does not consider the bulbs on the bar aspects not visible to me. Yes, I report any that have all but one/two lit, or in some cases where bar’s are not lit at all, but we cannot report every LRT on a route - s it feasible that a team can go out with a packet of bulbs and a step ladder and fix them route by route, then have a scheduled x-monthly schedule to check/replace? The new LED’s (?) ones being installed are much clearer and reliable | J34: INFRA | K34: Neill Barraclough Infrastructure Manager | L34: ENG | M34: =IF(D34="","",D34+28) -> 45345 | N34: =IF(D34="",3,IF(M34<$A$2,1,0)) -> 1 | O34: 45321 | Q34: Email from N Barraclough - We already have these actions in place for regular sweeps to check the LRT Lamps It's a regular inspection on xvp ; the issue we are now facing is the lamps we need to replace them with are no longer made. It may be worth sending the person who sent this a copy of the report I sent you, Josh, explaining why the lamps aren't always the issue. as they seem to believe we don't go and check them!! The comment about the new LED being better is nice to hear, and I will pass it on to AMEY, who are doing that work, as it will no doubt be pleasing to them.
A35: =IF(O35>1,"Closed",IF(N35=1,"Overdue",IF(N35=3,"","Open"))) -> Closed | B35: BOSRIA Action | C35: Alan Barclay | D35: 45317 | E35: 2310 | G35: =VLOOKUP(F35,'Accident & Incident Detail'!$D$3:$E$165,2,FALSE) -> #N/A | H35: 2023/2024-41 | I35: Would it be an idea to have signs on major junction traffic lights (i.e. Manor Top, Gleadless Townend) saying that if the traffic lights are off, give way to/beware of trams The same sort of thing they have at Parkway/Derek Dooley Way Junction | J35: SAFE | K35: Josh Keeling, Safety Manager | L35: SAFE | M35: =IF(D35="","",D35+28) -> 45345 | N35: =IF(D35="",3,IF(M35<$A$2,1,0)) -> 1 | O35: 45413 | Q35: MoU Felt that it would not help the situation as those signs were specifically for that junction where there have been previous incidents
A36: =IF(O36>1,"Closed",IF(N36=1,"Overdue",IF(N36=3,"","Open"))) -> Closed | B36: BOSRIA Action | C36: Anom | D36: 45320 | E36: 2310 | G36: =VLOOKUP(F36,'Accident & Incident Detail'!$D$3:$E$165,2,FALSE) -> #N/A | H36: 2023/2024-35 | I36: City Hall stop inbound to Cathedral Near miss as multiple vehicles followed 108 disobeying signals and 'Tram only' signage One was a council bus and another was a Taxi- Use CCTV checking. | J36: SAFE | K36: Josh Keeling, Safety Manager | L36: SAFE | M36: =IF(D36="","",D36+28) -> 45348 | N36: =IF(D36="",3,IF(M36<$A$2,1,0)) -> 1 | O36: 45349 | Q36: Already being actioned
A37: =IF(O37>1,"Closed",IF(N37=1,"Overdue",IF(N37=3,"","Open"))) -> Closed | B37: BOSRIA Action | C37: Keith Sockett | D37: 45320 | E37: 2310 | G37: =VLOOKUP(F37,'Accident & Incident Detail'!$D$3:$E$165,2,FALSE) -> #N/A | H37: 2023/2024-36 | I37: Safety course passes need updating. Nothing to stop for example a Depot, Track or Lookout pass being passed on to a person who has not completed the training. Passes should have a photo ID, we have the facilities to complete this, but not being used. Maybe now is a good time to create these with the new logo etc. | J37: SAFE | K37: Josh Keeling, Safety Manager | L37: ENG | M37: =IF(D37="","",D37+28) -> 45348 | N37: =IF(D37="",3,IF(M37<$A$2,1,0)) -> 1 | O37: 45385 | Q37: A new pass has been developed by all parties involved - finalising printer installation on training cabin
A38: =IF(O38>1,"Closed",IF(N38=1,"Overdue",IF(N38=3,"","Open"))) -> Closed | B38: BOSRIA Action | C38: Sharon Galloway | D38: 45324 | E38: 2310 | G38: =VLOOKUP(F38,'Accident & Incident Detail'!$D$3:$E$165,2,FALSE) -> #N/A | H38: 2023/2024-28 | I38: Hello, not a safety report, but an environmental and money saving suggestion? The upstairs corridor in the depot is illuminated 24 hours a day/ 7 days a week. When the office staff have left, there are minimal people walking up and down and especially after service ends there is little to no traffic for 4 hours. My suggestion is that we install sensors so the lighting is only on when someone is actually walking (like is in the upstairs toilets) Clearly don't know if there is legislation around this, but I have witnessed it in many hotels . Thanks for considering this. | J38: INFRA | K38: Neill Barraclough Infrastructure Manager | L38: ENG | M38: =IF(D38="","",D38+28) -> 45352 | N38: =IF(D38="",3,IF(M38<$A$2,1,0)) -> 1 | O38: 45355 | Q38: Email from MB 13/02/2024 This is a very valid point and I’m sure this could be done. It might be better passing this BOSRIA to Mark Tompkins and his electrical team to see if this could be achievable. Has been sent to MTomkins & Ilevin - Comments from Mark Tomkins - 04/03/2024 - Mark Tomkins it would not be reasonbabaly practical to fit sensots outside of every office - States that as the light fittings alrready in place are LED they do not use a vast amount of energy and it works out less expensive to leave them them on rather than purchasing sensors to swtich them on/off with occupancy
A39: =IF(O39>1,"Closed",IF(N39=1,"Overdue",IF(N39=3,"","Open"))) -> Closed | B39: BOSRIA Action | C39: Dave Johnson | D39: 45324 | E39: 2310 | G39: =VLOOKUP(F39,'Accident & Incident Detail'!$D$3:$E$165,2,FALSE) -> #N/A | H39: 2023/2024-34 | I39: Following up my previous advise about dogs & bikes boarding TramTrain: nice to see the new signs on the TramTrain doors, but someone that has been waiting for 25mins in freezing rain would most probably appreciate being told earlier - Could we erect similar signs on the approach to Parkgate & Rotherham Central stops. | J39: CS | K39: James Stewart, Head of Customer Services | L39: CS | M39: =IF(D39="","",D39+28) -> 45352 | N39: =IF(D39="",3,IF(M39<$A$2,1,0)) -> 1 | O39: 45334 | Q39: We cannot put up notices for every scenario or situation - speka to Nigel and ask about adding it to the notice case as a more general notice
A40: =IF(O40>1,"Closed",IF(N40=1,"Overdue",IF(N40=3,"","Open"))) -> Closed | B40: Level 1 Investigation Recommendation | C40: Nina Wybrant | D40: 45325 | E40: 2311 | F40: 2309-33 | G40: =VLOOKUP(F40,'Accident & Incident Detail'!$D$3:$E$165,2,FALSE) -> #N/A | H40: 2023/2024-57 | I40: Note to file | J40: CS | K40: Nina Wybrant Duty Manager | L40: CS | M40: =IF(D40="","",D40+28) -> 45353 | N40: =IF(D40="",3,IF(M40<$A$2,1,0)) -> 1 | O40: 45325
A41: =IF(O41>1,"Closed",IF(N41=1,"Overdue",IF(N41=3,"","Open"))) -> Closed | B41: Level 1 Investigation Recommendation | C41: Nina Wybrant | D41: 45325 | E41: 2311 | F41: 2309-33 | G41: =VLOOKUP(F41,'Accident & Incident Detail'!$D$3:$E$165,2,FALSE) -> #N/A | H41: 2023/2024-58 | I41: Covert ride check | J41: CS | K41: Nina Wybrant Duty Manager | L41: CS | M41: =IF(D41="","",D41+28) -> 45353 | N41: =IF(D41="",3,IF(M41<$A$2,1,0)) -> 1 | O41: 45325
A42: =IF(O42>1,"Closed",IF(N42=1,"Overdue",IF(N42=3,"","Open"))) -> Closed | B42: BOSRIA Action | C42: Russ Wild | D42: 45326 | E42: 2311 | G42: =VLOOKUP(F42,'Accident & Incident Detail'!$D$3:$E$165,2,FALSE) -> #N/A | H42: 2023/2024-32 | I42: Infirmary Road Flora Street -When travelling inbound at this location, trams will have a proceed but it is still possible for other road traffic coming the other way to turn right across the path of the tram (see attached screenshot), sometimes causing harsh braking/near miss by the tram. I believe this happens because the other vehicle also has a green light and the driver may assume the tram is going to stop - Could an orange "Right Turners Beware Oncoming Vehicles" sign be fitted in the location marked in the screenshot to make the junction clearer? | J42: SAFE | K42: Josh Keeling, Safety Manager | L42: SAFE | M42: =IF(D42="","",D42+28) -> 45354 | N42: =IF(D42="",3,IF(M42<$A$2,1,0)) -> 1 | O42: 45349 | Q42: JK to rasie at MOU meeting
A43: =IF(O43>1,"Closed",IF(N43=1,"Overdue",IF(N43=3,"","Open"))) -> Closed | B43: BOSRIA Action | C43: Emma Cooper | D43: 45326 | E43: 2311 | G43: =VLOOKUP(F43,'Accident & Incident Detail'!$D$3:$E$165,2,FALSE) -> #N/A | H43: 2023/2024-33 | I43: The sites here on events are dirty and sometimes unsafe if the weather has been bad. at arena the gates are very difficult to slide due to leaves and mud going into the runners and the walkway gets filled with fallen branches and rubbish. at Leppings Lane the barriers and chain collect mud, rubbish and leaves. our hands get filthy - that cleaners go to these areas on the days of events (use the event list that Andy Cullen sends out) and ensure they are clean and tidy. | J43: FACILITIES | K43: Mark Blackwell Cleaning Manager | L43: ENG | M43: =IF(D43="","",D43+28) -> 45354 | N43: =IF(D43="",3,IF(M43<$A$2,1,0)) -> 1 | O43: 45336 | Q43: The gate runners at the Arena get cleaned out weekly and before any major events. They gates are tried and any defect found are passed on to the FEM coordinator. The barriers at Leppings Lane get removed and taken back to depot every 2 months and are cleaned and jet washed before taking them back. Would suggest a box of disposable gloves are used when handling these barriers.
A44: =IF(O44>1,"Closed",IF(N44=1,"Overdue",IF(N44=3,"","Open"))) -> Closed | B44: Level 1 Investigation Recommendation | C44: Nina Wybrant | D44: 45326 | E44: 2311 | F44: 2309-30 | G44: =VLOOKUP(F44,'Accident & Incident Detail'!$D$3:$E$165,2,FALSE) -> #N/A | H44: 2023/2024-59 | I44: HR Investgation | J44: CS | K44: Nina Wybrant Duty Manager | L44: CS | M44: =IF(D44="","",D44+28) -> 45354 | N44: =IF(D44="",3,IF(M44<$A$2,1,0)) -> 1 | O44: 45287
A45: =IF(O45>1,"Closed",IF(N45=1,"Overdue",IF(N45=3,"","Open"))) -> Closed | B45: Level 1 Investigation Recommendation | C45: Rachel Bridges | D45: 45326 | E45: 2311 | F45: 2310-23 | G45: =VLOOKUP(F45,'Accident & Incident Detail'!$D$3:$E$165,2,FALSE) -> Wrong routing | H45: 2023/2024-87 | I45: Note to file | J45: CS | K45: Rachel Bridges, Duty Manager | L45: CS | M45: =IF(D45="","",D45+28) -> 45354 | N45: =IF(D45="",3,IF(M45<$A$2,1,0)) -> 1 | O45: 45350
A46: =IF(O46>1,"Closed",IF(N46=1,"Overdue",IF(N46=3,"","Open"))) -> Closed | B46: BOSRIA Action | C46: Matt Wright | D46: 45327 | E46: 2311 | G46: =VLOOKUP(F46,'Accident & Incident Detail'!$D$3:$E$165,2,FALSE) -> #N/A | H46: 2023/2024-30 | I46: Canteen walls look filthy, also a section of skirting has come adrift - Repaint | J46: FACILITIES | K46: Mark Blackwell Cleaning Manager | L46: ENG | M46: =IF(D46="","",D46+28) -> 45355 | N46: =IF(D46="",3,IF(M46<$A$2,1,0)) -> 1 | O46: 45335 | Q46: The canteen walls have been damaged by people sitting back on chairs. We can plan in a deep clean and re attached the skirting. A price from a contractor was submitted for the painting but due to costs, at the minute we have no plans to repaint.
A47: =IF(O47>1,"Closed",IF(N47=1,"Overdue",IF(N47=3,"","Open"))) -> Closed | B47: BOSRIA Action | C47: James Stewart | D47: 45327 | E47: 2311 | G47: =VLOOKUP(F47,'Accident & Incident Detail'!$D$3:$E$165,2,FALSE) -> #N/A | H47: 2023/2024-31 | I47: Still a lot of visitors to site who aren't expected. Creates a risk around LRSP as unapproved visitors could end up on site where they shouldn't be - Process whereby anyone expecting visitors tells Reception (and OCC particularly out of office hours) so that someone knows who is coming. Accepted deliveries are not easily addressed under this suggestion but at least contractors and visitors are known about before they arrive and are met by their appointed contact, who is known because Alison or OCC are aware to expect them | J47: SAFE | K47: Josh Keeling, Safety Manager | L47: SAFE | M47: =IF(D47="","",D47+28) -> 45355 | N47: =IF(D47="",3,IF(M47<$A$2,1,0)) -> 1 | O47: 45353 | Q47: JS has put comms out to remind people to inform reception/OCC when expecting visitors
A48: =IF(O48>1,"Closed",IF(N48=1,"Overdue",IF(N48=3,"","Open"))) -> Closed | B48: Level 1 Investigation Recommendation | C48: David Tingle | D48: 45327 | E48: 2311 | F48: 2310-51 | G48: =VLOOKUP(F48,'Accident & Incident Detail'!$D$3:$E$165,2,FALSE) -> Minor - RTC | H48: 2023/2024-84 | I48: A ride check was carried out with Jonathan Meikle to make sure he was ok after the incident and a meeting was held after the CCTV was viewed the driver was advised of audible warning and better anticipation | J48: CS | K48: David Tingle - Duty Manager | L48: CS | M48: =IF(D48="","",D48+28) -> 45355 | N48: =IF(D48="",3,IF(M48<$A$2,1,0)) -> 1 | O48: 45322
A49: =IF(O49>1,"Closed",IF(N49=1,"Overdue",IF(N49=3,"","Open"))) -> Closed | B49: Level 1 Investigation Recommendation | C49: David Tingle | D49: 45327 | E49: 2311 | F49: 2308-28 | G49: =VLOOKUP(F49,'Accident & Incident Detail'!$D$3:$E$165,2,FALSE) -> #N/A | H49: 2023/2024-85 | I49: Sarah Gregory to be spoken with regards future conflict avoidance and to check on her welfare | J49: CS | K49: David Tingle - Duty Manager | L49: CS | M49: =IF(D49="","",D49+28) -> 45355 | N49: =IF(D49="",3,IF(M49<$A$2,1,0)) -> 1 | O49: 45310
A50: =IF(O50>1,"Closed",IF(N50=1,"Overdue",IF(N50=3,"","Open"))) -> Closed | B50: Level 1 Investigation Recommendation | C50: David Tingle | D50: 45327 | E50: 2311 | F50: 2308-28 | G50: =VLOOKUP(F50,'Accident & Incident Detail'!$D$3:$E$165,2,FALSE) -> #N/A | H50: 2023/2024-86 | I50: Marie Rowbottom to be spoken to about the use of conflict training in future | J50: CS | K50: David Tingle - Duty Manager | L50: CS | M50: =IF(D50="","",D50+28) -> 45355 | N50: =IF(D50="",3,IF(M50<$A$2,1,0)) -> 1 | O50: 45327
A51: =IF(O51>1,"Closed",IF(N51=1,"Overdue",IF(N51=3,"","Open"))) -> Closed | B51: BOSRIA Action | C51: Anom | D51: 45328 | E51: 2311 | G51: =VLOOKUP(F51,'Accident & Incident Detail'!$D$3:$E$165,2,FALSE) -> #N/A | H51: 2023/2024-29 | I51: Crystal Peaks - As a driver finding this area very dark in this miserable weather, I wandered if the new light posts on the crossings are going to be working soon? Are they solar? - Switch lights on when dark. | J51: INFRA | L51: ENG | M51: =IF(D51="","",D51+28) -> 45356 | N51: =IF(D51="",3,IF(M51<$A$2,1,0)) -> 1 | O51: 45328 | Q51: Crystal Peaks issue Mark Tomkins in chasing
A52: =IF(O52>1,"Closed",IF(N52=1,"Overdue",IF(N52=3,"","Open"))) -> Closed | B52: BOSRIA Action | C52: Stephen White | D52: 45329 | E52: 2311 | I52: Tram 17 in cab 1 has a thick layer of black muck over the dash and emergency switch panel. Cab 2 is slightly better but still has a layer of black dust all throughout the cab. | J52: FACILITIES | K52: Mark Blackwell Cleaning Manager | L52: ENG | M52: =IF(D52="","",D52+28) -> 45357 | N52: =IF(D52="",3,IF(M52<$A$2,1,0)) -> 1 | O52: 45331 | Q52: Tram was cleaned when it came back inot the depot 09/02/2024
A53: =IF(O53>1,"Closed",IF(N53=1,"Overdue",IF(N53=3,"","Open"))) -> Closed | B53: BOSRIA Action | C53: Matt Wright | D53: 45330 | E53: 2311 | G53: =VLOOKUP(F53,'Accident & Incident Detail'!$D$3:$E$165,2,FALSE) -> #N/A | H53: 2023/2024-38 | I53: Duff Norton Jacks used by infrastructure for jacking track are not ideal. They are banned on NR and volker rail also do not use these due to the risk involved. | J53: INFRA | K53: Neill Barraclough Infrastructure Manager | L53: ENG | M53: =IF(D53="","",D53+28) -> 45358 | N53: =IF(D53="",3,IF(M53<$A$2,1,0)) -> 1 | O53: 45334 | Q53: Nbarraclough has sourced new jacks to be hired in when needed - also has attached standards breifing notice from Volker Rail that’s need to be factored into Supertram brief when jacks are used
A54: =IF(O54>1,"Closed",IF(N54=1,"Overdue",IF(N54=3,"","Open"))) -> Closed | B54: BOSRIA Action | C54: George Lilley | D54: 45330 | E54: 2311 | G54: =VLOOKUP(F54,'Accident & Incident Detail'!$D$3:$E$165,2,FALSE) -> #N/A | H54: 2023/2024-40 | I54: I reported to occ in September/October that at various locations we need the stop markers on the platforms repainting Hillsborough outbound Beighton outbound virtually nearly gone could we have this done before winter it got tacted down but now February and still not done - Paint please | J54: INFRA | K54: Neill Barraclough Infrastructure Manager | L54: ENG | M54: =IF(D54="","",D54+28) -> 45358 | N54: =IF(D54="",3,IF(M54<$A$2,1,0)) -> 1 | O54: 45376 | Q54: Email from Neill Barraclough this work is an ongoing project.
A55: =IF(O55>1,"Closed",IF(N55=1,"Overdue",IF(N55=3,"","Open"))) -> Closed | B55: BOSRIA Action | C55: Alex Howard | D55: 45335 | E55: 2311 | G55: =VLOOKUP(F55,'Accident & Incident Detail'!$D$3:$E$165,2,FALSE) -> #N/A | H55: 2023/2024-47 | I55: There is a open section of track that I feel requires a boundary fence fitting. On two recent occasions there have been people on or close to the line. The location is between Attercliffe and Arena, approx between poles ATT1136-ATT1137 on the outbound side. This section is 40mph running. There is a open grass slope/banking approx 10-15meters to the pavement and possibly 30-40meters long. The area at the bottom of the banking is used by school children, dog walkers and is now the car park for people visiting the new Canon Medical | J55: SAFE | K55: Josh Keeling, Safety Manager | L55: SAFE | M55: 45687 | N55: =IF(D55="",3,IF(M55<$A$2,1,0)) -> 1 | O55: 45713 | Q55: Will be risk assessed and fedback - JK has sumbmitted paperwork to KS for approval - date extended procurement lead time -25/02/2025JK has confirmed that the fencing has been installed authorised to close by WC
A56: =IF(O56>1,"Closed",IF(N56=1,"Overdue",IF(N56=3,"","Open"))) -> Closed | B56: Level 1 Investigation Recommendation | C56: Andy Roberts | D56: 45335 | E56: 2311 | F56: 2310-46 | G56: =VLOOKUP(F56,'Accident & Incident Detail'!$D$3:$E$165,2,FALSE) -> Threatening Behaviour | H56: 2023/2024-88 | I56: Praise the conductor for remaining calm not escalating and rpeorting correctly and quickly | J56: CS | K56: Andy Roberts, Duty Manager | L56: CS | M56: =IF(D56="","",D56+28) -> 45363 | N56: =IF(D56="",3,IF(M56<$A$2,1,0)) -> 1 | O56: 45333
A57: =IF(O57>1,"Closed",IF(N57=1,"Overdue",IF(N57=3,"","Open"))) -> Closed | B57: Level 1 Investigation Recommendation | C57: Andy Roberts | D57: 45336 | E57: 2311 | F57: 2310-60 | G57: =VLOOKUP(F57,'Accident & Incident Detail'!$D$3:$E$165,2,FALSE) -> Verbal Abuse | H57: 2023/2024-53 | I57: Discuss non-escalalting during nest time with your manager meeting | J57: CS | K57: Andy Roberts, Duty Manager | L57: CS | M57: =IF(D57="","",D57+28) -> 45364 | N57: =IF(D57="",3,IF(M57<$A$2,1,0)) -> 1 | O57: 45001
A58: =IF(O58>1,"Closed",IF(N58=1,"Overdue",IF(N58=3,"","Open"))) -> Closed | B58: Level 1 Investigation Recommendation | C58: Alan Barclay | D58: 45336 | E58: 2311 | F58: 2310-15 | G58: =VLOOKUP(F58,'Accident & Incident Detail'!$D$3:$E$165,2,FALSE) -> Minor - RTC | H58: 2023/2024-54 | I58: Driver retrained on swept path awareness and obsevrvational skilld (report supplied as an apendix | J58: TRAINING | K58: Training Department | L58: CS | M58: =IF(D58="","",D58+28) -> 45364 | N58: =IF(D58="",3,IF(M58<$A$2,1,0)) -> 1 | O58: 45121
A59: =IF(O59>1,"Closed",IF(N59=1,"Overdue",IF(N59=3,"","Open"))) -> Closed | B59: BOSRIA Action | C59: Anon | D59: 45338 | E59: 2311 | G59: =VLOOKUP(F59,'Accident & Incident Detail'!$D$3:$E$165,2,FALSE) -> #N/A | H59: 2023/2024-48 | I59: Just a suggestion for OCC. When doing a radio message/all stations with a road/junction/light location, some OCC controllers will only use the road/junction name. Newer drivers don’t always know exactly where that road junction is by name. | J59: OPS | K59: Dave Marrison, OCC Manager | L59: CS | M59: =IF(D59="","",D59+28) -> 45366 | N59: =IF(D59="",3,IF(M59<$A$2,1,0)) -> 1 | O59: 45365 | Q59: Email sent to OCC from Dave M I think some of you may already do this, I know some of us do this with points, which is good practise and is really helpful to drivers, particularly those that are newly qualified i.e. "Gleadless tango zero one points are in a failed state...". "Hillsborough Hotel Bravo zero one points have failed and will require hand operating...". "Signals at Calver St/West St Jn, just after City Hall O/B, are all out...". "Signals at Fitzwilliam St/West St Jn, after West St O/B, are all out...". etc. So please be mindful of this going forward and, if you're not alraedy doing so, let's start to include a little more location detail in our radio message.Kelly, can you feed back to the person (if possible) that going forward OCC will try to remember to include a little more info. ref. the location etc. but if they, or any driver, are ever unsure of where OCC are referring to or they don't fully understand a message, then they must not acknowledge via a status message and must ask for the message to be repeated, OCC will be more than happy to do so. Op's Standard C5.3 All Stations Acknowledge Addressees will be asked to acknowledge receipt of an all stations call by use of a status. OCC will check acknowledgement from trams and contact any relevant individuals that have not responded. Drivers must only send acknowledgement statuses if the message has been clear and fully understood.
A60: =IF(O60>1,"Closed",IF(N60=1,"Overdue",IF(N60=3,"","Open"))) -> Closed | B60: BOSRIA Action | C60: Anon | D60: 45340 | E60: 2311 | G60: =VLOOKUP(F60,'Accident & Incident Detail'!$D$3:$E$165,2,FALSE) -> #N/A | H60: 2023/2024-51 | I60: Sheffield Station - No platform lights on at gone 18:00 - Fix | J60: INFRA | K60: Neill Barraclough Deputy Head of Engineering | L60: ENG | M60: =IF(D60="","",D60+28) -> 45368 | N60: =IF(D60="",3,IF(M60<$A$2,1,0)) -> 1 | O60: 45377 | Q60: Already raised with Mark Tomkins
A61: =IF(O61>1,"Closed",IF(N61=1,"Overdue",IF(N61=3,"","Open"))) -> Closed | B61: BOSRIA Action | C61: Anon | D61: 45341 | E61: 2311 | G61: =VLOOKUP(F61,'Accident & Incident Detail'!$D$3:$E$165,2,FALSE) -> #N/A | H61: 2023/2024-49 | I61: Nuunery Depot - ST vehicle using the wrong side of entrance gates after a vehicle just departed for convenience - cnetre line posts to prevent wrong path taken | J61: FACILITIES | K61: Mark Blackwell Cleaning Manager | L61: ENG | M61: =IF(D61="","",D61+28) -> 45369 | N61: =IF(D61="",3,IF(M61<$A$2,1,0)) -> 1 | O61: 45377 | Q61: M Blackwell to inform staff that they are not to drive on the wrong side of the gate - Posts can not be put into the center line as this area needs to be clear for large deliveries and when contractors are on site.
A62: =IF(O62>1,"Closed",IF(N62=1,"Overdue",IF(N62=3,"","Open"))) -> Closed | B62: BOSRIA Action | C62: Anon | D62: 45342 | E62: 2311 | G62: =VLOOKUP(F62,'Accident & Incident Detail'!$D$3:$E$165,2,FALSE) -> #N/A | H62: 2023/2024-50 | I62: Nunnery Depot - Volker Rail staff operating telehandler not in work clothing or wearing hivis - ensure contractor operating safely | J62: INFRA | K62: Glin Stanford, Project Co-ordinator | L62: ENG | M62: =IF(D62="","",D62+28) -> 45370 | N62: =IF(D62="",3,IF(M62<$A$2,1,0)) -> 1 | O62: 45377 | Q62: G Stanford has been in touch with Volker Rail management regarding staff not wearing correct PPE
A63: =IF(O63>1,"Closed",IF(N63=1,"Overdue",IF(N63=3,"","Open"))) -> Closed | B63: Level 1 Investigation Recommendation | C63: Nina Wybrant | D63: 45343 | E63: 2311 | G63: =VLOOKUP(F63,'Accident & Incident Detail'!$D$3:$E$1154,2,FALSE) -> #N/A | H63: 2023/2024-217 | I63: Depot refresher trianing | J63: TRAINING | K63: Training Department | L63: CS | M63: =IF(D63="","",D63+28) -> 45371 | N63: =IF(D63="",3,IF(M63<$A$2,1,0)) -> 1 | O63: 45343
A64: =IF(O64>1,"Closed",IF(N64=1,"Overdue",IF(N64=3,"","Open"))) -> Closed | B64: Level 1 Investigation Recommendation | C64: Nina Wybrant | D64: 45343 | E64: 2311 | G64: =VLOOKUP(F64,'Accident & Incident Detail'!$D$3:$E$1154,2,FALSE) -> #N/A | H64: 2023/2024-218 | I64: PDDP | J64: CS | K64: Nina Wybrant Duty Manager | L64: ENG | M64: =IF(D64="","",D64+28) -> 45371 | N64: =IF(D64="",3,IF(M64<$A$2,1,0)) -> 1 | O64: 45343
A65: =IF(O65>1,"Closed",IF(N65=1,"Overdue",IF(N65=3,"","Open"))) -> Closed | B65: BOSRIA Action | C65: Anon | D65: 45348 | E65: 2311 | G65: =VLOOKUP(F65,'Accident & Incident Detail'!$D$3:$E$165,2,FALSE) -> #N/A | H65: 2023/2024-56 | I65: Blue trolley located at bottom of stairs near lift potential hazard for serious injury from falls and preventing accessible users access with reduced gap - previous user return to safe storage area | J65: SAFE | K65: Kelly Henley-Smith, Safety Co-ordinator | L65: SAFE | M65: =IF(D65="","",D65+28) -> 45376 | N65: =IF(D65="",3,IF(M65<$A$2,1,0)) -> 1 | O65: 30/02/2024 | Q65: Trolley has been relocated to the side of the lift on the first floor of the dpet with a noitce reminding staff to put back there when they have finished using it.
A66: =IF(O66>1,"Closed",IF(N66=1,"Overdue",IF(N66=3,"","Open"))) -> Closed | B66: Level 2 Investigation Recommendation | C66: Russ Wild | D66: 45350 | E66: 2311 | F66: 2308-01 | G66: =VLOOKUP(F66,'Accident & Incident Detail'!$D$3:$E$165,2,FALSE) -> #N/A | H66: 2023/2024-64 | I66: The driver should receive an additional covert ride check,, during low rail adhesion conditions to ensure his driving style is adjusted accordingly to mitigate any safety issues which may arise | J66: CS | K66: Russ Wild, Duty Manager | L66: CS | M66: =IF(D66="","",D66+28) -> 45378 | N66: =IF(D66="",3,IF(M66<$A$2,1,0)) -> 1 | O66: 45350 | Q66: Email from DM stating when ride check was completed
A67: =IF(O67>1,"Closed",IF(N67=1,"Overdue",IF(N67=3,"","Open"))) -> Closed | B67: Level 2 Investigation Recommendation | C67: Russ Wild | D67: 45350 | E67: 2311 | F67: 2308-01 | G67: =VLOOKUP(F67,'Accident & Incident Detail'!$D$3:$E$165,2,FALSE) -> #N/A | H67: 2023/2024-66 | I67: Consider additional measures on approach to Meadow Street such as lowering the speed limit during times of low rail adhesion conditions | J67: SAFE | K67: Josh Keeling, Safety Manager | L67: SAFE | M67: =IF(D67="","",D67+28) -> 45378 | N67: =IF(D67="",3,IF(M67<$A$2,1,0)) -> 1 | O67: 45680 | Q67: Consideration of low rail adhesion hot spots to be identified with signage
A68: =IF(O68>1,"Closed",IF(N68=1,"Overdue",IF(N68=3,"","Open"))) -> Closed | B68: Safety Inspection Action | C68: Andy Buckley | D68: 45355 | E68: 2312 | G68: =VLOOKUP(F68,'Accident & Incident Detail'!$D$3:$E$165,2,FALSE) -> #N/A | H68: 2023/2024-60 | I68: Gary Seaborn has been actioned with looking into decanted toxic substances into unlabelled vessels of various sorts after been pulled about it this morning by another colleague. Suggest we give it 2wks to be fully rectified. | J68: RSM | K68: Gary Seaborn RSM Production Manager | L68: ENG | M68: =IF(D68="","",D68+28) -> 45383 | N68: =IF(D68="",3,IF(M68<$A$2,1,0)) -> 1 | O68: 45412
A69: =IF(O69>1,"Closed",IF(N69=1,"Overdue",IF(N69=3,"","Open"))) -> Closed | B69: Safety Inspection Action | C69: Andy Buckley | D69: 45355 | E69: 2312 | G69: =VLOOKUP(F69,'Accident & Incident Detail'!$D$3:$E$165,2,FALSE) -> #N/A | H69: 2023/2024-61 | I69: Any ladders used in the workshop by RSM to have rubber feet fitted or replaced with insulated of the same type action within one month | J69: RSM | K69: Gary Seaborn RSM Production Manager | L69: ENG | M69: =IF(D69="","",D69+28) -> 45383 | N69: =IF(D69="",3,IF(M69<$A$2,1,0)) -> 1 | O69: 45902 | Q69: 11/12/2024 Item ongoing
A70: =IF(O70>1,"Closed",IF(N70=1,"Overdue",IF(N70=3,"","Open"))) -> Closed | B70: Safety Inspection Action | C70: Andy Buckley | D70: 45355 | E70: 2312 | G70: =VLOOKUP(F70,'Accident & Incident Detail'!$D$3:$E$165,2,FALSE) -> #N/A | H70: 2023/2024-62 | I70: Clear Moss along side of old paint shed and around to the back upto fire escape and if possible treat on more regular basis.(reported anonymously by colleague), action within one month, | J70: FACILITIES | K70: Mark Blackwell Cleaning Manager | L70: ENG | M70: =IF(D70="","",D70+28) -> 45383 | N70: =IF(D70="",3,IF(M70<$A$2,1,0)) -> 1 | O70: 45368
A71: =IF(O71>1,"Closed",IF(N71=1,"Overdue",IF(N71=3,"","Open"))) -> Closed | B71: Safety Inspection Action | C71: Andy Buckley | D71: 45355 | E71: 2312 | G71: =VLOOKUP(F71,'Accident & Incident Detail'!$D$3:$E$165,2,FALSE) -> #N/A | H71: 2023/2024-63 | I71: Fit vent covers either side of hole for old flue at rear of old paint shed, action within fortnight, | J71: FACILITIES | K71: Mark Blackwell Cleaning Manager | L71: ENG | M71: =IF(D71="","",D71+28) -> 45383 | N71: =IF(D71="",3,IF(M71<$A$2,1,0)) -> 1 | O71: 45376
A72: =IF(O72>1,"Closed",IF(N72=1,"Overdue",IF(N72=3,"","Open"))) -> Closed | B72: BOSRIA Action | C72: Darren Justice | D72: 45358 | E72: 2312 | G72: =VLOOKUP(F72,'Accident & Incident Detail'!$D$3:$E$165,2,FALSE) -> #N/A | H72: 2023/2024-71 | I72: Spllliages on corridor and stairwells not getting wiped up someone will get hurt | J72: SAFE | K72: Andy Buckley, Safety Officer | L72: SAFE | M72: =IF(D72="","",D72+28) -> 45386 | N72: =IF(D72="",3,IF(M72<$A$2,1,0)) -> 1 | O72: 45366 | Q72: Comms displayed on BLINK
A73: =IF(O73>1,"Closed",IF(N73=1,"Overdue",IF(N73=3,"","Open"))) -> Closed | B73: BOSRIA Action | C73: Darren Justice | D73: 45358 | E73: 2312 | G73: =VLOOKUP(F73,'Accident & Incident Detail'!$D$3:$E$165,2,FALSE) -> #N/A | H73: 2023/2024-72 | I73: Fire door blocked (Castle House) bloked in quiet room | J73: SAFE | K73: Andy Buckley, Safety Officer | L73: SAFE | M73: =IF(D73="","",D73+28) -> 45386 | N73: =IF(D73="",3,IF(M73<$A$2,1,0)) -> 1 | O73: 45362 | Q73: Door checked by Abuckfield on 11/03/2024
A74: =IF(O74>1,"Closed",IF(N74=1,"Overdue",IF(N74=3,"","Open"))) -> Closed | B74: BOSRIA Action | C74: Anon | D74: 45359 | E74: 2312 | G74: =VLOOKUP(F74,'Accident & Incident Detail'!$D$3:$E$165,2,FALSE) -> #N/A | H74: 2023/2024-67 | I74: Two near misses of people walking through long corridor doors this week, could the doors without quarter glass be changed to ones with so can see through like the singular door openings?- Change doors | J74: SAFE | K74: Josh Keeling, Safety Manager | L74: SAFE | M74: =IF(D74="","",D74+28) -> 45387 | N74: =IF(D74="",3,IF(M74<$A$2,1,0)) -> 1 | O74: 45387 | Q74: DorGards have been fitted to the doors to hold the doors open - the Dor Gards are activated by the fire alarm and proceed to close
A75: =IF(O75>1,"Closed",IF(N75=1,"Overdue",IF(N75=3,"","Open"))) -> Closed | B75: BOSRIA Action | C75: Gary Seaborn | D75: 45364 | E75: 2312 | G75: =VLOOKUP(F75,'Accident & Incident Detail'!$D$3:$E$165,2,FALSE) -> #N/A | H75: 2023/2024-73 | I75: One of the double doors into the pneumatic room has been strained and requires attention - Pneumatic room 10 road east | J75: FACILITIES | K75: Mark Blackwell Cleaning Manager | L75: ENG | M75: =IF(D75="","",D75+28) -> 45392 | N75: =IF(D75="",3,IF(M75<$A$2,1,0)) -> 1 | O75: 45415 | Q75: This door had been continuously wedged open by a tyre block causing the hinge to strain - this hinge has now been replaced and toghtened with no further issues
A76: =IF(O76>1,"Closed",IF(N76=1,"Overdue",IF(N76=3,"","Open"))) -> Closed | B76: BOSRIA Action | C76: Gary Seaborn | D76: 45364 | E76: 2312 | G76: =VLOOKUP(F76,'Accident & Incident Detail'!$D$3:$E$165,2,FALSE) -> #N/A | H76: 2023/2024-74 | I76: Access/egress door opposite the bogie section does not close properly it has to be pulled firmly - RSM dept road 10 west | J76: FACILITIES | K76: Mark Blackwell Cleaning Manager | L76: ENG | M76: =IF(D76="","",D76+28) -> 45392 | N76: =IF(D76="",3,IF(M76<$A$2,1,0)) -> 1 | O76: 45415 | Q76: The door has been checked and no issues were found - will continue to monitor
A77: =IF(O77>1,"Closed",IF(N77=1,"Overdue",IF(N77=3,"","Open"))) -> Closed | B77: SAFE | C77: Andy Buckley | D77: 45364 | E77: 2312 | G77: =VLOOKUP(F77,'Accident & Incident Detail'!$D$3:$E$165,2,FALSE) -> #N/A | H77: 2023/2024-69 | I77: New Risk Assessment required on ORR style template regarding Bogies. | J77: RSM | K77: Gary Seaborn RSM Production Manager | L77: ENG | M77: =IF(D77="","",D77+28) -> 45392 | N77: =IF(D77="",3,IF(M77<$A$2,1,0)) -> 1 | O77: 45383
A78: =IF(O78>1,"Closed",IF(N78=1,"Overdue",IF(N78=3,"","Open"))) -> Closed | B78: SAFE | C78: Andy Buckley | D78: 45365 | E78: 2312 | G78: =VLOOKUP(F78,'Accident & Incident Detail'!$D$3:$E$165,2,FALSE) -> #N/A | H78: 2023/2024-68 | I78: SAFETY/ JK- to review COSHH risk assessment for SYPOL implementation etc | J78: SAFE | K78: Josh Keeling, Safety Manager | L78: SAFE | M78: =IF(D78="","",D78+28) -> 45393 | N78: =IF(D78="",3,IF(M78<$A$2,1,0)) -> 1 | O78: 45534
A79: =IF(O79>1,"Closed",IF(N79=1,"Overdue",IF(N79=3,"","Open"))) -> Closed | B79: Level 1 Investigation Recommendation | C79: Nina Wybrant | D79: 45370 | E79: 2311 | F79: 2311-67 | G79: =VLOOKUP(F79,'Accident & Incident Detail'!$D$3:$E$1154,2,FALSE) -> Tramstop Overrun | H79: 2023/2024-173 | I79: PDDP | J79: CS | K79: Rachel Bridges, Duty Manager | L79: CS | M79: =IF(D79="","",D79+28) -> 45398 | N79: =IF(D79="",3,IF(M79<$A$2,1,0)) -> 1 | O79: 45370
A80: =IF(O80>1,"Closed",IF(N80=1,"Overdue",IF(N80=3,"","Open"))) -> Closed | B80: Level 1 Investigation Recommendation | C80: Nina Wybrant | D80: 45370 | E80: 2311 | F80: 2311-67 | G80: =VLOOKUP(F80,'Accident & Incident Detail'!$D$3:$E$1154,2,FALSE) -> Tramstop Overrun | H80: 2023/2024-174 | I80: Note to file | J80: CS | K80: Rachel Bridges, Duty Manager | L80: CS | M80: =IF(D80="","",D80+28) -> 45398 | N80: =IF(D80="",3,IF(M80<$A$2,1,0)) -> 1 | O80: 45370
A81: =IF(O81>1,"Closed",IF(N81=1,"Overdue",IF(N81=3,"","Open"))) -> Closed | B81: Level 1 Investigation Recommendation | C81: Nina Wybrant | D81: 45370 | E81: 2311 | F81: 2311-67 | G81: =VLOOKUP(F81,'Accident & Incident Detail'!$D$3:$E$1154,2,FALSE) -> Tramstop Overrun | H81: 2023/2024-175 | I81: Mentoring | J81: TRAINING | K81: Training Department | L81: CS | M81: =IF(D81="","",D81+28) -> 45398 | N81: =IF(D81="",3,IF(M81<$A$2,1,0)) -> 1 | O81: 45428
A82: =IF(O82>1,"Closed",IF(N82=1,"Overdue",IF(N82=3,"","Open"))) -> Closed | B82: Level 2 Investigation Recommendation | C82: Matt Wright | D82: 45375 | E82: 2402 | F82: 2312-41 | G82: =VLOOKUP(F82,'Accident & Incident Detail'!$D$3:$E$1154,2,FALSE) -> Near Miss | H82: 2023/2024-153 | I82: Update of VMI to include check for elbow lift | J82: RSM | K82: Matt Wright - RSM Competency Co-ordinator | L82: ENG | M82: =IF(D82="","",D82+28) -> 45403 | N82: =IF(D82="",3,IF(M82<$A$2,1,0)) -> 1 | O82: 45443
A83: =IF(O83>1,"Closed",IF(N83=1,"Overdue",IF(N83=3,"","Open"))) -> Closed | B83: Level 2 Investigation Recommendation | C83: Matt Wright | D83: 45375 | E83: 2402 | F83: 2312-41 | G83: =VLOOKUP(F83,'Accident & Incident Detail'!$D$3:$E$1154,2,FALSE) -> Near Miss | H83: 2023/2024-154 | I83: Toolbox talk on how to check elbow tension | J83: TRAINING | K83: Training Department | L83: CS | M83: =IF(D83="","",D83+28) -> 45403 | N83: =IF(D83="",3,IF(M83<$A$2,1,0)) -> 1 | O83: 45443
A84: =IF(O84>1,"Closed",IF(N84=1,"Overdue",IF(N84=3,"","Open"))) -> Closed | B84: Level 2 Investigation Recommendation | C84: Matt Wright | D84: 45375 | E84: 2402 | F84: 2312-41 | G84: =VLOOKUP(F84,'Accident & Incident Detail'!$D$3:$E$1154,2,FALSE) -> Near Miss | H84: 2023/2024-155 | I84: Discussion with person who originally set elbow height | J84: TRAINING | K84: Training Department | L84: CS | M84: =IF(D84="","",D84+28) -> 45403 | N84: =IF(D84="",3,IF(M84<$A$2,1,0)) -> 1 | O84: 45443
A85: =IF(O85>1,"Closed",IF(N85=1,"Overdue",IF(N85=3,"","Open"))) -> Closed | B85: Internal Audit Corrective Action | C85: Andy Buckley | D85: 45376 | E85: 2401 | G85: =VLOOKUP(F85,'Accident & Incident Detail'!$D$3:$E$165,2,FALSE) -> #N/A | H85: 2023/2024-75 | I85: Carry out regular monitoring of HAVS for relevant employees and equipment use and record/ act on results as required internally and consider implementation by an external medical surveillance provider for coverage. | J85: SAFE | K85: Josh Keeling, Safety Manager | L85: SAFE | M85: =IF(D85="","",D85+28) -> 45404 | N85: =IF(D85="",3,IF(M85<$A$2,1,0)) -> 1 | O85: 45635 | Q85: Confirmation from Jk that Iptima health will be staring staff HS in January 2025 -covers monitoring
A86: =IF(O86>1,"Closed",IF(N86=1,"Overdue",IF(N86=3,"","Open"))) -> Closed | B86: Internal Audit Corrective Action | C86: Andy Buckley | D86: 45376 | E86: 2401 | G86: =VLOOKUP(F86,'Accident & Incident Detail'!$D$3:$E$165,2,FALSE) -> #N/A | H86: 2023/2024-76 | I86: Erect temporary screens around the working zone to control arisings that may affect others. | J86: RSM | K86: Paul Holdsworth - Asst RSM Manager | L86: ENG | M86: =IF(D86="","",D86+28) -> 45404 | N86: =IF(D86="",3,IF(L86<$A$2,1,0)) -> 0 | O86: 46066
A87: =IF(O87>1,"Closed",IF(N87=1,"Overdue",IF(N87=3,"","Open"))) -> Closed | B87: Internal Audit Corrective Action | C87: Andy Buckley | D87: 45376 | E87: 2401 | G87: =VLOOKUP(F87,'Accident & Incident Detail'!$D$3:$E$165,2,FALSE) -> #N/A | H87: 2023/2024-77 | I87: Pits to be barriered off when no tram on using twin belt yellow/black retractable barriers on mobile weighted stands. | J87: RSM | K87: Gary Seaborn RSM Production Manager | L87: ENG | M87: 45473 | N87: =IF(D87="",3,IF(M87<$A$2,1,0)) -> 1 | O87: 45555 | Q87: 20/06/2024 - Update from Abuckely - I have chased these items up with RSM as requested, I have assisted with measuring and compiling requirements for the pit barriers and left with Gary today.(Approx cost £15k for portable HSE approved Pit Tensator barriers covering approx 400m) GSeaborn is gathering quotes. Date on this action has been extened to accomadate this workstream
A88: =IF(O88>1,"Closed",IF(N88=1,"Overdue",IF(N88=3,"","Open"))) -> Closed | B88: Internal Audit Corrective Action | C88: Andy Buckley | D88: 45376 | E88: 2401 | G88: =VLOOKUP(F88,'Accident & Incident Detail'!$D$3:$E$165,2,FALSE) -> #N/A | H88: 2023/2024-78 | I88: Ensure SSOW/ Method Statement(MA) for relevant activity states no traversing by any operatives under suspended loads and correct PPE worn at all times in the blue zone regardless of activity by all including but not limited to safety boots, orange hi vis vests and safety helmets etc | J88: RSM | K88: Gary Seaborn RSM Production Manager | L88: ENG | M88: =IF(D88="","",D88+28) -> 45404 | N88: =IF(D88="",3,IF(M88<$A$2,1,0)) -> 1 | O88: 46042 | Q88: 08/12/2025 all Gary Seaborns actions were reassigned to Paul Holdsworth under instruction from Josh Keeling - 16/12/2025 email from Josh to Paul - Happy to authorise an extension for Paul to review and come back to us on achievable timescales given the circumstances. 20/01/2026 - Action closed
A89: =IF(O89>1,"Closed",IF(N89=1,"Overdue",IF(N89=3,"","Open"))) -> Closed | B89: Internal Audit Corrective Action | C89: Andy Buckley | D89: 45376 | E89: 2401 | G89: =VLOOKUP(F89,'Accident & Incident Detail'!$D$3:$E$165,2,FALSE) -> #N/A | H89: 2023/2024-79 | I89: Ensure RA/SSOW/MS in place on new required template for the sole activity of jacking vehicles and then send for review. (Existing in place) | J89: RSM | K89: Gary Seaborn RSM Production Manager | L89: ENG | M89: =IF(D89="","",D89+28) -> 45404 | N89: =IF(D89="",3,IF(M89<$A$2,1,0)) -> 1 | O89: 46042 | Q89: 08/12/2025 all Gary Seaborns actions were reassigned to Paul Holdsworth under instruction from Josh Keeling - 16/12/2025 email from Josh to Paul - Happy to authorise an extension for Paul to review and come back to us on achievable timescales given the circumstances. 20/01/2026 - Action closed
A90: =IF(O90>1,"Closed",IF(N90=1,"Overdue",IF(N90=3,"","Open"))) -> Closed | B90: Internal Audit Corrective Action | C90: Andy Buckley | D90: 45376 | E90: 2401 | G90: =VLOOKUP(F90,'Accident & Incident Detail'!$D$3:$E$165,2,FALSE) -> #N/A | H90: 2023/2024-80 | I90: Ensure regular and recorded cleaning regime in place following required RA/SSOW/MS's etc. and records shared with relevant departments of this been carried out. | J90: RSM | K90: Gary Seaborn RSM Production Manager | L90: ENG | M90: =IF(D90="","",D90+28) -> 45404 | N90: =IF(D90="",3,IF(M90<$A$2,1,0)) -> 1 | O90: 46042 | Q90: 08/12/2025 all Gary Seaborns actions were reassigned to Paul Holdsworth under instruction from Josh Keeling - 16/12/2025 email from Josh to Paul - Happy to authorise an extension for Paul to review and come back to us on achievable timescales given the circumstances. 20/01/2026 Action closed
A91: =IF(O91>1,"Closed",IF(N91=1,"Overdue",IF(N91=3,"","Open"))) -> Open | B91: Internal Audit Corrective Action | C91: Andy Buckley | D91: 45376 | E91: 2401 | G91: =VLOOKUP(F91,'Accident & Incident Detail'!$D$3:$E$165,2,FALSE) -> #N/A | H91: 2023/2024-81 | I91: Ensure creation of RA/SSOW/MS's and then followed for lone working and regular supervision at appropriate intervals is carried out. Each shift should be covered by a named First Aid person working within that area. Ensure all staff are aware of any emergency procedures etc. | J91: RSM | K91: Paul Holdsworth - Asst RSM Manager | L91: ENG | M91: 46066 | N91: =IF(D91="",3,IF(M91<$A$2,1,0)) -> 0 | Q91: 08/12/2025 all Gary Seaborns actions were reassigned to Paul Holdsworth under instruction from Josh Keeling - 16/12/2025 email from Josh to Paul - Happy to authorise an extension for Paul to review and come back to us on achievable timescales given the circumstances. 20/01/2026 - 30 Days extension granted to allow time for tool box to be deliev
A92: =IF(O92>1,"Closed",IF(N92=1,"Overdue",IF(N92=3,"","Open"))) -> Closed | B92: BOSRIA Action | C92: Nikolas Dobbs | D92: 45378 | E92: 2401 | G92: =VLOOKUP(F92,'Accident & Incident Detail'!$D$3:$E$165,2,FALSE) -> #N/A | H92: 2023/2024-83 | I92: Display link signage coordinator not clipped on in MEWP basket - positive safety conversatin held - later day checked and compliant | J92: INFRA | K92: Nikolas Dobbs Head of Engineering | L92: ENG | M92: =IF(D92="","",D92+28) -> 45406 | N92: =IF(D92="",3,IF(M92<$A$2,1,0)) -> 1 | O92: 45378
A93: =IF(O93>1,"Closed",IF(N93=1,"Overdue",IF(N93=3,"","Open"))) -> Closed | B93: BOSRIA Action | C93: Roger Coates | D93: 45385 | E93: 2401 | G93: =VLOOKUP(F93,'Accident & Incident Detail'!$D$3:$E$165,2,FALSE) -> #N/A | H93: 2023/2024-90 | I93: The white lines in depot east are in need of repainting . They’re extremely difficult to see while reverse parking - Can we get the white lines repainted in depot east car park, early morning and late nights it’s extremely difficult to see them while reverse parking even more so in wet conditions | J93: FACILITIES | K93: Mark Blackwell Cleaning Manager | L93: ENG | M93: =IF(D93="","",D93+28) -> 45413 | N93: =IF(D93="",3,IF(M93<$A$2,1,0)) -> 1 | O93: 45415 | Q93: Paul, if you could let us know that you have reviewed these by Jan 16th, we can then agree some new deadlines for these outstanding actions, many thanks. Also, any actions that you need wider context for, just let us know and Kelly can go over where they originated from with you.
A94: =IF(O94>1,"Closed",IF(N94=1,"Overdue",IF(N94=3,"","Open"))) -> Closed | B94: BOSRIA Action | C94: Sean Cuckson | D94: 45385 | E94: 2401 | G94: =VLOOKUP(F94,'Accident & Incident Detail'!$D$3:$E$165,2,FALSE) -> #N/A | H94: 2023/2024-91 | I94: Segregated sections - If a tram stops suddenly, breaks down on the segregated sections of our system, there’s no way for the Network Coordinators to know how far behind a tram could be following behind and may not answer the radio call from the stationary tram in time to inform the tram behind. This could cause a potential tram on tram impact, for example if a tram stops prior to ValleyCentertaiment o/b, the tram behind is potentially doing 40mph, the line of sight is blocked by the trees. suggest Trams that stop on segregated sections should send an emergency call to inform the Network Coordinators sooner and avoid a potential Collision | J94: CS | K94: Sharon Galloway, Senior Customer Service Manager | L94: CS | M94: =IF(D94="","",D94+28) -> 45413 | N94: =IF(D94="",3,IF(M94<$A$2,1,0)) -> 1 | O94: 45400 | Q94: 18/04/2024 - have asked driver to be more specific with regard to location
A95: =IF(O95>1,"Closed",IF(N95=1,"Overdue",IF(N95=3,"","Open"))) -> Closed | B95: BOSRIA Action | C95: Danielle Willey | D95: 45385 | E95: 2401 | G95: =VLOOKUP(F95,'Accident & Incident Detail'!$D$3:$E$165,2,FALSE) -> #N/A | H95: 2023/2024-92 | I95: White Lane - Birley Lane - A few times last week I saw/reported to OCC birley school pupils walking on the segregated track between the Birley Lane stop and white lane/fox lane junction - I know it’s probably been done before but maybe the school can be contacted to reiterate safety around the tramway | J95: CS | K95: James Stewart, Head of Customer Services | L95: CS | M95: =IF(D95="","",D95+28) -> 45413 | N95: =IF(D95="",3,IF(M95<$A$2,1,0)) -> 1 | O95: 45397 | Q95: The school have been contacted and asked to remind pupils of the dangers and therefore ask them not to walk on track. Obviously we can't physically stop them but hopefully a reminder will help.
A96: =IF(O96>1,"Closed",IF(N96=1,"Overdue",IF(N96=3,"","Open"))) -> Closed | B96: Safety Concern Action | C96: Andy Buckley | D96: 45386 | E96: 2402 | G96: =VLOOKUP(F96,'Accident & Incident Detail'!$D$3:$E$165,2,FALSE) -> #N/A | H96: 2023/2024-93 | I96: Workshop Plant Room should be secure(ie door locked) at all times when not occupied for legal compliance including insurance. | J96: FACILITIES | K96: Mark Blackwell Cleaning Manager | L96: ENG | M96: =IF(D96="","",D96+28) -> 45414 | N96: =IF(D96="",3,IF(M96<$A$2,1,0)) -> 1 | O96: 45392
A97: =IF(O97>1,"Closed",IF(N97=1,"Overdue",IF(N97=3,"","Open"))) -> Open | B97: Safety Inspection Action | C97: Andy Buckley | D97: 45387 | E97: 2402 | G97: =VLOOKUP(F97,'Accident & Incident Detail'!$D$3:$E$165,2,FALSE) -> #N/A | H97: 2023/2024-94 | I97: Ensure assets/ equipment where required is ATEX rated to comply with DSEAR when undertaking any depot refurbishment project/ projects. To be reviewed or actioned by given date. Due date 04.04.26 | J97: SAFE | K97: Josh Keeling, Safety Manager | L97: SAFE | M97: 46116 | N97: =IF(D97="",3,IF(M97<$A$2,1,0)) -> 0
A98: =IF(O98>1,"Closed",IF(N98=1,"Overdue",IF(N98=3,"","Open"))) -> Closed | B98: BOSRIA Action | C98: Anom | D98: 45391 | E98: 2401 | G98: =VLOOKUP(F98,'Accident & Incident Detail'!$D$3:$E$165,2,FALSE) -> #N/A | H98: 2023/2024-98 | I98: Just a general comment as a conductor I find it difficult to manoeuvre sometimes due to how busy it gets, the narrower aisles on TT makes more side way movements and without the grab loops like you get on the older trams better for people my height I find it alot more difficult to get around whilst being stable and maintianing three points of contact - consider fitting grab loops to newer trams. | J98: RSM | K98: Gary Seaborn RSM Production Manager | L98: ENG | M98: =IF(D98="","",D98+28) -> 45419 | N98: =IF(D98="",3,IF(M98<$A$2,1,0)) -> 1 | O98: 45422 | Q98: Covered in safety reps meeting JK has TT comlplies construction and use regs
A99: =IF(O99>1,"Closed",IF(N99=1,"Overdue",IF(N99=3,"","Open"))) -> Closed | B99: Level 1 Investigation Recommendation | C99: Russ Wild | D99: 45391 | E99: 2402 | F99: 2312-40 | G99: =VLOOKUP(F99,'Accident & Incident Detail'!$D$3:$E$165,2,FALSE) -> #N/A | H99: 2023/2024-99 | I99: Driver to be issued Note to File for non reporting of incident | J99: CS | K99: Russ Wild, Duty Manager | L99: CS | M99: =IF(D99="","",D99+28) -> 45419 | N99: =IF(D99="",3,IF(M99<$A$2,1,0)) -> 1 | O99: 45390
A100: =IF(O100>1,"Closed",IF(N100=1,"Overdue",IF(N100=3,"","Open"))) -> Closed | B100: Level 1 Investigation Recommendation | C100: Russ Wild | D100: 45391 | E100: 2402 | F100: 2312-40 | G100: =VLOOKUP(F100,'Accident & Incident Detail'!$D$3:$E$165,2,FALSE) -> #N/A | H100: 2023/2024-100 | I100: Each team on infrastructure to have their own van deicated to the team & a van capable of the needs of the team - this negating the need tom catch a tram to a worksite - from our teams experience when on days dependant on what other teams are on days, on numerous occassions our team have to catch a tram to our worksite in addition if each team have a dedicated van they could carry spares on their van associated to their discipline | J100: CS | K100: Neill Barraclough Infrastructure Manager | L100: ENG | M100: =IF(D100="","",D100+28) -> 45419 | N100: =IF(D100="",3,IF(M100<$A$2,1,0)) -> 1 | O100: 24/02/205 | Q100: The new van fleet factored this into the design-making process, and we have expanded the number of vehicles. 24/02/2025 authorised to close WC
A101: =IF(O101>1,"Closed",IF(N101=1,"Overdue",IF(N101=3,"","Open"))) -> Closed | B101: Level 1 Investigation Recommendation | C101: Russ Wild | D101: 45391 | E101: 2402 | F101: 2312-40 | G101: =VLOOKUP(F101,'Accident & Incident Detail'!$D$3:$E$165,2,FALSE) -> #N/A | H101: 2023/2024-101 | I101: Trap and drag brief to be reissued as a timely reminder of the importance of final mirror checks | J101: CS | K101: Sharon Galloway, Senior Customer Service Manager | L101: CS | M101: =IF(D101="","",D101+28) -> 45419 | N101: =IF(D101="",3,IF(M101<$A$2,1,0)) -> 1 | O101: 45333
...

Sheet Accident & Incident Detail
A1: =TODAY() -> 46057
A2: Status | B2: Date | C2: Reporting Period | D2: Accident/ Incident Reference | E2: Incident | F2: Location | G2: Direction of Travel | H2: Tram | I2: Catergory | J2: Staff No | K2: Person Type | L2: Description of incident | M2: Total Number of days Lost | N2: RIDDOR/SMIS | O2: Initial Report Received? | P2: Type of investigation carried out | Q2: Investigating Manager | R2: Function if Staff Accident or Assault (CS or Eng) | S2: Investigation Due | T2: Investigation Completion date | U2: Immediate Cause | V2: Underlying Cause | W2: Driver Contributory Factor | X2: Recommendations Made? | Y2: Lan & Lon | Z2: Comments | AA2: Column1 | AB2: Claim received? | AC2: Citylink or Siemens
A3: =IF(T3>1,"Closed",IF(AA3=1,"Overdue",IF(AA3=3,"","Open"))) -> Closed | B3: 45293 | C3: 2309 | D3: 2309-46 | E3: Verbal Abuse | F3: Parkgate | H3: 205 | I3: Assaults | J3: 8501823 | K3: Staff | L3: 11:30 S GALLOWAY 2 02/01/2024 INCIDENT CONDUCTOR D.THOMPSON (8501823) DUTY R2 REPORTED ON HIS BREAK TO OCC, A VERBAL ALTERCATION / ABUSE FROM A PASSENGER BETWEEN PARKGATE AND ROTHERHAM CENTRAL FROM APPROX 09:30 ONBOARD TRAM 205. REPORT AND CCTV REQUESTED. DM R.BRIDGES INFORMED. | M3: 0 | N3: No | O3: Yes | P3: Assault | Q3: Andy Roberts | R3: CS | S3: =IF(B3="","",B3+28) -> 45321 | T3: 45313 | U3: Passenger swearing at conductor | V3: Malicious behaviour /attempt to fare evade | W3: No | X3: None | Z3: Incident was reported to OCC | AA3: =IF(B3="",3,IF(S3<$A$1,1,0)) -> 1 | AC3: =LEFT(H3,1) -> 2
A4: =IF(T4>1,"Closed",IF(AA4=1,"Overdue",IF(AA4=3,"","Open"))) -> Closed | B4: 45293 | C4: 2309 | D4: 2309-47 | E4: Threatening Behaviour | F4: University | H4: 118 | I4: Assaults | J4: 41395 | K4: Staff | L4: 16:05 J WILKS 479 02/01/2024 INCIDENT DRV C MORRISON (41395) REPORTS FROM T118 AT UOS THE CONDUCTOR HAS BEEN THREATENED BY A PASSENGER. DM R WILD AWARE CCTV AND REPORTS REQUESTED. EV/2024/00086 | M4: 0 | N4: No | O4: No | P4: Assault | Q4: Alan Barclay | R4: CS | S4: =IF(B4="","",B4+28) -> 45321 | T4: 45336 | U4: Passenger refusing to pay | V4: No means to pay | W4: No | X4: None | Y4: POINT (-1.4840641 53.3807511) | Z4: Conductor walked away driver reported the incident once aware | AA4: =IF(B4="",3,IF(S4<$A$1,1,0)) -> 1 | AC4: =LEFT(H4,1) -> 1
A5: =IF(T5>1,"Closed",IF(AA5=1,"Overdue",IF(AA5=3,"","Open"))) -> Closed | B5: 45293 | C5: 2309 | D5: 2309-48 | E5: Incorrect VIS | F5: Depot | I5: Operational | J5: 377 | L5: 18:53 J WILKS 479 02/01/2024 INCIDENT DRV D SIMPSON (377) WRONG CODE TO ENTER DEPOT. POINTS DW1 HAND OPERATED TO GET DETECTION. DW1 POINTS ALARM/FAIL INFRA TO ATTEND. EV/2024/00087 | M5: =IF(I5="Staff Accident","Entry Required",IF(I5="Assaults","Entry Required",0)) -> 0 | N5: No | O5: No | P5: Level 1 | Q5: Rachel Bridges | R5: CS | S5: =IF(B5="","",B5+28) -> 45321 | T5: 45307 | U5: Incorrect VIS code | V5: Driver error | W5: Yes | X5: None | Z5: The driver stopped and informed OCC | AA5: =IF(B5="",3,IF(S5<$A$1,1,0)) -> 1 | AC5: =LEFT(H5,1)
A6: =IF(T6>1,"Closed",IF(AA6=1,"Overdue",IF(AA6=3,"","Open"))) -> Closed | B6: 45294 | C6: 2309 | D6: 2309-49 | E6: Near Miss | F6: Moss Way | G6: I/B | H6: 108 | I6: Operational | J6: 8504143 | L6: 11:22 J LAVER 792 03/01/2024 INCIDENT DRV OF T108 J LEGGETT (8504143) REPORTED NEAR MISS MOW I/B CAR CAME THROUGH RED LIGHT (REG YR14 DCE) TRACK BRAKE APPLIED. NO INJURIES REPORTED AT THE TIME. CCTV, REPORT AND SIBAS REQUESTED TACT 147964. EV/2024/00088 | M6: =IF(I6="Staff Accident","Entry Required",IF(I6="Assaults","Entry Required",0)) -> 0 | N6: No | O6: Yes | P6: Level 1 | Q6: Alan Barclay | R6: CS | S6: =IF(B6="","",B6+28) -> 45322 | T6: 45407 | U6: Car going through a redlight | V6: Car driver not paying attention | W6: No | X6: None | Y6: POINT (-1.3626489 53.3421838) | Z6: Driver infomrc OOC of thr incident | AA6: =IF(B6="",3,IF(S6<$A$1,1,0)) -> 1 | AC6: =LEFT(H6,1) -> 1
A7: =IF(T7>1,"Closed",IF(AA7=1,"Overdue",IF(AA7=3,"","Open"))) -> Closed | B7: 45294 | C7: 2309 | D7: 2309-50 | E7: Anti -social behaviour | F7: Park Square | H7: 103 | I7: INFO ONLY | J7: 426 | K7: Staff | L7: 16:55 S COLLINS 406 03/01/2024 INCIDENT DRIVER D.WILLEY (426) ON T103 REPORTS HAVING A LASER PEN SHONE AT HER FROM THE FLATS AS SHE PASSED PARK SQUARE VIADUCT. NEXT TRAMS ADVISED BUT NO FURTHER INCIDENTS. EV/2024/00089 | M7: =IF(I7="Staff Accident","Entry Required",IF(I7="Assaults","Entry Required",0)) -> 0 | N7: No | O7: No | P7: Info only/SAFE | R7: 0 | S7: =IF(B7="","",B7+28) -> 45322 | T7: 45294 | AA7: =IF(B7="",3,IF(S7<$A$1,1,0)) -> 1 | AC7: =LEFT(H7,1) -> 1
A8: =IF(T8>1,"Closed",IF(AA8=1,"Overdue",IF(AA8=3,"","Open"))) -> Closed | B8: 45295 | C8: 2309 | D8: 2309-51 | E8: Near Miss | F8: Cathedral | G8: O/B | H8: 115 | I8: Operational | J8: 8504143 | L8: 07:45 S GALLOWAY 2 04/01/2024 INCIDENT DRIVER J.LEGGETT (8504143) TRAM 115 REPORTS A NEAR MISS WITH A CAR AS THE TRAM LEFT CATHEDRAL O/B. TRACK BRAKE APPLIED, NO INJURIES REPORTED. CCTV REQUESTED. EV/2024/00090 | M8: =IF(I8="Staff Accident","Entry Required",IF(I8="Assaults","Entry Required",0)) -> 0 | N8: No | O8: Yes | P8: Level 1 | Q8: Alan Barclay | R8: CS | S8: =IF(B8="","",B8+28) -> 45323 | T8: 45300 | U8: Car driver rushing | V8: Car driver not stopping and giving way | W8: No | X8: Yes | Y8: POINT (-1.4690354 53.3825278) | Z8: Driver informs OCC as soon as possible | AA8: =IF(B8="",3,IF(S8<$A$1,1,0)) -> 1 | AC8: =LEFT(H8,1) -> 1
